Workbook

Sheet ppal B
E1: t/c usd/eur | F1: =Hoja1!H8 -> 1.1716 | G1: t/c usd/zar | H1: =Hoja1!H15 -> 16.4854 | I1: t/c usd/brl | J1: =Hoja1!H7 -> 5.0295 | K1: EEM | L1: =+S22 -> 0 | N1: Rent Spy | O1: =+I11 -> 0
B2: INFORME FINANCIERO 2026-FONDO JEB | D2: =TODAY() -> 46125 | E2: t/c usd/clp | F2: =+Hoja1!H6 -> 898.375 | G2: AAPL | H2: =Hoja1!H13 -> 257.4 | I2: USO | J2: =+S14 -> 0 | K2: ILF | L2: =+S23 -> 0
G3: SPY | H3: =Hoja1!H12 -> 679.25 | I3: GLD | J3: =+S11 -> 0 | K3: EWW
C4: Resultados Realizados | D4: Comisión | E4: MTM USD | G4: Risk | I4: MX | J4: =+S12 -> 0
I5: GOOG | J5: =+S29 -> 0 | K5: $$USDJPY | L5: =Hoja1!H16 -> 159.565
B6: P&L Opciones ETF-CDF-NDF-CLP | C6: =+opete!I107 -> 117.32766 | I6: FXI | J6: =+S20 -> 0 | K6: $$MEXUSD | L6: =Hoja1!H14 -> 17.34315
B7: P&L ETF | C7: =+etf!K102 -> 0
B8: P&L t10y | C8: =+t10y!J87 -> -1875 | I8: =+C39 -> 11000.715 | K8: $$USDCLP | L8: =Hoja1!H6 -> 898.375 | N8: -360000
B9: P&L Comm | K9: $$audUSD | L9: =Hoja1!H10 -> 0.7067 | N9: 252000
B10: P&L NDF | C10: =NDF!I30 -> 28223.04 | I10: Rt | K10: $$EURUSD | L10: =Hoja1!H8 -> 1.1716 | N10: =+N9+N8 -> -108000
B11: CLP-UF | C11: =UF!I45 -> 0 | I11: 0 | K11: $$ZARUSD | L11: =Hoja1!H15 -> 16.4854
B12: Div-2026 | K12: $$MXNUSD | L12: =Hoja1!H14 -> 17.34315
I13: Vol | K13: Xau | L13: =Hoja1!$H$11 -> 4720.375
E14: MTM USD | F14: POS USD | G14: MTM Cierre | I14: 0.3 | K14: $$BRLUSD | L14: =Hoja1!H7 -> 5.0295
B15: MTM Comm
B16: MTM NDF clp | E16: =+NDF!I99 -> -44.652695 | F16: =+NDF!F99 -> 2000
B17: MTM NDF fx | E17: =+NDF!I151 -> -15420 | F17: =NDF!K151 -> 0 | I17: Hedge MXN | K17: =+NDF!F120+opete!#REF!+opete!#REF! -> #REF!
B18: MTM t10y | E18: =t10y!J48 -> 0 | F18: 0 | G18: =7%*0.05*F18*-1*3 -> 0 | I18: Hedge BRL | K18: =+NDF!F112+opete!#REF!+opete!#REF! -> #REF!
B19: MTM ETF | E19: =etf!K44 -> 0 | F19: =etf!M44 -> 0 | I19: Hedge EUR | K19: =+NDF!F142+opete!#REF!+opete!#REF! -> #REF!
B20: Primas Op clp/usd | I20: Hedge ZAR | K20: =+NDF!F127+opete!#REF!+opete!#REF! -> #REF!
B21: MTM CLP-UF | E21: =UF!I26 -> 0 | F21: =+opete!#REF!+opete!#REF! -> #REF! | I21: Hedge aud/USD | K21: =+NDF!F151+opete!#REF!+opete!#REF! -> #REF!
B22: MTM Op ETF-CDF-NDF-CLP | E22: =+opete!I371 -> 0 | G22: =+opete!#REF! -> #REF! | I22: Hedge aud/JPY
B23: Pos.Neta USD clp | F23: =+F21+F16+F17 -> #REF! | I23: Hedge AUDEUR
B24: Pos.Neta USD TOTAL | D24: Pos USD Tot | E24: =SUM(E15:E23) -> -15464.653 | G24: =+opete!#REF! -> #REF! | I24: Hedge SPY | K24: =+etf!M29+etf!M38+etf!M40 -> 0
B25: Total USD (neto com) | C25: =SUM(C5:C14)+D25 -> 26465.367 | D25: =SUM(D6:D10) -> 0 | I25: Hedge FXI | K25: =+etf!#REF!+opete!#REF! -> #REF!
I26: Hedge MDB
I27: Hedge GOOG | K27: =+etf!#REF!+opete!#REF! -> #REF!
B28: Total USD | C28: =+C25 -> 26465.367 | I28: Hedge GLD | K28: =opete!#REF!+NDF!K160+etf!M14+etf!M15+etf!M16+etf!M17+etf!M18 -> #REF!
I29: Hedge USO | K29: =+etf!#REF!+opete!#REF! -> #REF!
I30: Hedge CRSP
I31: Hedge ETF | K31: =+etf!M44-opete!#REF! -> #REF!
E32: MTM total | F32: Plazo Prom | G32: =+G22-E22 -> #REF!
B33: Total P&L Hedge Fund | C33: =SUM(C28:C32) -> 26465.367 | E33: =SUM(E15:E23) -> -15464.653 | F33: =+opete!N371 -> 211.19802
E35: Stress
B36: Gastos Adm USD | C36: 0
B39: USD TOTAL | C39: =SUM(C33:C37)+E33 -> 11000.715 | D39: Retorno Mes | E39: =+C39/7000000 -> 0.0015715307
B45: FONDO JEB -2026
B48: Año | C48: Utilidad USD | D48: Fondos Util
C49: =+C39 -> 11000.715
B53: Total Resultado USD | C53: =SUM(C49:C52) -> 11000.715 | D53: =+opete!#REF! -> #REF!
B54: Promedio P&L Mes | C54: =+C53/12 -> 916.72622
B56: Retorno Año (base 360) | D56: =+C53/D53 -> #REF!
J57: V

Sheet NDF
F1: MONEDAS
A5: REALIZADAS
A8: Fecha Aper | B8: Contraparte | C8: Fecha cierre | D8: ticker | E8: País | F8: Monto | G8: Precio Inicial | H8: Precio Cierre | I8: MTM | J8: Rent | K8: Garantía | L8: Plazo | M8: Fix | N8: Settelment
A9: 46003 | B9: HSBC | D9: USDCLP | E9: CHILE | F9: -500 | G9: 909.01 | H9: 888.99 | I9: 11259.969 | J9: -0.02202396 | K9: 500000 | L9: -7 | M9: 46027 | N9: 46028
A10: 46003 | B10: HSBC | D10: USDCLP | E10: CHILE | F10: -500 | G10: 909.08 | H10: 888.99 | I10: 11299.34 | J10: -0.022099265 | K10: 500000 | L10: -7 | M10: 46027 | N10: 46028
A11: 46006 | B11: HSBC | D11: USDCLP | E11: CHILE | F11: -500 | G11: 911.79 | H11: 888.99 | I11: 12823.541 | J11: -0.025005758 | K11: 500000 | L11: -7 | M11: 46027 | N11: 46028
A12: 46006 | B12: HSBC | D12: USDCLP | E12: CHILE | F12: -500 | G12: 905.86 | H12: 888.99 | I12: 9488.2957 | J12: -0.018623187 | K12: 500000 | L12: -7 | M12: 46027 | N12: 46028
A13: 46009 | B13: HSBC | D13: USDCLP | E13: CHILE | F13: -500 | G13: 912.81 | H13: 888.99 | I13: 13397.226 | J13: -0.026095244 | K13: 500000 | L13: -7 | M13: 46027 | N13: 46028
A14: 46009 | B14: HSBC | D14: USDCLP | E14: CHILE | F14: 500 | G14: 911.15 | H14: 888.99 | I14: -12463.582 | J14: -0.024320913 | K14: 500000 | L14: -7 | M14: 46027 | N14: 46028
A15: 46013 | B15: HSBC | D15: USDCLP | E15: CHILE | F15: 500 | G15: 906.81 | H15: 888.99 | I15: -10022.61 | J15: -0.019651305 | K15: 500000 | L15: -7 | M15: 46027 | N15: 46028
A16: 46013 | B16: HSBC | D16: USDCLP | E16: CHILE | F16: 500 | G16: 906.56 | H16: 888.99 | I16: -9882.0009 | J16: -0.019380957 | K16: 500000 | L16: -7 | M16: 46027 | N16: 46028
A17: 46013 | B17: HSBC | D17: USDCLP | E17: CHILE | F17: 500 | G17: 905.86 | H17: 888.99 | I17: -9488.2957 | J17: -0.018623187 | K17: 500000 | L17: -7 | M17: 46027 | N17: 46028
A18: 46015 | B18: HSBC | D18: USDCLP | E18: CHILE | F18: -500 | G18: 905.66 | H18: 888.99 | I18: 9375.8085 | J18: -0.018406466 | K18: 500000 | L18: -7 | M18: 46027 | N18: 46028
A19: 46015 | B19: HSBC | D19: USDCLP | E19: CHILE | F19: -500 | G19: 904.13 | H19: 888.99 | I19: 8515.2814 | J19: -0.01674538 | K19: 500000 | L19: -7 | M19: 46027 | N19: 46028
A20: 46024 | B20: HSBC | D20: USDCLP | E20: CHILE | F20: 500 | G20: 899.8 | H20: 888.99 | I20: -6079.9334 | J20: -0.012013781 | K20: 500000 | L20: -7 | M20: 46027 | N20: 46028
I30: 28223.04
H31: SAXO | I31: 0
H32: SCHWAB | I32: 0
H33: CHILE | I33: 0
H34: UBS | I34: 0
H35: SB | I35: 0
A36: TRADING
A39: FECHA | B39: Contraparte | C39: Pos | D39: ticker | E39: País | F39: Monto | G39: Precio Inicial | H39: Precio Cierre | I39: MTM | J39: Rent | K39: Garantía | L39: Plazo | M39: Fix/Exp | N39: Val Date/Settlement
D40: USDCLP | E40: CHILE | H40: 898.49 | I40: 0 | K40: 0 | O40: 0
A41: 46097 | B41: BANCO DE TALCA | D41: USDCLP | E41: CHILE | F41: 1000 | G41: 917.59 | H41: 898.49 | I41: -21.257888 | J41: -0.020815397 | K41: 1000 | L41: -20 | M41: 46105 | N41: 46106 | O41: Vcto x Ocurrir
A42: 46097 | B42: BANCO DE TALCA | D42: USDCLP | E42: CHILE | F42: 1000 | G42: 916.24 | H42: 898.49 | I42: -19.755367 | J42: -0.019372653 | K42: 1000 | L42: -20 | M42: 46105 | N42: 46106 | O42: Vcto x Ocurrir
A43: 46097 | B43: BANCO DE TALCA | D43: USDCLP | E43: CHILE | F43: -500 | G43: 910.73 | H43: 898.49 | I43: 6.8114281 | J43: -0.013439768 | K43: 500 | L43: -20 | M43: 46105 | N43: 46106 | O43: Vcto x Ocurrir
A44: 46097 | B44: BANCO DE TALCA | D44: USDCLP | E44: CHILE | F44: 500 | G44: 908.67 | H44: 898.49 | I44: -5.6650603 | J44: -0.011203187 | K44: 500 | L44: -20 | M44: 46105 | N44: 46106 | O44: Vcto x Ocurrir
A45: 46097 | B45: BANCO DE TALCA | D45: USDCLP | E45: CHILE | F45: -500 | G45: 905.86 | H45: 898.49 | I45: 4.1013256 | J45: -0.008135915 | K45: 500 | L45: -20 | M45: 46105 | N45: 46106 | O45: Vcto x Ocurrir
A46: 46097 | B46: BANCO DE TALCA | D46: USDCLP | E46: CHILE | F46: -500 | G46: 905.86 | H46: 898.49 | I46: 4.1013256 | J46: -0.008135915 | K46: 500 | L46: -20 | M46: 46105 | N46: 46106 | O46: Vcto x Ocurrir
A47: 46097 | B47: BANCO DE TALCA | D47: USDCLP | E47: CHILE | F47: 500 | G47: 909.5 | H47: 898.49 | I47: -6.1269463 | J47: -0.012105553 | K47: 500 | L47: -20 | M47: 46105 | N47: 46106 | O47: Vcto x Ocurrir
A48: 46097 | B48: BANCO DE TALCA | D48: USDCLP | E48: CHILE | F48: 500 | G48: 910.82 | H48: 898.49 | I48: -6.8615121 | J48: -0.013537252 | K48: 500 | L48: -20 | M48: 46105 | N48: 46106 | O48: Vcto x Ocurrir
D49: USDCLP | E49: CHILE | H49: 898.49 | I49: 0 | K49: 0 | O49: 0
D50: USDCLP | E50: CHILE | H50: 898.49 | I50: 0 | K50: 0 | O50: 0
D51: USDCLP | E51: CHILE | H51: 898.49 | I51: 0 | K51: 0 | O51: 0
D52: USDCLP | E52: CHILE | H52: 898.49 | I52: 0 | K52: 0 | O52: 0
D53: USDCLP | E53: CHILE | H53: 898.49 | I53: 0 | K53: 0 | O53: 0
D54: USDCLP | E54: CHILE | H54: 898.49 | I54: 0 | K54: 0 | O54: 0
D55: USDCLP | E55: CHILE | H55: 898.49 | I55: 0 | K55: 0 | O55: 0
D56: USDCLP | E56: CHILE | H56: 898.49 | I56: 0 | K56: 0 | O56: 0
D57: USDCLP | E57: CHILE | H57: 898.49 | I57: 0 | K57: 0 | O57: 0
D58: USDCLP | E58: CHILE | H58: 898.49 | I58: 0 | K58: 0 | O58: 0
D59: USDCLP | E59: CHILE | H59: 898.49 | I59: 0 | K59: 0 | O59: 0
D60: USDCLP | E60: CHILE | H60: 898.49 | I60: 0 | K60: 0 | O60: 0
... D97: USDCLP | E97: CHILE | H97: 898.49 | I97: 0 | K97: 0 | O97: 0
F99: 2000 | H99: Resultado USD | I99: -44.652695
H101: HEDGE | I101: 0
H102: DB | I102: 0 | K102: 5 | L102: 0
H103: UBS | I103: 0 | K103: 7 | L103: 0
H104: SB | I104: 0 | K104: 8 | L104: 0
K105: 12 | L105: 0
K106: 13 | L106: 0
A108: FECHA | B108: Contraparte | C108: Pos | D108: ticker | E108: País | F108: Monto | G108: Precio Inicial | H108: Precio Cierre | I108: MTM | J108: Rent | K108: Garantía | L108: Plazo | M108: Fix | N108: Settlement
D109: USDBRL | E109: Brasil | H109: 5.0277 | I109: 0 | K109: 0 | O109: 0
D110: USDBRL | E110: Brasil | H110: 5.0277 | I110: 0 | K110: 0 | O110: 0
F112: 0 | I112: 0
A115: FECHA | B115: Contraparte | C115: Pos | D115: ticker | E115: País | F115: Monto | G115: Precio Inicial | H115: Precio Cierre | I115: MTM | J115: Rent | K115: Garantía | L115: Plazo | M115: Fix 12:30 | N115: Settlement
D116: USDMXN | E116: Mexico | H116: 17.34455 | I116: 0 | K116: 0 | O116: 0
D117: USDMXN | E117: Mexico | H117: 17.34455 | I117: 0 | K117: 0 | O117: 0
D118: USDMXN | E118: Mexico | H118: 17.34455 | I118: 0 | K118: 0 | O118: 0
D119: USDMXN | E119: Mexico | H119: 17.34455 | I119: 0 | K119: 0 | O119: 0
D120: OP | E120: #REF! | F120: 0 | I120: 0
D121: POS TOT | E121: #REF!
A123: FECHA | B123: Contraparte | C123: Pos | D123: ticker | E123: País | F123: Monto | G123: Precio Inicial | H123: Precio Cierre | I123: MTM | J123: Rent | K123: Garantía | L123: Plazo | M123: Settlement | O123: 0
D124: USDZAR | E124: Sudafrica | H124: 16.47525 | I124: 0 | K124: 0 | O124: 0
D125: USDZAR | E125: Sudafrica | H125: 16.47525 | I125: 0 | K125: 0 | O125: 0
D126: USDZAR | E126: Sudafrica | H126: 16.47525 | I126: 0 | K126: 0 | O126: 0
D127: OP | E127: #REF! | F127: 0 | I127: 0
D128: POS TOT | E128: #REF!
A130: FECHA | B130: Contraparte | C130: Pos | D130: ticker | E130: País | F130: Monto | G130: Precio Inicial | H130: Precio Cierre | I130: MTM | J130: Rent | K130: Garantía | L130: Plazo | M130: Fix | N130: Settlement | O130: 0
D131: EURUSD | E131: Europa | H131: 1.1717 | I131: 0 | K131: 0 | O131: 0
D132: EURUSD | E132: Europa | H132: 1.1717 | I132: 0 | K132: 0 | O132: 0
D133: EURUSD | E133: Europa | H133: 1.1717 | I133: 0 | K133: 0 | O133: 0
D134: EURUSD | E134: Europa | H134: 1.1717 | I134: 0 | K134: 0 | O134: 0
D135: EURUSD | E135: Europa | H135: 1.1717 | I135: 0 | K135: 0 | O135: 0
D136: EURUSD | E136: Europa | H136: 1.1717 | I136: 0 | K136: 0 | O136: 0
D137: EURUSD | E137: Europa | H137: 1.1717 | I137: 0 | K137: 0 | O137: 0
D138: EURUSD | E138: Europa | H138: 1.1717 | I138: 0 | K138: 0 | O138: 0
D139: EURUSD | E139: Europa | H139: 1.1717 | I139: 0 | K139: 0 | O139: 0
D140: EURUSD | E140: Europa | H140: 1.1717 | I140: 0 | K140: 0 | O140: 0
O141: 0
D142: op | E142: #REF! | F142: 0 | I142: 0
D143: POS TOT | E143: #REF!
A145: FECHA | B145: Contraparte | C145: Pos | D145: ticker | E145: País | F145: Monto | G145: Precio Inicial | H145: Precio Cierre | I145: MTM | J145: Rent | K145: Garantía | L145: Plazo | M145: Exp Date | O145: 0
A146: 46091 | B146: UBS | D146: AUDUSD | E146: Australia | F146: 1500000 | G146: 0.7158 | H146: 0.70675 | I146: -13575 | J146: -0.012643196 | K146: -1060125 | L146: -24 | M146: 46101 | O146: Vcto x Ocurrir
A147: 46097 | B147: UBS | D147: AUDUSD | E147: Australia | F147: -1500000 | G147: 0.70552 | H147: 0.70675 | I147: -1845 | J147: 0.0017433949 | K147: 1060125 | L147: -24 | M147: 46101 | O147: Vcto x Ocurrir
D148: AUDUSD | E148: Australia | H148: 0.70675 | I148: 0 | K148: 0 | O148: 0
D149: AUDUSD | E149: Australia | H149: 0.70675 | I149: 0 | K149: 0 | O149: 0
O150: 0
D151: op | E151: #REF! | F151: 0 | I151: -15420 | K151: 0
D152: POS TOT | E152: #REF!
A154: FECHA | B154: Contraparte | C154: Pos | D154: ticker | E154: País | F154: Monto | G154: Precio Inicial | H154: Precio Cierre | I154: MTM | J154: Rent | K154: Garantía | L154: Plazo | M154: Exp Date | N154: Settelment | O154: 0
D155: XAUUSD | E155: Oro | H155: 4720.535 | I155: 0 | K155: 0
D156: XAUUSD | E156: Oro | H156: 4720.535 | I156: 0 | K156: 0
D157: XAUUSD | E157: Oro | H157: 4720.535 | I157: 0 | K157: 0
D158: XAUUSD | E158: Oro | H158: 4720.535 | I158: 0 | K158: 0
K159: 0
D160: op | E160: #REF! | F160: 0 | I160: 0 | K160: 0
D161: POS TOT | E161: #REF!

Sheet opete
E1: OPCIONES
A5: REALIZADAS
A7: Estado | B7: Contraparte | C7: Pos | D7: ticker | E7: País | F7: Monto | G7: Precio Inicial | H7: Precio Cierre | I7: PRIMAS | J7: STRIKE | K7: Prob. Ocurrencia | L7: Exposición | M7: EXPIRACIÖN | N7: DIAS
A8: 45967 | B8: banco ohiggings | C8: VTA CALL | D8: USDCLP | E8: banco ohiggings | F8: -2000 | G8: 1170 | H8: 941.245 | I8: 2.32 | J8: 0.24303449 | L8: 10000 | M8: 46329 | N8: 363
A9: 45967 | B9: banco ohiggings | C9: VTA CALL | D9: USDCLP | E9: banco ohiggings | F9: -2000 | G9: 1180 | H9: 943.03 | I9: 2.12 | J9: 0.25128575 | L9: 10000 | M9: 46329 | N9: 362
A10: 45971 | B10: banco ohiggings | C10: VTA CALL | D10: USDCLP | E10: banco ohiggings | F10: -2000 | G10: 1160 | H10: 942 | I10: 2.32 | J10: 0.23142251 | L10: 10000 | M10: 46329 | N10: 358
A11: 45978 | B11: banco ohiggings | C11: VTA PUT | D11: USDCLP | E11: banco ohiggings | F11: -2000 | G11: 830 | H11: 920.69 | I11: 3.6 | J11: -0.09850221 | L11: 10000 | M11: 46329 | N11: 352
A12: 46002 | B12: PUP | C12: VTA PUT | D12: QQQ | E12: NASDAQ | F12: -8.5 | G12: 490 | H12: 624.13 | I12: 11.9674 | J12: -0.21490715 | L12: 20825 | M12: 46191 | N12: 189
A13: 46003 | B13: UBS | C13: VTA CALL | D13: AUDUSD | E13: Australia | F13: -1500 | G13: 0.725 | H13: 0.6646 | I13: 0 | J13: 0.090881733 | K13: 0.21216884 | L13: 4984.5 | M13: 46373 | N13: 370
A14: 46003 | B14: UBS | C14: VTA PUT | D14: AUDUSD | E14: Australia | F14: -1500 | G14: 0.615 | H14: 0.6646 | I14: 4.25 | J14: -0.074631357 | K14: 0.24931985 | L14: 4984.5 | M14: 46373 | N14: 370
A15: 46003 | B15: PUP | C15: VTA PUT | D15: SPY | E15: USA | F15: -7.5 | G15: 520 | H15: 683.855 | I15: 6.6594 | J15: -0.23960489 | K15: 0.17269283 | L15: 19500 | M15: 46191 | N15: 188
A16: 46030 | B16: PUP | C16: VTA PUT | D16: GS | E16: GoldmanSachs | F16: -6 | G16: 640 | H16: 937 | I16: 6.5154 | J16: =IF(G16="",0,G16/H16-1) -> -0.31696905 | K16: =IFERROR(#REF!,0) -> 0 | L16: 9.6 | M16: 46191 | N16: =IF(M16="","",M16-TODAY()) -> 66
A17: 46030 | B17: SSCH | C17: VTA PUT | D17: QQQ | E17: NASDAQ | F17: -8.5 | G17: 460 | H17: 621 | I17: 8.075 | J17: =IF(G17="",0,G17/H17-1) -> -0.25925926 | K17: =IFERROR(#REF!,0) -> 0 | L17: 9.775 | M17: 46191 | N17: =IF(M17="","",M17-TODAY()) -> 66
A18: 46034 | B18: PUP | C18: VTA PUT | D18: SPY | E18: USA | F18: -7.5 | G18: 525 | H18: 695.035 | I18: 4.6644 | J18: -0.24464236 | K18: 0.14226847 | L18: 19687.5 | M18: 46191 | N18: 157
A19: 46034 | B19: PUP | C19: VTA PUT | D19: AAPL | E19: AAPL | F19: -7.5 | G19: 190 | H19: 260.66 | I19: 2.0994 | J19: -0.23271695 | K19: 0.15071999 | L19: 7500 | M19: 46191 | N19: 157
A20: 46034 | B20: PUP | C20: VTA PUT | D20: MBbva | E20: MongoBbva | F20: -2 | G20: 280 | H20: 415.235 | I20: 4.5914 | J20: -0.32568305 | K20: 0.057191006 | L20: 2800 | M20: 46191 | N20: 156
A21: 46035 | B21: CS-K | C21: COMPRA PUT | D21: USDCLP | E21: banco ohiggings | F21: 1000 | G21: 830 | H21: 886.675 | I21: -3.1 | J21: -0.063918572 | K21: 0.34232165 | L21: -5000 | M21: 46329 | N21: 294
A22: 46035 | B22: CS-K | C22: VTA PUT | D22: AUDUSD | E22: Australia | F22: -1500 | G22: 0.62 | H22: 0.67035 | I22: 2.2 | J22: -0.075110017 | K22: 0.23745864 | L22: 5027.625 | M22: 46373 | N22: 338
A23: 46035 | B23: PUP | C23: VTA PUT | D23: QQQ | E23: NASDAQ | F23: -8.5 | G23: 370 | H23: 627.29 | I23: 6.1704 | J23: -0.41016117 | K23: 0.13124236 | L23: 15725 | M23: 46374 | N23: 339
A24: 46035 | B24: PUP | C24: VTA PUT | D24: SPY | E24: USA | F24: -6 | G24: 480 | H24: 695.59 | I24: 2.4594 | J24: -0.30993833 | K24: 0.075232142 | L24: 14400 | M24: 46191 | N24: 156
A25: 46035 | B25: PUP | C25: VTA PUT | D25: PUP | E25: Morgan Stanley | F25: -25 | G25: 115 | H25: 184.235 | I25: 3.9488 | J25: -0.37579722 | K25: 0.028844322 | L25: 14375 | M25: 46191 | N25: 156
A26: 46035 | B26: PUP | C26: VTA PUT | D26: JPM | E26: JPM | F26: -7.5 | G26: 235 | H26: 320.77 | I26: 2.9694 | J26: -0.26738785 | K26: 0.10822654 | L26: 8812.5 | M26: 46191 | N26: 156
A27: 46036 | B27: PUP | C27: COMPRA PUT | D27: SPY | E27: USA | F27: -6 | G27: 480 | H27: 690.805 | I27: -3.0126 | J27: -0.30515847 | K27: 0.078533505 | L27: 14400 | M27: 46191 | N27: 155
A28: 46036 | B28: PUP | C28: COMPRA PUT | D28: SPY | E28: USA | F28: -7.5 | G28: 520 | H28: 689.945 | I28: -5.5206 | J28: -0.24631674 | K28: 0.13857602 | L28: 19500 | M28: 46191 | N28: 155
A29: 46036 | B29: CS-K | C29: VTA PUT | D29: SPY | E29: USA | F29: -7.5 | G29: 520 | H29: 689.735 | I29: 5.325 | J29: -0.24608727 | K29: 0.13884793 | L29: 19500 | M29: 46191 | N29: 155
... A62: 46052 | B62: SSCH | C62: VTA PUT | D62: PUPFT | E62: Microsoft | F62: -3.5 | G62: 320 | H62: 437.63 | I62: 5.50326 | J62: -0.2687887 | K62: 0 | L62: 5600 | M62: 46374 | N62: 322
A63: 46052 | B63: NEVASA | C63: VTA CALL | D63: USDCLP | E63: banco ohiggings | F63: -1500 | G63: 910 | H63: 868 | I63: 1.7511521 | J63: =IF(G63="",0,G63/H63-1) -> 0.048387097 | K63: =IFERROR(#REF!,0) -> 0 | L63: 3.75 | M63: 46141 | N63: =IF(M63="","",M63-TODAY()) -> 16
A64: 46059 | B64: SSCH | C64: COMPRA PUT | D64: PUPFT | E64: Microsoft | F64: -4.5 | G64: 370 | H64: 394.615 | I64: 0 | J64: -0.062377254 | K64: 0.36525019 | L64: 8325 | M64: 46191 | N64: 132
A65: 46059 | B65: SSCH | C65: VTA PUT | D65: PUPFT | E65: Microsoft | F65: -4.5 | G65: 300 | H65: 394.695 | I65: -6.156 | J65: -0.23991943 | K65: 0.16802904 | L65: 6750 | M65: 46374 | N65: 315
A66: 46048 | B66: PUP | C66: VTA PUT | D66: PUP | E66: Morgan Stanley | F66: -22.5 | G66: 145 | H66: 167.695 | I66: -25.09935 | J66: -0.13533498 | K66: 0.22481736 | L66: 16312.5 | M66: 46191 | N66: 125
A67: 46066 | B67: PUP | C67: VTA PUT | D67: PUP | E67: Morgan Stanley | F67: -25 | G67: 120 | H67: 170.265 | I67: 21.6494 | J67: -0.29521628 | K67: 0 | L67: 15000 | M67: 46374 | N67: 308
A68: 46006 | B68: SSCH | C68: VTA PUT | D68: MBbva | E68: MongoBbva | F68: -2 | G68: 290 | H68: 308.54 | I68: -16.812 | J68: -0.060089454 | K68: 0.47086035 | L68: 2900 | M68: 46191 | N68: 115
A69: 46076 | B69: SSCH | C69: VTA PUT | D69: TSLA | E69: Tesla | F69: -6 | G69: 220 | H69: 394.665 | I69: 9.9 | J69: -0.44256521 | K69: 0 | L69: 6600 | M69: 46374 | N69: 298
A70: 46015 | B70: SSCH | C70: VTA PUT | D70: PUPFT | E70: Microsoft | F70: -4.5 | G70: 340 | H70: 387.53 | I70: -18.70299 | J70: -0.12264857 | K70: 0.32124329 | L70: 7650 | M70: 46374 | N70: 298
A71: 46034 | B71: PUP | C71: VTA PUT | D71: MBbva | E71: MongoBbva | F71: -2 | G71: 280 | H71: 313.425 | I71: -14.6886 | J71: -0.10664433 | K71: 0.40751128 | L71: 2800 | M71: 46191 | N71: 114
A72: 46077 | B72: PUP | C72: VTA PUT | D72: NVDA | E72: Nvidia | F72: -17.5 | G72: 95 | H72: 199.23 | I72: 8.2944 | J72: -0.52316418 | K72: 0.048886733 | L72: 8312.5 | M72: 46374 | N72: 297
A73: 46077 | B73: PUP | C73: VTA PUT | D73: BAC | E73: Bofa | F73: -37.5 | G73: 42 | H73: 49.975 | I73: -7.7256 | J73: -0.15957979 | K73: 0.15206188 | L73: 15750 | M73: 46191 | N73: 114
A74: 46077 | B74: PUP | C74: VTA PUT | D74: BAC | E74: Bofa | F74: -37.5 | G74: 28 | H74: 49.915 | I74: 3.32865 | J74: -0.43904638 | K74: 0.016949619 | L74: 5250 | M74: 46374 | N74: 297
A75: 46077 | B75: SSCH | C75: VTA PUT | D75: GS | E75: GoldmanSachs | F75: -3.75 | G75: 750 | H75: 897.63 | I75: -16.5 | J75: -0.16446643 | K75: 0.1711005 | L75: 14062.5 | M75: 46191 | N75: 114
... A104: 46100 | B104: SSCH | C104: VTA PUT | D104: META | E104: META | F104: -5 | G104: 360 | H104: 612.965 | I104: 8.115 | J104: -0.41269077 | K104: 0.10136369 | L104: 9000 | M104: 46374 | N104: 274
H107: Resultado USD | I107: =SUM(I8:I106) -> 117.32766
A115: Fecha Aper | B115: Contraparte | C115: Pos | D115: ticker | E115: País | F115: Monto | G115: STRIKE | H115: Precio Cierre | I115: MTM | J115: STRIKE | K115: Prob. Ocurrencia | L115: Exposición | M115: Exp/Fix | N115: DIAS
C117: MONEDAS
D118: CALL | J118: STRIKE | K118: Prob. Ocurrencia
C121: VTA CALL | D121: EURUSD | E121: EUROPA | H121: 1.17165 | I121: 0 | J121: 0 | K121: 0 | L121: 0
C122: VTA CALL | D122: EURUSD | E122: EUROPA | H122: 1.17165 | I122: 0 | J122: 0 | K122: 0 | L122: 0
C123: VTA CALL | D123: EURUSD | E123: EUROPA | H123: 1.17165 | I123: 0 | J123: 0 | K123: 0 | L123: 0
C124: VTA CALL | D124: EURUSD | E124: EUROPA | H124: 1.17165 | I124: 0 | J124: 0 | K124: 0 | L124: 0
C125: VTA CALL | D125: EURUSD | E125: EUROPA | H125: 1.17165 | I125: 0 | J125: 0 | K125: 0 | L125: 0
C126: VTA CALL | D126: EURUSD | E126: EUROPA | H126: 1.17165 | I126: 0 | J126: 0 | K126: 0 | L126: 0
A129: 45967 | B129: banco ohiggings | C129: VTA CALL | D129: USDCLP | E129: banco ohiggings | F129: -1333.3333 | G129: 1180 | H129: 898.505 | I129: 0 | J129: 0.31329264 | K129: 0.0060754948 | L129: 1333.3333 | M129: 46329 | N129: 204
A130: 45967 | B130: banco ohiggings | C130: VTA CALL | D130: USDCLP | E130: banco ohiggings | F130: -1333.3333 | G130: 1170 | H130: 898.505 | I130: 0 | J130: 0.30216304 | K130: 0.0075004601 | L130: 1333.3333 | M130: 46329 | N130: 204
A131: 45971 | B131: banco ohiggings | C131: VTA CALL | D131: USDCLP | E131: banco ohiggings | F131: -1333.3333 | G131: 1160 | H131: 898.505 | I131: 0 | J131: 0.29103344 | K131: 0.0092280597 | L131: 1333.3333 | M131: 46329 | N131: 204
A132: 45987 | B132: banco ohiggings | C132: VTA CALL | D132: USDCLP | E132: banco ohiggings | F132: -1333.3333 | G132: 1140 | H132: 898.505 | I132: 0 | J132: 0.26877424 | K132: 0.013821566 | L132: 1333.3333 | M132: 46329 | N132: 204
A133: 45987 | B133: BCI | C133: VTA CALL | D133: USDCLP | E133: banco ohiggings | F133: -1333.3333 | G133: 1130 | H133: 898.505 | I133: 0 | J133: 0.25764464 | K133: 0.016823125 | L133: 1333.3333 | M133: 46329 | N133: 204
A134: 45988 | B134: banco ohiggings | C134: VTA CALL | D134: USDCLP | E134: banco ohiggings | F134: -1333.3333 | G134: 1120 | H134: 898.505 | I134: 0 | J134: 0.24651504 | K134: 0.020399644 | L134: 1333.3333 | M134: 46329 | N134: 204
A135: 45992 | B135: banco ohiggings | C135: VTA CALL | D135: USDCLP | E135: banco ohiggings | F135: -1333.3333 | G135: 1110 | H135: 898.505 | I135: 0 | J135: 0.23538545 | K135: 0.024641446 | L135: 1333.3333 | M135: 46329 | N135: 204
A136: 45992 | B136: BCI | C136: VTA CALL | D136: USDCLP | E136: banco ohiggings | F136: -1333.3333 | G136: 1100 | H136: 898.505 | I136: 0 | J136: 0.22425585 | K136: 0.029648191 | L136: 1333.3333 | M136: 46329 | N136: 204
A137: 46091 | B137: Bbva | C137: VTA CALL | D137: USDCLP | E137: banco ohiggings | F137: -1333.3333 | G137: 1040 | H137: 898.505 | I137: 0 | J137: 0.15747826 | K137: 0.082377954 | L137: 1333.3333 | M137: 46329 | N137: 204
A138: 46091 | B138: Bbva | C138: VTA CALL | D138: USDCLP | E138: banco ohiggings | F138: -1666.6667 | G138: 1020 | H138: 898.505 | I138: 0 | J138: 0.13521906 | K138: 0.11174823 | L138: 1666.6667 | M138: 46329 | N138: 204
A139: 46099 | B139: Bbva | C139: VTA CALL | D139: USDCLP | E139: banco ohiggings | F139: -1000 | G139: 1010 | H139: 898.505 | I139: 0 | J139: 0.12408946 | K139: 0.12923182 | L139: 1000 | M139: 46329 | N139: 204
A140: 46052 | B140: NEVASA | C140: VTA CALL | D140: USDCLP | E140: banco ohiggings | F140: -1000 | G140: 910 | H140: 898.505 | I140: 0 | J140: 0.012793474 | K140: 0.33419764 | L140: 1000 | M140: 46141 | N140: 16
A141: 46091 | B141: Bbva | C141: compra call | D141: USDCLP | E141: banco ohiggings | F141: 1000 | G141: 910 | H141: 898.505 | I141: 0 | J141: 0.012793474 | K141: 0.33419764 | L141: -1000 | M141: 46141 | N141: 16
C142: VTA CALL | D142: USDCLP | E142: banco ohiggings | F142: 0 | H142: 898.505 | I142: 0 | J142: 0 | K142: 0 | L142: 0
C143: VTA CALL | D143: USDCLP | E143: banco ohiggings | F143: 0 | H143: 898.505 | I143: 0 | J143: 0 | K143: 0 | L143: 0
C144: VTA CALL | D144: USDCLP | E144: banco ohiggings | F144: 0 | H144: 898.505 | I144: 0 | J144: 0 | K144: 0 | L144: 0
C145: VTA CALL | D145: USDCLP | E145: banco ohiggings | F145: 0 | H145: 898.505 | I145: 0 | J145: 0 | K145: 0 | L145: 0
F146: 0
C147: VTA CALL | D147: USBbvaRL | E147: Brazil | F147: 0 | H147: 5.02835 | I147: 0 | J147: 0 | K147: 0 | L147: 0
C148: VTA CALL | D148: USBbvaRL | E148: Brazil | F148: 0 | H148: 5.02835 | I148: 0 | J148: 0 | K148: 0 | L148: 0
C149: VTA CALL | D149: USBbvaRL | E149: Brazil | F149: 0 | H149: 5.02835 | I149: 0 | J149: 0 | K149: 0 | L149: 0
F150: 0
C151: VTA CALL | D151: USDMXN | E151: México | F151: 0 | H151: 17.34405 | I151: 0 | J151: 0 | K151: 0 | L151: 0
C152: VTA CALL | D152: USDMXN | E152: México | F152: 0 | H152: 17.34405 | I152: 0 | J152: 0 | K152: 0 | L152: 0
F153: 0
C154: VTA CALL | D154: USDZAR | E154: Sudáfrica | F154: 0 | H154: 16.47875 | I154: 0 | J154: 0 | K154: 0 | L154: 0
C155: VTA CALL | D155: USDZAR | E155: Sudáfrica | F155: 0 | H155: 16.47875 | I155: 0 | J155: 0 | K155: 0 | L155: 0
C156: VTA CALL | D156: USDZAR | E156: Sudáfrica | F156: 0 | H156: 16.47875 | I156: 0 | J156: 0 | K156: 0 | L156: 0
C157: VTA CALL | D157: USDZAR | E157: Sudáfrica | F157: 0 | H157: 16.47875 | I157: 0 | J157: 0 | K157: 0 | L157: 0
C158: VTA CALL | D158: USDZAR | E158: Sudáfrica | F158: 0 | H158: 16.47875 | I158: 0 | J158: 0 | K158: 0 | L158: 0
C159: VTA CALL | D159: USDZAR | E159: Sudáfrica | F159: 0 | H159: 16.47875 | I159: 0 | J159: 0 | K159: 0 | L159: 0
C160: VTA CALL | D160: USDZAR | E160: Sudáfrica | F160: 0 | H160: 16.47875 | I160: 0 | J160: 0 | K160: 0 | L160: 0
F161: 0
A162: 46050 | B162: CS-K | C162: VTA CALL | D162: AUDUSD | E162: Australia | F162: -1000 | G162: 0.745 | H162: 0.7067 | I162: 0 | J162: 0.054195557 | K162: 0.37057799 | L162: 706.7 | M162: 46351 | N162: 226
A163: 46048 | B163: CS-K | C163: VTA CALL | D163: AUDUSD | E163: Australia | F163: -1000 | G163: 0.74 | H163: 0.7067 | I163: 0 | J163: 0.047120419 | K163: 0.38132884 | L163: 706.7 | M163: 46351 | N163: 226
A164: 46045 | B164: UBS | C164: VTA CALL | D164: AUDUSD | E164: Australia | F164: -1000 | G164: 0.735 | H164: 0.7067 | I164: 0 | J164: 0.040045281 | K164: 0.39224587 | L164: 706.7 | M164: 46351 | N164: 226
A165: 46045 | B165: CS-K | C165: VTA CALL | D165: AUDUSD | E165: Australia | F165: -1000 | G165: 0.73 | H165: 0.7067 | I165: 0 | J165: 0.032970143 | K165: 0.40332376 | L165: 706.7 | M165: 46351 | N165: 226
A166: 46003 | B166: UBS | C166: VTA CALL | D166: AUDUSD | E166: Australia | F166: -1000 | G166: 0.725 | H166: 0.7067 | I166: 0 | J166: 0.025895005 | K166: 0.41445273 | L166: 706.7 | M166: 46373 | N166: 248
C167: VTA CALL | D167: AUDUSD | E167: Australia | F167: 0 | H167: 0.7067 | I167: 0 | J167: 0 | K167: 0 | L167: 0
C168: VTA CALL | D168: AUDUSD | E168: Australia | F168: 0 | H168: 0.7067 | I168: 0 | J168: 0 | K168: 0 | L168: 0
C169: VTA CALL | D169: AUDUSD | E169: Australia | F169: 0 | H169: 0.7067 | I169: 0 | J169: 0 | K169: 0 | L169: 0
C170: VTA CALL | D170: AUDUSD | E170: Australia | F170: 0 | H170: 0.7067 | I170: 0 | J170: 0 | K170: 0 | L170: 0
C171: VTA CALL | D171: AUDUSD | E171: Australia | F171: 0 | H171: 0.7067 | I171: 0 | J171: 0 | K171: 0 | L171: 0
C172: VTA CALL | D172: AUDUSD | E172: Australia | F172: 0 | H172: 0.7067 | I172: 0 | J172: 0 | K172: 0 | L172: 0
C173: VTA CALL | D173: AUDUSD | E173: Australia | F173: 0 | H173: 0.7067 | I173: 0 | J173: 0 | K173: 0 | L173: 0
C174: VTA CALL | D174: AUDUSD | E174: Australia | F174: 0 | H174: 0.7067 | I174: 0 | J174: 0 | K174: 0 | L174: 0
F175: 0
C176: VTA CALL | D176: XAUUSD | E176: Gold | F176: 0 | H176: 4720.645 | I176: 0 | J176: 0 | K176: 0 | L176: 0
C177: VTA CALL | D177: XAUUSD | E177: Gold | F177: 0 | H177: 4720.645 | I177: 0 | J177: 0 | K177: 0 | L177: 0
F178: 0
...

Sheet etf
F4: CARTERA DELTA EQUITY
B7: Fecha | C7: Estado | D7: Contraparte | E7: RSI | F7: ticker | G7: País | H7: Monto | I7: Precio Inicial | J7: Precio Cierre | K7: MTM | L7: Rent | M7: VP
C8: E | F8: FXI | G8: China | I8: 46.11 | K8: =+J8*H8-H8*I8 -> 0 | M8: =+J8*H8 -> 0
C9: E | F9: DBA | G9: Agriculture | I9: 20.185 | J9: 19.6722 | K9: =+J9*H9-H9*I9 -> 0 | L9: =LN(J9/I9) -> -0.025733283 | M9: =+J9*H9 -> 0
C10: E | F10: DB | G10: Deursche Bank | I10: 19.215 | K10: =+J10*H10-H10*I10 -> 0 | M10: =+J10*H10 -> 0
C11: E | F11: LIT | G11: Lithium ETF | I11: 61.89 | J11: 78.915 | K11: =+J11*H11-H11*I11 -> 0 | L11: =LN(J11/I11) -> 0.24301271 | M11: =+J11*H11 -> 0
C12: E | F12: AAPL | G12: Apple | I12: =323.0656/4 -> 80.7664 | K12: =+J12*H12-H12*I12 -> 0 | M12: =+J12*H12 -> 0
C13: E | F13: AAPL | G13: Apple | I13: 123.78987 | K13: =+J13*H13-H13*I13 -> 0 | M13: =+J13*H13 -> 0
C14: E | F14: GLD | G14: ETF Oro | I14: 247.0999 | J14: 432.95 | K14: =+J14*H14-H14*I14 -> 0 | L14: =LN(J14/I14) -> 0.56082954 | M14: =+J14*H14 -> 0
C15: E | F15: GLD | G15: ETF Oro | I15: 248.5491 | J15: 432.95 | K15: =+J15*H15-H15*I15 -> 0 | L15: =LN(J15/I15) -> 0.55498184 | M15: =+J15*H15 -> 0
C16: E | F16: GLD | G16: ETF Oro | I16: 251.615 | J16: 432.95 | K16: =+J16*H16-H16*I16 -> 0 | L16: =LN(J16/I16) -> 0.54272211 | M16: =+J16*H16 -> 0
C17: E | F17: GLD | G17: ETF Oro | I17: 248.9399 | J17: 432.95 | K17: =+J17*H17-H17*I17 -> 0 | L17: =LN(J17/I17) -> 0.55341075 | M17: =+J17*H17 -> 0
C18: E | F18: GLD | G18: ETF Oro | I18: 248.8599 | J18: 432.95 | K18: =+J18*H18-H18*I18 -> 0 | L18: =LN(J18/I18) -> 0.55373216 | M18: =+J18*H18 -> 0
C19: E | F19: QQQ | G19: NASDAQ | I19: 531.5826 | J19: 611.205 | K19: =+J19*H19-H19*I19 -> 0 | L19: =LN(J19/I19) -> 0.13957382 | M19: =+J19*H19 -> 0
C20: E | F20: CRSP | G20: CRISPR THERAPEUTICS AG | I20: 114.8742 | J20: 52.805 | K20: =+J20*H20-H20*I20 -> 0 | L20: =LN(J20/I20) -> -0.77723173 | M20: =+J20*H20 -> 0
C21: E | F21: BABA | G21: Alibaba | I21: 263.75 | K21: =+J21*H21-H21*I21 -> 0 | M21: =+J21*H21 -> 0
C22: E | F22: DIA | G22: DOW JONES | I22: 344.3755 | J22: 476.98 | K22: =+J22*H22-H22*I22 -> 0 | L22: =LN(J22/I22) -> 0.32574193 | M22: =+J22*H22 -> 0
C23: E | F23: DIA | G23: DOW JONES | I23: 338.4971 | J23: 476.98 | K23: =+J23*H23-H23*I23 -> 0 | L23: =LN(J23/I23) -> 0.34295904 | M23: =+J23*H23 -> 0
C24: E | F24: BOTZ | G24: ETF AI | I24: 28.2394 | J24: 35.445 | K24: =+J24*H24-H24*I24 -> 0 | L24: =LN(J24/I24) -> 0.22726403 | M24: =+J24*H24 -> 0
C25: E | F25: BOTZ | G25: ETF AI | I25: 30.9971 | J25: 35.445 | K25: =+J25*H25-H25*I25 -> 0 | L25: =LN(J25/I25) -> 0.13408855 | M25: =+J25*H25 -> 0
C26: E | F26: MDB | G26: MDB | I26: 222.1239 | J26: 231.515 | K26: =+J26*H26-H26*I26 -> 0 | L26: =LN(J26/I26) -> 0.041409332 | M26: =+J26*H26 -> 0
C27: E | F27: AIQ | G27: AIQ | I27: 52.745 | J27: 49.635 | K27: =+J27*H27-H27*I27 -> 0 | L27: =LN(J27/I27) -> -0.060772751 | M27: =+J27*H27 -> 0
C28: E | F28: AIQ | G28: AIQ | I28: 40.6669 | J28: 49.635 | K28: =+J28*H28-H28*I28 -> 0 | L28: =LN(J28/I28) -> 0.19928174 | M28: =+J28*H28 -> 0
C29: E | F29: SPY | G29: S&P500 | I29: 595.1734 | J29: 679.305 | K29: =+J29*H29-H29*I29 -> 0 | L29: =LN(J29/I29) -> 0.13221743 | M29: =+J29*H29 -> 0
C30: E | F30: TSLA | G30: Tesla | I30: 453.65132 | J30: 351.675 | K30: =+J30*H30-H30*I30 -> 0 | L30: =LN(J30/I30) -> -0.25462142 | M30: =+J30*H30 -> 0
C31: E | F31: AMZN | G31: AMZN | I31: 234.8292 | J31: 236.945 | K31: =+J31*H31-H31*I31 -> 0 | L31: =LN(J31/I31) -> 0.0089696053 | M31: =+J31*H31 -> 0
C32: E | F32: NVDA | G32: NVDA | I32: 193.269 | J32: 188.315 | K32: =+J32*H32-H32*I32 -> 0 | L32: =LN(J32/I32) -> -0.025966908 | M32: =+J32*H32 -> 0
C33: E | F33: MSFT | G33: Microsoft | I33: 439.57 | J33: 376.725 | K33: =+J33*H33-H33*I33 -> 0 | L33: =LN(J33/I33) -> -0.1542815 | M33: =+J33*H33 -> 0
... C42: E | F42: NVDA | G42: USA | I42: 130.5197 | J42: 188.315 | K42: =+J42*H42-H42*I42 -> 0 | L42: =LN(J42/I42) -> 0.36659192 | M42: =+J42*H42 -> 0
B43: FIN
J44: Resultado USD | K44: =SUM(K8:K43) -> 0 | M44: =SUM(M8:M43) -> 0
J46: Trading
J47: Cash
J48: TOTAL ETF | M48: =+M46+M44 -> 0
B51: Fecha Aper | C51: Fecha Cierre | D51: Contraparte | E51: Pos | F51: ticker | G51: País | H51: Monto | I51: Precio Inicial | J51: Precio Cierre | K51: MTM
K53: =+J53*H53-H53*I53 -> 0
K54: =+J54*H54-H54*I54 -> 0
K55: =+J55*H55-H55*I55 -> 0
K56: =+J56*H56-H56*I56 -> 0
K57: =+J57*H57-H57*I57 -> 0
K58: =+J58*H58-H58*I58 -> 0
K59: =+J59*H59-H59*I59 -> 0
K60: =+J60*H60-H60*I60 -> 0
K61: =+J61*H61-H61*I61 -> 0
K62: =+J62*H62-H62*I62 -> 0
K63: =+J63*H63-H63*I63 -> 0
K64: =+J64*H64-H64*I64 -> 0
... K66: =+J66*H66-H66*I66 -> 0
K102: =SUM(K52:K101) -> 0

Sheet Hoja1
G1: SPY
F2: Caida | G2: -0.05
B5: Bid | C5: Ask | D5: mid | E5: Betas | F5: Betas | G5: BETA | H5: Precio Final | I5: Precio Final | K5: beta
A6: CLP= | B6: {=_xll.RDP.Data(A6,"CF_BID")} -> 894.04 | C6: {=_xll.RDP.Data(A6,"CF_ASK")} -> 894.87 | D6: =(B6+C6)/2 -> 894.455 | E6: -0.015 | F6: -0.015 | G6: =IF('ppal B'!$I$11=0,0,IF('ppal B'!$I$11>0,E6*'ppal B'!$I$11*100,F6*'ppal B'!$I$11*100)) -> 0 | H6: 898.375 | I6: =E6*(1+H6) -> -13.490625 | K6: =_xll.RDP.Data(A6,"TR.WACCBeta") -> Unable to resolve all requested identifiers.
A7: BRL= | B7: {=_xll.RDP.Data(A7,"CF_BID")} -> 4.9873 | C7: {=_xll.RDP.Data(A7,"CF_ASK")} -> 4.9882 | D7: =(B7+C7)/2 -> 4.98775 | E7: -0.025 | F7: -0.025 | G7: =IF('ppal B'!$I$11=0,0,IF('ppal B'!$I$11>0,E7*'ppal B'!$I$11*100,F7*'ppal B'!$I$11*100)) -> 0 | H7: 5.0295 | I7: =E7*(1+H7) -> -0.1507375 | K7: =_xll.RDP.Data(A7,"TR.WACCBeta") -> Unable to resolve all requested identifiers.
A8: EUR= | B8: {=_xll.RDP.Data(A8,"CF_BID")} -> 1.1736 | C8: {=_xll.RDP.Data(A8,"CF_ASK")} -> 1.1737 | D8: =(B8+C8)/2 -> 1.17365 | E8: 0.016 | F8: 0.016 | G8: =IF('ppal B'!$I$11=0,0,IF('ppal B'!$I$11>0,E8*'ppal B'!$I$11*100,F8*'ppal B'!$I$11*100)) -> 0 | H8: 1.1716 | I8: =E8*(1+H8) -> 0.0347456 | K8: =_xll.RDP.Data(A8,"TR.WACCBeta") -> Unable to resolve all requested identifiers.
A9: ARKF.K | B9: {=_xll.RDP.Data(A9,"CF_BID")} -> 39.39 | C9: {=_xll.RDP.Data(A9,"CF_ASK")} -> 39.46 | D9: =(B9+C9)/2 -> 39.425 | E9: 0 | F9: 0 | G9: =IF('ppal B'!$I$11=0,0,IF('ppal B'!$I$11>0,E9*'ppal B'!$I$11*100,F9*'ppal B'!$I$11*100)) -> 0 | H9: 39.05 | I9: =E9*(1+H9) -> 0 | K9: =_xll.RDP.Data(A9,"TR.WACCBeta") -> NULL
A10: aud= | B10: {=_xll.RDP.Data(A10,"CF_BID")} -> 0.7088 | C10: {=_xll.RDP.Data(A10,"CF_ASK")} -> 0.7091 | D10: =(B10+C10)/2 -> 0.70895 | E10: 0.01 | F10: 0.01 | G10: =IF('ppal B'!$I$11=0,0,IF('ppal B'!$I$11>0,E10*'ppal B'!$I$11*100,F10*'ppal B'!$I$11*100)) -> 0 | H10: 0.7067 | I10: =E10*(1+H10) -> 0.017067 | K10: =_xll.RDP.Data(A10,"TR.WACCBeta") -> NULL
A11: xau= | B11: {=_xll.RDP.Data(A11,"CF_BID")} -> 4745.46 | C11: {=_xll.RDP.Data(A11,"CF_ASK")} -> 4746.2 | D11: =(B11+C11)/2 -> 4745.83 | E11: 0.02 | F11: 0.01 | G11: =IF('ppal B'!$I$11=0,0,IF('ppal B'!$I$11>0,E11*'ppal B'!$I$11*100,F11*'ppal B'!$I$11*100)) -> 0 | H11: 4720.375 | I11: =E11*(1+H11) -> 94.4275 | K11: =_xll.RDP.Data(A11,"TR.WACCBeta") -> Unable to resolve all requested identifiers.
A12: SPY | B12: {=_xll.RDP.Data(A12,"CF_BID")} -> 682.17 | C12: {=_xll.RDP.Data(A12,"CF_ASK")} -> 682.18 | D12: =(B12+C12)/2 -> 682.175 | E12: 0.01 | F12: 0.01 | G12: =IF('ppal B'!$I$11=0,0,IF('ppal B'!$I$11>0,E12*'ppal B'!$I$11*100,F12*'ppal B'!$I$11*100)) -> 0 | H12: 679.25 | I12: =E12*(1+H12) -> 6.8025 | K12: =_xll.RDP.Data(A12,"TR.WACCBeta") -> NULL
A13: AAPL.O | B13: {=_xll.RDP.Data(A13,"CF_BID")} -> 257.83 | C13: {=_xll.RDP.Data(A13,"CF_ASK")} -> 257.85 | D13: =(B13+C13)/2 -> 257.84 | E13: 0.02 | F13: 0.03 | G13: =IF('ppal B'!$I$11=0,0,IF('ppal B'!$I$11>0,E13*'ppal B'!$I$11*100,F13*'ppal B'!$I$11*100)) -> 0 | H13: 257.4 | I13: =E13*(1+H13) -> 5.168 | K13: =_xll.RDP.Data(A13,"TR.WACCBeta") -> 1.0952454
A14: MXN= | B14: {=_xll.RDP.Data(A14,"CF_BID")} -> 17.2929 | C14: {=_xll.RDP.Data(A14,"CF_ASK")} -> 17.3034 | D14: =(B14+C14)/2 -> 17.29815 | E14: -0.01 | F14: -0.03 | G14: =IF('ppal B'!$I$11=0,0,IF('ppal B'!$I$11>0,E14*'ppal B'!$I$11*100,F14*'ppal B'!$I$11*100)) -> 0 | H14: 17.34315 | I14: =E14*(1+H14) -> -0.1834315 | K14: =_xll.RDP.Data(A14,"TR.WACCBeta") -> Unable to resolve all requested identifiers.
A15: ZAR= | B15: {=_xll.RDP.Data(A15,"CF_BID")} -> 16.4046 | C15: {=_xll.RDP.Data(A15,"CF_ASK")} -> 16.4077 | D15: =(B15+C15)/2 -> 16.40615 | E15: -0.025 | F15: -0.025 | G15: =IF('ppal B'!$I$11=0,0,IF('ppal B'!$I$11>0,E15*'ppal B'!$I$11*100,F15*'ppal B'!$I$11*100)) -> 0 | H15: 16.4854 | I15: =E15*(1+H15) -> -0.437135 | K15: =_xll.RDP.Data(A15,"TR.WACCBeta") -> Unable to resolve all requested identifiers.
A16: JPY= | B16: {=_xll.RDP.Data(A16,"CF_BID")} -> 159.39 | C16: {=_xll.RDP.Data(A16,"CF_ASK")} -> 159.4 | D16: =(B16+C16)/2 -> 159.395 | E16: 0 | F16: 0 | G16: =IF('ppal B'!$I$11=0,0,IF('ppal B'!$I$11>0,E16*'ppal B'!$I$11*100,F16*'ppal B'!$I$11*100)) -> 0 | H16: 159.565 | I16: =E16*(1+H16) -> 0 | K16: =_xll.RDP.Data(A16,"TR.WACCBeta") -> NULL
A17: ARKQ.K | B17: {=_xll.RDP.Data(A17,"CF_BID")} -> 121.21 | C17: {=_xll.RDP.Data(A17,"CF_ASK")} -> 121.31 | D17: =(B17+C17)/2 -> 121.26 | E17: 0 | F17: 0 | G17: =IF('ppal B'!$I$11=0,0,IF('ppal B'!$I$11>0,E17*'ppal B'!$I$11*100,F17*'ppal B'!$I$11*100)) -> 0 | H17: 120.07 | I17: =E17*(1+H17) -> 0 | K17: =_xll.RDP.Data(A17,"TR.WACCBeta") -> NULL
... A71: MRNA.O | B71: {=_xll.RDP.Data(A71,"CF_BID")} -> 51.37 | C71: {=_xll.RDP.Data(A71,"CF_ASK")} -> 51.39 | D71: =(B71+C71)/2 -> 51.38 | E71: 0 | F71: 0 | G71: =IF('ppal B'!$I$11=0,0,IF('ppal B'!$I$11>0,E71*'ppal B'!$I$11*100,F71*'ppal B'!$I$11*100)) -> 0 | H71: 52.335 | I71: =E71*(1+H71) -> 0 | K71: =_xll.RDP.Data(A71,"TR.WACCBeta") -> 1.2050528
A72: TCEHY.PQ | B72: {=_xll.RDP.Data(A72,"CF_BID")} -> 64.18 | C72: {=_xll.RDP.Data(A72,"CF_ASK")} -> 64.23 | D72: =+C72 -> 64.23 | E72: 0 | F72: 0 | G72: =IF('ppal B'!$I$11=0,0,IF('ppal B'!$I$11>0,E72*'ppal B'!$I$11*100,F72*'ppal B'!$I$11*100)) -> 0 | H72: 63.12 | I72: =E72*(1+H72) -> 0 | K72: =_xll.RDP.Data(A72,"TR.WACCBeta") -> 1.3525632
A73: CRSP.O | B73: {=_xll.RDP.Data(A73,"CF_BID")} -> 53.87 | C73: {=_xll.RDP.Data(A73,"CF_ASK")} -> 53.93 | D73: =(B73+C73)/2 -> 53.9 | E73: 0 | F73: 0 | G73: =IF('ppal B'!$I$11=0,0,IF('ppal B'!$I$11>0,E73*'ppal B'!$I$11*100,F73*'ppal B'!$I$11*100)) -> 0 | H73: 52.75 | I73: =E73*(1+H73) -> 0 | K73: =_xll.RDP.Data(A73,"TR.WACCBeta") -> 1.7981445
A74: PYPL.O | B74: {=_xll.RDP.Data(A74,"CF_BID")} -> 47.24 | C74: {=_xll.RDP.Data(A74,"CF_ASK")} -> 47.25 | D74: =(B74+C74)/2 -> 47.245 | E74: 0 | F74: 0 | G74: =IF('ppal B'!$I$11=0,0,IF('ppal B'!$I$11>0,E74*'ppal B'!$I$11*100,F74*'ppal B'!$I$11*100)) -> 0 | H74: 46.195 | I74: =E74*(1+H74) -> 0 | K74: =_xll.RDP.Data(A74,"TR.WACCBeta") -> 1.387552
A75: TSLA.O | B75: {=_xll.RDP.Data(A75,"CF_BID")} -> 353.09 | C75: {=_xll.RDP.Data(A75,"CF_ASK")} -> 353.13 | D75: =(B75+C75)/2 -> 353.11 | E75: 0 | F75: 0 | G75: =IF('ppal B'!$I$11=0,0,IF('ppal B'!$I$11>0,E75*'ppal B'!$I$11*100,F75*'ppal B'!$I$11*100)) -> 0 | H75: 351.485 | I75: =E75*(1+H75) -> 0 | K75: =_xll.RDP.Data(A75,"TR.WACCBeta") -> 1.8855773
A76: SLV | B76: {=_xll.RDP.Data(A76,"CF_BID")} -> 68.08 | C76: {=_xll.RDP.Data(A76,"CF_ASK")} -> 68.09 | D76: =(B76+C76)/2 -> 68.085 | E76: 0 | F76: 0 | G76: =IF('ppal B'!$I$11=0,0,IF('ppal B'!$I$11>0,E76*'ppal B'!$I$11*100,F76*'ppal B'!$I$11*100)) -> 0 | H76: 66.955 | I76: =E76*(1+H76) -> 0 | K76: =_xll.RDP.Data(A76,"TR.WACCBeta") -> NULL
A77: COPX.K | B77: {=_xll.RDP.Data(A77,"CF_BID")} -> 84.47 | C77: {=_xll.RDP.Data(A77,"CF_ASK")} -> 84.52 | D77: =(B77+C77)/2 -> 84.495 | E77: 0 | F77: 0 | G77: =IF('ppal B'!$I$11=0,0,IF('ppal B'!$I$11>0,E77*'ppal B'!$I$11*100,F77*'ppal B'!$I$11*100)) -> 0 | H77: 83.12 | I77: =E77*(1+H77) -> 0 | K77: =_xll.RDP.Data(A77,"TR.WACCBeta") -> NULL
A78: MTLS.O | B78: {=_xll.RDP.Data(A78,"CF_BID")} -> 5.18 | C78: {=_xll.RDP.Data(A78,"CF_ASK")} -> 5.24 | D78: =(B78+C78)/2 -> 5.21 | E78: 0 | F78: 0 | G78: =IF('ppal B'!$I$11=0,0,IF('ppal B'!$I$11>0,E78*'ppal B'!$I$11*100,F78*'ppal B'!$I$11*100)) -> 0 | H78: 5.045 | I78: =E78*(1+H78) -> 0 | K78: =_xll.RDP.Data(A78,"TR.WACCBeta") -> NULL
A79: AVAV.O | B79: {=_xll.RDP.Data(A79,"CF_BID")} -> 191.5 | C79: {=_xll.RDP.Data(A79,"CF_ASK")} -> 191.98 | D79: =(B79+C79)/2 -> 191.74 | E79: 0 | F79: 0 | G79: =IF('ppal B'!$I$11=0,0,IF('ppal B'!$I$11>0,E79*'ppal B'!$I$11*100,F79*'ppal B'!$I$11*100)) -> 0 | H79: 187.055 | I79: =E79*(1+H79) -> 0 | K79: =_xll.RDP.Data(A79,"TR.WACCBeta") -> 1.3983783
A80: xag= | B80: {=_xll.RDP.Data(A80,"CF_BID")} -> 75.52 | C80: {=_xll.RDP.Data(A80,"CF_ASK")} -> 75.6 | D80: =(B80+C80)/2 -> 75.56 | E80: 0 | F80: 0 | G80: =IF('ppal B'!$I$11=0,0,IF('ppal B'!$I$11>0,E80*'ppal B'!$I$11*100,F80*'ppal B'!$I$11*100)) -> 0 | H80: 74.1715 | I80: =E80*(1+H80) -> 0 | K80: =_xll.RDP.Data(A80,"TR.WACCBeta") -> Unable to resolve all requested identifiers.
A81: JD.O | B81: {=_xll.RDP.Data(A81,"CF_BID")} -> 28.67 | C81: {=_xll.RDP.Data(A81,"CF_ASK")} -> 28.68 | D81: =(B81+C81)/2 -> 28.675 | E81: 0 | F81: 0 | G81: =IF('ppal B'!$I$11=0,0,IF('ppal B'!$I$11>0,E81*'ppal B'!$I$11*100,F81*'ppal B'!$I$11*100)) -> 0 | H81: 28.515 | I81: =E81*(1+H81) -> 0 | K81: =_xll.RDP.Data(A81,"TR.WACCBeta") -> 1.5628516
A82: CPER.K | B82: {=_xll.RDP.Data(A82,"CF_BID")} -> 36.71 | C82: {=_xll.RDP.Data(A82,"CF_ASK")} -> 36.73 | D82: =(B82+C82)/2 -> 36.72 | E82: 0 | F82: 0 | G82: =IF('ppal B'!$I$11=0,0,IF('ppal B'!$I$11>0,E82*'ppal B'!$I$11*100,F82*'ppal B'!$I$11*100)) -> 0 | H82: 36.335 | I82: =E82*(1+H82) -> 0 | K82: =_xll.RDP.Data(A82,"TR.WACCBeta") -> NULL
A83: ARCT.O | B83: {=_xll.RDP.Data(A83,"CF_BID")} -> 8.45 | C83: {=_xll.RDP.Data(A83,"CF_ASK")} -> 8.47 | D83: =(B83+C83)/2 -> 8.46 | E83: 0 | F83: 0 | G83: =IF('ppal B'!$I$11=0,0,IF('ppal B'!$I$11>0,E83*'ppal B'!$I$11*100,F83*'ppal B'!$I$11*100)) -> 0 | H83: 8.47 | I83: =E83*(1+H83) -> 0 | K83: =_xll.RDP.Data(A83,"TR.WACCBeta") -> 2.5186186
A84: CGEN.O | B84: {=_xll.RDP.Data(A84,"CF_BID")} -> 2.71 | C84: {=_xll.RDP.Data(A84,"CF_ASK")} -> 2.72 | D84: =(B84+C84)/2 -> 2.715 | E84: 0 | F84: 0 | G84: =IF('ppal B'!$I$11=0,0,IF('ppal B'!$I$11>0,E84*'ppal B'!$I$11*100,F84*'ppal B'!$I$11*100)) -> 0 | H84: 2.615 | I84: =E84*(1+H84) -> 0 | K84: =_xll.RDP.Data(A84,"TR.WACCBeta") -> 2.8519402
... A87: PINS.K | B87: {=_xll.RDP.Data(A87,"CF_BID")} -> 18.03 | C87: {=_xll.RDP.Data(A87,"CF_ASK")} -> 18.04 | D87: =(B87+C87)/2 -> 18.035 | E87: 0 | F87: 0 | G87: =IF('ppal B'!$I$11=0,0,IF('ppal B'!$I$11>0,E87*'ppal B'!$I$11*100,F87*'ppal B'!$I$11*100)) -> 0 | H87: 17.745 | I87: =E87*(1+H87) -> 0 | K87: =_xll.RDP.Data(A87,"TR.WACCBeta") -> 0.90575576
B88: {=_xll.RDP.Data(A88,"CF_BID")} -> No universe defined. | C88: {=_xll.RDP.Data(A88,"CF_ASK")} -> No universe defined. | D88: =(B88+C88)/2 -> #VALUE! | E88: 0 | F88: 0 | G88: =IF('ppal B'!$I$11=0,0,IF('ppal B'!$I$11>0,E88*'ppal B'!$I$11*100,F88*'ppal B'!$I$11*100)) -> 0 | H88: #VALUE! | I88: =E88*(1+H88) -> #VALUE! | K88: =_xll.RDP.Data(A88,"TR.WACCBeta") -> No universe defined.
A89: FVRR.K | B89: {=_xll.RDP.Data(A89,"CF_BID")} -> 10.38 | C89: {=_xll.RDP.Data(A89,"CF_ASK")} -> 10.4 | D89: =(B89+C89)/2 -> 10.39 | E89: 0 | F89: 0 | G89: =IF('ppal B'!$I$11=0,0,IF('ppal B'!$I$11>0,E89*'ppal B'!$I$11*100,F89*'ppal B'!$I$11*100)) -> 0 | H89: 10.065 | I89: =E89*(1+H89) -> 0 | K89: =_xll.RDP.Data(A89,"TR.WACCBeta") -> 1.3835844
A90: SEDG.O | B90: {=_xll.RDP.Data(A90,"CF_BID")} -> 43.82 | C90: {=_xll.RDP.Data(A90,"CF_ASK")} -> 43.9 | D90: =(B90+C90)/2 -> 43.86 | E90: 0 | F90: 0 | G90: =IF('ppal B'!$I$11=0,0,IF('ppal B'!$I$11>0,E90*'ppal B'!$I$11*100,F90*'ppal B'!$I$11*100)) -> 0 | H90: 43.355 | I90: =E90*(1+H90) -> 0 | K90: =_xll.RDP.Data(A90,"TR.WACCBeta") -> 1.3290473
A91: SPNS.O | B91: {=_xll.RDP.Data(A91,"CF_BID")} -> The record could not be found (Error code: 0) | C91: {=_xll.RDP.Data(A91,"CF_ASK")} -> The record could not be found (Error code: 0) | D91: =(B91+C91)/2 -> #VALUE! | E91: 0 | F91: 0 | G91: =IF('ppal B'!$I$11=0,0,IF('ppal B'!$I$11>0,E91*'ppal B'!$I$11*100,F91*'ppal B'!$I$11*100)) -> 0 | H91: #VALUE! | I91: =E91*(1+H91) -> #VALUE! | K91: =_xll.RDP.Data(A91,"TR.WACCBeta") -> NULL
B92: {=_xll.RDP.Data(A92,"CF_BID")} -> No universe defined. | C92: {=_xll.RDP.Data(A92,"CF_ASK")} -> No universe defined. | D92: =(B92+C92)/2 -> #VALUE! | E92: 0 | F92: 0 | G92: =IF('ppal B'!$I$11=0,0,IF('ppal B'!$I$11>0,E92*'ppal B'!$I$11*100,F92*'ppal B'!$I$11*100)) -> 0 | H92: #VALUE! | I92: =E92*(1+H92) -> #VALUE! | K92: =_xll.RDP.Data(A92,"TR.WACCBeta") -> No universe defined.
A93: CAMT.O | B93: {=_xll.RDP.Data(A93,"CF_BID")} -> 173.35 | C93: {=_xll.RDP.Data(A93,"CF_ASK")} -> 174.97 | D93: =(B93+C93)/2 -> 174.16 | E93: 0 | F93: 0 | G93: =IF('ppal B'!$I$11=0,0,IF('ppal B'!$I$11>0,E93*'ppal B'!$I$11*100,F93*'ppal B'!$I$11*100)) -> 0 | H93: 173.28 | I93: =E93*(1+H93) -> 0 | K93: =_xll.RDP.Data(A93,"TR.WACCBeta") -> 1.5800617
A94: ADSK.O | B94: {=_xll.RDP.Data(A94,"CF_BID")} -> 226.38 | C94: {=_xll.RDP.Data(A94,"CF_ASK")} -> 226.51 | D94: =(B94+C94)/2 -> 226.445 | E94: 0 | F94: 0 | G94: =IF('ppal B'!$I$11=0,0,IF('ppal B'!$I$11>0,E94*'ppal B'!$I$11*100,F94*'ppal B'!$I$11*100)) -> 0 | H94: 222.325 | I94: =E94*(1+H94) -> 0 | K94: =_xll.RDP.Data(A94,"TR.WACCBeta") -> 1.3946633
B95: {=_xll.RDP.Data(A95,"CF_BID")} -> No universe defined. | C95: {=_xll.RDP.Data(A95,"CF_ASK")} -> No universe defined. | D95: =(B95+C95)/2 -> #VALUE! | E95: 0 | F95: 0 | G95: =IF('ppal B'!$I$11=0,0,IF('ppal B'!$I$11>0,E95*'ppal B'!$I$11*100,F95*'ppal B'!$I$11*100)) -> 0 | H95: #VALUE! | I95: =E95*(1+H95) -> #VALUE! | K95: =_xll.RDP.Data(A95,"TR.WACCBeta") -> No universe defined.
A96: AUDC.O | B96: {=_xll.RDP.Data(A96,"CF_BID")} -> 8.86 | C96: {=_xll.RDP.Data(A96,"CF_ASK")} -> 8.93 | D96: =(B96+C96)/2 -> 8.895 | E96: 0 | F96: 0 | G96: =IF('ppal B'!$I$11=0,0,IF('ppal B'!$I$11>0,E96*'ppal B'!$I$11*100,F96*'ppal B'!$I$11*100)) -> 0 | H96: 8.865 | I96: =E96*(1+H96) -> 0 | K96: =_xll.RDP.Data(A96,"TR.WACCBeta") -> 0.94782491
A97: CDNA.O | B97: {=_xll.RDP.Data(A97,"CF_BID")} -> 16.51 | C97: {=_xll.RDP.Data(A97,"CF_ASK")} -> 16.56 | D97: =(B97+C97)/2 -> 16.535 | E97: 0 | F97: 0 | G97: =IF('ppal B'!$I$11=0,0,IF('ppal B'!$I$11>0,E97*'ppal B'!$I$11*100,F97*'ppal B'!$I$11*100)) -> 0 | H97: 16.335 | I97: =E97*(1+H97) -> 0 | K97: =_xll.RDP.Data(A97,"TR.WACCBeta") -> 2.4689168
A98: EDIT.O | B98: {=_xll.RDP.Data(A98,"CF_BID")} -> 3.12 | C98: {=_xll.RDP.Data(A98,"CF_ASK")} -> 3.13 | D98: =(B98+C98)/2 -> 3.125 | E98: 0 | F98: 0 | G98: =IF('ppal B'!$I$11=0,0,IF('ppal B'!$I$11>0,E98*'ppal B'!$I$11*100,F98*'ppal B'!$I$11*100)) -> 0 | H98: 3.085 | I98: =E98*(1+H98) -> 0 | K98: =_xll.RDP.Data(A98,"TR.WACCBeta") -> 2.1563471
A99: HP | B99: {=_xll.RDP.Data(A99,"CF_BID")} -> 35.79 | C99: {=_xll.RDP.Data(A99,"CF_ASK")} -> 35.85 | D99: =(B99+C99)/2 -> 35.82 | E99: 0 | F99: 0 | G99: =IF('ppal B'!$I$11=0,0,IF('ppal B'!$I$11>0,E99*'ppal B'!$I$11*100,F99*'ppal B'!$I$11*100)) -> 0 | H99: 35.835 | I99: =E99*(1+H99) -> 0 | K99: =_xll.RDP.Data(A99,"TR.WACCBeta") -> 0.55516319
A100: IOVA.O | B100: {=_xll.RDP.Data(A100,"CF_BID")} -> 3.47 | C100: {=_xll.RDP.Data(A100,"CF_ASK")} -> 3.48 | D100: =(B100+C100)/2 -> 3.475 | E100: 0 | F100: 0 | G100: =IF('ppal B'!$I$11=0,0,IF('ppal B'!$I$11>0,E100*'ppal B'!$I$11*100,F100*'ppal B'!$I$11*100)) -> 0 | H100: 3.775 | I100: =E100*(1+H100) -> 0 | K100: =_xll.RDP.Data(A100,"TR.WACCBeta") -> 0.7876512
A101: NTLA.O | B101: {=_xll.RDP.Data(A101,"CF_BID")} -> 13.82 | C101: {=_xll.RDP.Data(A101,"CF_ASK")} -> 13.84 | D101: =(B101+C101)/2 -> 13.83 | E101: 0 | F101: 0 | G101: =IF('ppal B'!$I$11=0,0,IF('ppal B'!$I$11>0,E101*'ppal B'!$I$11*100,F101*'ppal B'!$I$11*100)) -> 0 | H101: 13.88 | I101: =E101*(1+H101) -> 0 | K101: =_xll.RDP.Data(A101,"TR.WACCBeta") -> 2.035406
A102: NVMI.O | B102: {=_xll.RDP.Data(A102,"CF_BID")} -> 502.54 | C102: {=_xll.RDP.Data(A102,"CF_ASK")} -> 504.12 | D102: =(B102+C102)/2 -> 503.33 | E102: 0 | F102: 0 | G102: =IF('ppal B'!$I$11=0,0,IF('ppal B'!$I$11>0,E102*'ppal B'!$I$11*100,F102*'ppal B'!$I$11*100)) -> 0 | H102: 495.075 | I102: =E102*(1+H102) -> 0 | K102: =_xll.RDP.Data(A102,"TR.WACCBeta") -> 1.8366635
A103: PDD.O | B103: {=_xll.RDP.Data(A103,"CF_BID")} -> 100.18 | C103: {=_xll.RDP.Data(A103,"CF_ASK")} -> 100.22 | D103: =(B103+C103)/2 -> 100.2 | E103: 0 | F103: 0 | G103: =IF('ppal B'!$I$11=0,0,IF('ppal B'!$I$11>0,E103*'ppal B'!$I$11*100,F103*'ppal B'!$I$11*100)) -> 0 | H103: 99.815 | I103: =E103*(1+H103) -> 0 | K103: =_xll.RDP.Data(A103,"TR.WACCBeta") -> 0.052905001
A104: PTC.O | B104: {=_xll.RDP.Data(A104,"CF_BID")} -> 135.03 | C104: {=_xll.RDP.Data(A104,"CF_ASK")} -> 135.35 | D104: =(B104+C104)/2 -> 135.19 | E104: 0 | F104: 0 | G104: =IF('ppal B'!$I$11=0,0,IF('ppal B'!$I$11>0,E104*'ppal B'!$I$11*100,F104*'ppal B'!$I$11*100)) -> 0 | H104: 134.49 | I104: =E104*(1+H104) -> 0 | K104: =_xll.RDP.Data(A104,"TR.WACCBeta") -> 1.062901
B105: {=_xll.RDP.Data(A105,"CF_BID")} -> No universe defined. | C105: {=_xll.RDP.Data(A105,"CF_ASK")} -> No universe defined. | D105: =(B105+C105)/2 -> #VALUE! | E105: 0 | F105: 0 | G105: =IF('ppal B'!$I$11=0,0,IF('ppal B'!$I$11>0,E105*'ppal B'!$I$11*100,F105*'ppal B'!$I$11*100)) -> 0 | H105: #VALUE! | I105: =E105*(1+H105) -> #VALUE! | K105: =_xll.RDP.Data(A105,"TR.WACCBeta") -> No universe defined.
A106: SSYS.O | B106: {=_xll.RDP.Data(A106,"CF_BID")} -> 8.5 | C106: {=_xll.RDP.Data(A106,"CF_ASK")} -> 8.51 | D106: =(B106+C106)/2 -> 8.505 | E106: 0 | F106: 0 | G106: =IF('ppal B'!$I$11=0,0,IF('ppal B'!$I$11>0,E106*'ppal B'!$I$11*100,F106*'ppal B'!$I$11*100)) -> 0 | H106: 8.275 | I106: =E106*(1+H106) -> 0 | K106: =_xll.RDP.Data(A106,"TR.WACCBeta") -> 1.8931532
A107: TER.O | B107: {=_xll.RDP.Data(A107,"CF_BID")} -> 366.46 | C107: {=_xll.RDP.Data(A107,"CF_ASK")} -> 367.08 | D107: =(B107+C107)/2 -> 366.77 | E107: 0 | F107: 0 | G107: =IF('ppal B'!$I$11=0,0,IF('ppal B'!$I$11>0,E107*'ppal B'!$I$11*100,F107*'ppal B'!$I$11*100)) -> 0 | H107: 363.305 | I107: =E107*(1+H107) -> 0 | K107: =_xll.RDP.Data(A107,"TR.WACCBeta") -> 1.8702194
A108: TRMB.O | B108: {=_xll.RDP.Data(A108,"CF_BID")} -> 66.61 | C108: {=_xll.RDP.Data(A108,"CF_ASK")} -> 66.67 | D108: =(B108+C108)/2 -> 66.64 | E108: 0 | F108: 0 | G108: =IF('ppal B'!$I$11=0,0,IF('ppal B'!$I$11>0,E108*'ppal B'!$I$11*100,F108*'ppal B'!$I$11*100)) -> 0 | H108: 65.205 | I108: =E108*(1+H108) -> 0 | K108: =_xll.RDP.Data(A108,"TR.WACCBeta") -> 1.5224489
A109: WIX.O | B109: {=_xll.RDP.Data(A109,"CF_BID")} -> 64.82 | C109: {=_xll.RDP.Data(A109,"CF_ASK")} -> 64.97 | D109: =(B109+C109)/2 -> 64.895 | E109: 0 | F109: 0 | G109: =IF('ppal B'!$I$11=0,0,IF('ppal B'!$I$11>0,E109*'ppal B'!$I$11*100,F109*'ppal B'!$I$11*100)) -> 0 | H109: 65.05 | I109: =E109*(1+H109) -> 0 | K109: =_xll.RDP.Data(A109,"TR.WACCBeta") -> 1.128255
B110: {=_xll.RDP.Data(A110,"CF_BID")} -> No universe defined. | C110: {=_xll.RDP.Data(A110,"CF_ASK")} -> No universe defined. | D110: =(B110+C110)/2 -> #VALUE! | E110: 0 | F110: 0 | G110: =IF('ppal B'!$I$11=0,0,IF('ppal B'!$I$11>0,E110*'ppal B'!$I$11*100,F110*'ppal B'!$I$11*100)) -> 0 | H110: #VALUE! | I110: =E110*(1+H110) -> #VALUE! | K110: =_xll.RDP.Data(A110,"TR.WACCBeta") -> No universe defined.
A111: ABT | B111: {=_xll.RDP.Data(A111,"CF_BID")} -> 100.13 | C111: {=_xll.RDP.Data(A111,"CF_ASK")} -> 100.14 | D111: =(B111+C111)/2 -> 100.135 | E111: 0 | F111: 0 | G111: =IF('ppal B'!$I$11=0,0,IF('ppal B'!$I$11>0,E111*'ppal B'!$I$11*100,F111*'ppal B'!$I$11*100)) -> 0 | H111: 99.75 | I111: =E111*(1+H111) -> 0 | K111: =_xll.RDP.Data(A111,"TR.WACCBeta") -> 0.77821713
A112: AMN | B112: {=_xll.RDP.Data(A112,"CF_BID")} -> 18.61 | C112: {=_xll.RDP.Data(A112,"CF_ASK")} -> 18.66 | D112: =(B112+C112)/2 -> 18.635 | E112: 0 | F112: 0 | G112: =IF('ppal B'!$I$11=0,0,IF('ppal B'!$I$11>0,E112*'ppal B'!$I$11*100,F112*'ppal B'!$I$11*100)) -> 0 | H112: 17.94 | I112: =E112*(1+H112) -> 0 | K112: =_xll.RDP.Data(A112,"TR.WACCBeta") -> 0.21212423
B113: {=_xll.RDP.Data(A113,"CF_BID")} -> No universe defined. | C113: {=_xll.RDP.Data(A113,"CF_ASK")} -> No universe defined. | D113: =(B113+C113)/2 -> #VALUE! | E113: 0 | F113: 0 | G113: =IF('ppal B'!$I$11=0,0,IF('ppal B'!$I$11>0,E113*'ppal B'!$I$11*100,F113*'ppal B'!$I$11*100)) -> 0 | H113: #VALUE! | I113: =E113*(1+H113) -> #VALUE! | K113: =_xll.RDP.Data(A113,"TR.WACCBeta") -> No universe defined.
A114: BLK | B114: {=_xll.RDP.Data(A114,"CF_BID")} -> 1013.56 | C114: {=_xll.RDP.Data(A114,"CF_ASK")} -> 1014.12 | D114: =(B114+C114)/2 -> 1013.84 | E114: 0 | F114: 0 | G114: =IF('ppal B'!$I$11=0,0,IF('ppal B'!$I$11>0,E114*'ppal B'!$I$11*100,F114*'ppal B'!$I$11*100)) -> 0 | H114: 1002.635 | I114: =E114*(1+H114) -> 0 | K114: =_xll.RDP.Data(A114,"TR.WACCBeta") -> 1.4806085
A115: BSX | B115: {=_xll.RDP.Data(A115,"CF_BID")} -> 62.83 | C115: {=_xll.RDP.Data(A115,"CF_ASK")} -> 62.84 | D115: =(B115+C115)/2 -> 62.835 | E115: 0 | F115: 0 | G115: =IF('ppal B'!$I$11=0,0,IF('ppal B'!$I$11>0,E115*'ppal B'!$I$11*100,F115*'ppal B'!$I$11*100)) -> 0 | H115: 62.415 | I115: =E115*(1+H115) -> 0 | K115: =_xll.RDP.Data(A115,"TR.WACCBeta") -> 0.73256657
A116: BX | B116: {=_xll.RDP.Data(A116,"CF_BID")} -> 120.88 | C116: {=_xll.RDP.Data(A116,"CF_ASK")} -> 120.92 | D116: =(B116+C116)/2 -> 120.9 | E116: 0 | F116: 0 | G116: =IF('ppal B'!$I$11=0,0,IF('ppal B'!$I$11>0,E116*'ppal B'!$I$11*100,F116*'ppal B'!$I$11*100)) -> 0 | H116: 117.245 | I116: =E116*(1+H116) -> 0 | K116: =_xll.RDP.Data(A116,"TR.WACCBeta") -> 1.6725167
A117: CHRS.O | B117: {=_xll.RDP.Data(A117,"CF_BID")} -> 1.68 | C117: {=_xll.RDP.Data(A117,"CF_ASK")} -> 1.69 | D117: =(B117+C117)/2 -> 1.685 | E117: 0 | F117: 0 | G117: =IF('ppal B'!$I$11=0,0,IF('ppal B'!$I$11>0,E117*'ppal B'!$I$11*100,F117*'ppal B'!$I$11*100)) -> 0 | H117: 1.695 | I117: =E117*(1+H117) -> 0 | K117: =_xll.RDP.Data(A117,"TR.WACCBeta") -> 1.037054
A118: MRK | B118: {=_xll.RDP.Data(A118,"CF_BID")} -> 119.35 | C118: {=_xll.RDP.Data(A118,"CF_ASK")} -> 119.4 | D118: =(B118+C118)/2 -> 119.375 | E118: 0 | F118: 0 | G118: =IF('ppal B'!$I$11=0,0,IF('ppal B'!$I$11>0,E118*'ppal B'!$I$11*100,F118*'ppal B'!$I$11*100)) -> 0 | H118: 120.67 | I118: =E118*(1+H118) -> 0 | K118: =_xll.RDP.Data(A118,"TR.WACCBeta") -> 0.29911662
A119: VTRS.O | B119: {=_xll.RDP.Data(A119,"CF_BID")} -> 13.61 | C119: {=_xll.RDP.Data(A119,"CF_ASK")} -> 13.62 | D119: =(B119+C119)/2 -> 13.615 | E119: 0 | F119: 0 | G119: =IF('ppal B'!$I$11=0,0,IF('ppal B'!$I$11>0,E119*'ppal B'!$I$11*100,F119*'ppal B'!$I$11*100)) -> 0 | H119: 13.505 | I119: =E119*(1+H119) -> 0 | K119: =_xll.RDP.Data(A119,"TR.WACCBeta") -> 0.84439517
A120: TMO | B120: {=_xll.RDP.Data(A120,"CF_BID")} -> 508.92 | C120: {=_xll.RDP.Data(A120,"CF_ASK")} -> 509.2 | D120: =(B120+C120)/2 -> 509.06 | E120: 0 | F120: 0 | G120: =IF('ppal B'!$I$11=0,0,IF('ppal B'!$I$11>0,E120*'ppal B'!$I$11*100,F120*'ppal B'!$I$11*100)) -> 0 | H120: 501.43 | I120: =E120*(1+H120) -> 0 | K120: =_xll.RDP.Data(A120,"TR.WACCBeta") -> 0.96882921
A121: UNH | B121: {=_xll.RDP.Data(A121,"CF_BID")} -> 311.34 | C121: {=_xll.RDP.Data(A121,"CF_ASK")} -> 311.35 | D121: =(B121+C121)/2 -> 311.345 | E121: 0 | F121: 0 | G121: =IF('ppal B'!$I$11=0,0,IF('ppal B'!$I$11>0,E121*'ppal B'!$I$11*100,F121*'ppal B'!$I$11*100)) -> 0 | H121: 306.36 | I121: =E121*(1+H121) -> 0 | K121: =_xll.RDP.Data(A121,"TR.WACCBeta") -> 0.42292325
A122: ARKK.K | B122: {=_xll.RDP.Data(A122,"CF_BID")} -> 71.5 | C122: {=_xll.RDP.Data(A122,"CF_ASK")} -> 71.51 | D122: =(B122+C122)/2 -> 71.505 | E122: 0 | F122: 0 | G122: =IF('ppal B'!$I$11=0,0,IF('ppal B'!$I$11>0,E122*'ppal B'!$I$11*100,F122*'ppal B'!$I$11*100)) -> 0 | H122: 70.985 | I122: =E122*(1+H122) -> 0 | K122: =_xll.RDP.Data(A122,"TR.WACCBeta") -> NULL
A123: ARKG.K | B123: {=_xll.RDP.Data(A123,"CF_BID")} -> 27.64 | C123: {=_xll.RDP.Data(A123,"CF_ASK")} -> 27.65 | D123: =(B123+C123)/2 -> 27.645 | E123: 0 | F123: 0 | G123: =IF('ppal B'!$I$11=0,0,IF('ppal B'!$I$11>0,E123*'ppal B'!$I$11*100,F123*'ppal B'!$I$11*100)) -> 0 | H123: 27.545 | I123: =E123*(1+H123) -> 0 | K123: =_xll.RDP.Data(A123,"TR.WACCBeta") -> NULL
A124: DIS | B124: {=_xll.RDP.Data(A124,"CF_BID")} -> 101.03 | C124: {=_xll.RDP.Data(A124,"CF_ASK")} -> 101.05 | D124: =(B124+C124)/2 -> 101.04 | E124: 0 | F124: 0 | G124: =IF('ppal B'!$I$11=0,0,IF('ppal B'!$I$11>0,E124*'ppal B'!$I$11*100,F124*'ppal B'!$I$11*100)) -> 0 | H124: 99.385 | I124: =E124*(1+H124) -> 0 | K124: =_xll.RDP.Data(A124,"TR.WACCBeta") -> 1.4541991
A125: BUG.O | B125: {=_xll.RDP.Data(A125,"CF_BID")} -> 24.31 | C125: {=_xll.RDP.Data(A125,"CF_ASK")} -> 24.33 | D125: =(B125+C125)/2 -> 24.32 | E125: 0 | F125: 0 | G125: =IF('ppal B'!$I$11=0,0,IF('ppal B'!$I$11>0,E125*'ppal B'!$I$11*100,F125*'ppal B'!$I$11*100)) -> 0 | H125: 24.015 | I125: =E125*(1+H125) -> 0 | K125: =_xll.RDP.Data(A125,"TR.WACCBeta") -> NULL
... A130: XBI | B130: {=_xll.RDP.Data(A130,"CF_BID")} -> 130.8 | C130: {=_xll.RDP.Data(A130,"CF_ASK")} -> 130.82 | D130: =(B130+C130)/2 -> 130.81 | E130: 0 | F130: 0 | G130: =IF('ppal B'!$I$11=0,0,IF('ppal B'!$I$11>0,E130*'ppal B'!$I$11*100,F130*'ppal B'!$I$11*100)) -> 0 | H130: 132.46 | I130: =E130*(1+H130) -> 0 | K130: =_xll.RDP.Data(A130,"TR.WACCBeta") -> NULL
B131: {=_xll.RDP.Data(A131,"CF_BID")} -> No universe defined. | C131: {=_xll.RDP.Data(A131,"CF_ASK")} -> No universe defined. | D131: =(B131+C131)/2 -> #VALUE! | E131: 0 | F131: 0 | G131: =IF('ppal B'!$I$11=0,0,IF('ppal B'!$I$11>0,E131*'ppal B'!$I$11*100,F131*'ppal B'!$I$11*100)) -> 0 | H131: #VALUE! | I131: =E131*(1+H131) -> #VALUE! | K131: =_xll.RDP.Data(A131,"TR.WACCBeta") -> No universe defined.
A132: EA.O | B132: {=_xll.RDP.Data(A132,"CF_BID")} -> 202.35 | C132: {=_xll.RDP.Data(A132,"CF_ASK")} -> 202.4 | D132: =(B132+C132)/2 -> 202.375 | E132: 0 | F132: 0 | G132: =IF('ppal B'!$I$11=0,0,IF('ppal B'!$I$11>0,E132*'ppal B'!$I$11*100,F132*'ppal B'!$I$11*100)) -> 0 | H132: 202.73 | I132: =E132*(1+H132) -> 0 | K132: =_xll.RDP.Data(A132,"TR.WACCBeta") -> 0.71001595
A133: NVDA.O | B133: {=_xll.RDP.Data(A133,"CF_BID")} -> 188.18 | C133: {=_xll.RDP.Data(A133,"CF_ASK")} -> 188.19 | D133: =(B133+C133)/2 -> 188.185 | E133: 0 | F133: 0 | G133: =IF('ppal B'!$I$11=0,0,IF('ppal B'!$I$11>0,E133*'ppal B'!$I$11*100,F133*'ppal B'!$I$11*100)) -> 0 | H133: 188.33 | I133: =E133*(1+H133) -> 0 | K133: =_xll.RDP.Data(A133,"TR.WACCBeta") -> 2.3296569
A134: TTWO.O | B134: {=_xll.RDP.Data(A134,"CF_BID")} -> 201.29 | C134: {=_xll.RDP.Data(A134,"CF_ASK")} -> 201.59 | D134: =(B134+C134)/2 -> 201.44 | E134: 0 | F134: 0 | G134: =IF('ppal B'!$I$11=0,0,IF('ppal B'!$I$11>0,E134*'ppal B'!$I$11*100,F134*'ppal B'!$I$11*100)) -> 0 | H134: 199.61 | I134: =E134*(1+H134) -> 0 | K134: =_xll.RDP.Data(A134,"TR.WACCBeta") -> 0.97355964
B135: {=_xll.RDP.Data(A135,"CF_BID")} -> No universe defined. | C135: {=_xll.RDP.Data(A135,"CF_ASK")} -> No universe defined. | D135: =(B135+C135)/2 -> #VALUE! | E135: 0 | F135: 0 | G135: =IF('ppal B'!$I$11=0,0,IF('ppal B'!$I$11>0,E135*'ppal B'!$I$11*100,F135*'ppal B'!$I$11*100)) -> 0 | H135: #VALUE! | I135: =E135*(1+H135) -> #VALUE! | K135: =_xll.RDP.Data(A135,"TR.WACCBeta") -> No universe defined.
B136: {=_xll.RDP.Data(A136,"CF_BID")} -> No universe defined. | C136: {=_xll.RDP.Data(A136,"CF_ASK")} -> No universe defined. | D136: =(B136+C136)/2 -> #VALUE! | E136: 0 | F136: 0 | G136: =IF('ppal B'!$I$11=0,0,IF('ppal B'!$I$11>0,E136*'ppal B'!$I$11*100,F136*'ppal B'!$I$11*100)) -> 0 | H136: #VALUE! | I136: =E136*(1+H136) -> #VALUE! | K136: =_xll.RDP.Data(A136,"TR.WACCBeta") -> No universe defined.
B137: {=_xll.RDP.Data(A137,"CF_BID")} -> No universe defined. | C137: {=_xll.RDP.Data(A137,"CF_ASK")} -> No universe defined. | D137: =(B137+C137)/2 -> #VALUE! | E137: 0 | F137: 0 | G137: =IF('ppal B'!$I$11=0,0,IF('ppal B'!$I$11>0,E137*'ppal B'!$I$11*100,F137*'ppal B'!$I$11*100)) -> 0 | H137: #VALUE! | I137: =E137*(1+H137) -> #VALUE! | K137: =_xll.RDP.Data(A137,"TR.WACCBeta") -> No universe defined.
A138: XLP | B138: {=_xll.RDP.Data(A138,"CF_BID")} -> 81.39 | C138: {=_xll.RDP.Data(A138,"CF_ASK")} -> 81.4 | D138: =(B138+C138)/2 -> 81.395 | E138: 0 | F138: 0 | G138: =IF('ppal B'!$I$11=0,0,IF('ppal B'!$I$11>0,E138*'ppal B'!$I$11*100,F138*'ppal B'!$I$11*100)) -> 0 | H138: 81.645 | I138: =E138*(1+H138) -> 0 | K138: =_xll.RDP.Data(A138,"TR.WACCBeta") -> NULL
A139: RBOT.P | B139: {=_xll.RDP.Data(A139,"CF_BID")} -> The record could not be found (Error code: 0) | C139: {=_xll.RDP.Data(A139,"CF_ASK")} -> The record could not be found (Error code: 0) | D139: =(B139+C139)/2 -> #VALUE! | E139: 0 | F139: 0 | G139: =IF('ppal B'!$I$11=0,0,IF('ppal B'!$I$11>0,E139*'ppal B'!$I$11*100,F139*'ppal B'!$I$11*100)) -> 0 | H139: #VALUE! | I139: =E139*(1+H139) -> #VALUE! | K139: =_xll.RDP.Data(A139,"TR.WACCBeta") -> 1.8145759
A140: BYND.O | B140: {=_xll.RDP.Data(A140,"CF_BID")} -> 0.6448 | C140: {=_xll.RDP.Data(A140,"CF_ASK")} -> 0.6449 | D140: =(B140+C140)/2 -> 0.64485 | E140: 0 | F140: 0 | G140: =IF('ppal B'!$I$11=0,0,IF('ppal B'!$I$11>0,E140*'ppal B'!$I$11*100,F140*'ppal B'!$I$11*100)) -> 0 | H140: 0.6472 | I140: =E140*(1+H140) -> 0 | K140: =_xll.RDP.Data(A140,"TR.WACCBeta") -> 2.6372875
A141: EWY | B141: {=_xll.RDP.Data(A141,"CF_BID")} -> 139.88 | C141: {=_xll.RDP.Data(A141,"CF_ASK")} -> 139.92 | D141: =(B141+C141)/2 -> 139.9 | E141: 0 | F141: 0 | G141: =IF('ppal B'!$I$11=0,0,IF('ppal B'!$I$11>0,E141*'ppal B'!$I$11*100,F141*'ppal B'!$I$11*100)) -> 0 | H141: 136.94 | I141: =E141*(1+H141) -> 0 | K141: =_xll.RDP.Data(A141,"TR.WACCBeta") -> NULL
A142: EWT | B142: {=_xll.RDP.Data(A142,"CF_BID")} -> 77.88 | C142: {=_xll.RDP.Data(A142,"CF_ASK")} -> 77.89 | D142: =(B142+C142)/2 -> 77.885 | E142: 0 | F142: 0 | G142: =IF('ppal B'!$I$11=0,0,IF('ppal B'!$I$11>0,E142*'ppal B'!$I$11*100,F142*'ppal B'!$I$11*100)) -> 0 | H142: 77.295 | I142: =E142*(1+H142) -> 0 | K142: =_xll.RDP.Data(A142,"TR.WACCBeta") -> NULL
B143: {=_xll.RDP.Data(A143,"CF_BID")} -> No universe defined. | C143: {=_xll.RDP.Data(A143,"CF_ASK")} -> No universe defined. | D143: =(B143+C143)/2 -> #VALUE! | E143: 0 | F143: 0 | G143: =IF('ppal B'!$I$11=0,0,IF('ppal B'!$I$11>0,E143*'ppal B'!$I$11*100,F143*'ppal B'!$I$11*100)) -> 0 | H143: #VALUE! | I143: =E143*(1+H143) -> #VALUE! | K143: =_xll.RDP.Data(A143,"TR.WACCBeta") -> No universe defined.
A144: EIDO.K | B144: {=_xll.RDP.Data(A144,"CF_BID")} -> 16.1 | C144: {=_xll.RDP.Data(A144,"CF_ASK")} -> 16.11 | D144: =(B144+C144)/2 -> 16.105 | E144: 0 | F144: 0 | G144: =IF('ppal B'!$I$11=0,0,IF('ppal B'!$I$11>0,E144*'ppal B'!$I$11*100,F144*'ppal B'!$I$11*100)) -> 0 | H144: 16.055 | I144: =E144*(1+H144) -> 0 | K144: =_xll.RDP.Data(A144,"TR.WACCBeta") -> NULL
A145: EWM | B145: {=_xll.RDP.Data(A145,"CF_BID")} -> 28.62 | C145: {=_xll.RDP.Data(A145,"CF_ASK")} -> 28.63 | D145: =(B145+C145)/2 -> 28.625 | E145: 0 | F145: 0 | G145: =IF('ppal B'!$I$11=0,0,IF('ppal B'!$I$11>0,E145*'ppal B'!$I$11*100,F145*'ppal B'!$I$11*100)) -> 0 | H145: 28.585 | I145: =E145*(1+H145) -> 0 | K145: =_xll.RDP.Data(A145,"TR.WACCBeta") -> NULL
A146: EWS | B146: {=_xll.RDP.Data(A146,"CF_BID")} -> 29.13 | C146: {=_xll.RDP.Data(A146,"CF_ASK")} -> 29.14 | D146: =(B146+C146)/2 -> 29.135 | E146: 0 | F146: 0 | G146: =IF('ppal B'!$I$11=0,0,IF('ppal B'!$I$11>0,E146*'ppal B'!$I$11*100,F146*'ppal B'!$I$11*100)) -> 0 | H146: 28.925 | I146: =E146*(1+H146) -> 0 | K146: =_xll.RDP.Data(A146,"TR.WACCBeta") -> NULL
A147: VNM | B147: {=_xll.RDP.Data(A147,"CF_BID")} -> 18.26 | C147: {=_xll.RDP.Data(A147,"CF_ASK")} -> 18.27 | D147: =(B147+C147)/2 -> 18.265 | E147: 0 | F147: 0 | G147: =IF('ppal B'!$I$11=0,0,IF('ppal B'!$I$11>0,E147*'ppal B'!$I$11*100,F147*'ppal B'!$I$11*100)) -> 0 | H147: 18.255 | I147: =E147*(1+H147) -> 0 | K147: =_xll.RDP.Data(A147,"TR.WACCBeta") -> NULL
A148: THD | B148: {=_xll.RDP.Data(A148,"CF_BID")} -> 71.99 | C148: {=_xll.RDP.Data(A148,"CF_ASK")} -> 72.09 | D148: =(B148+C148)/2 -> 72.04 | E148: 0 | F148: 0 | G148: =IF('ppal B'!$I$11=0,0,IF('ppal B'!$I$11>0,E148*'ppal B'!$I$11*100,F148*'ppal B'!$I$11*100)) -> 0 | H148: 71.705 | I148: =E148*(1+H148) -> 0 | K148: =_xll.RDP.Data(A148,"TR.WACCBeta") -> NULL
A149: CRM | B149: {=_xll.RDP.Data(A149,"CF_BID")} -> 172.84 | C149: {=_xll.RDP.Data(A149,"CF_ASK")} -> 172.92 | D149: =(B149+C149)/2 -> 172.88 | E149: 0 | F149: 0 | G149: =IF('ppal B'!$I$11=0,0,IF('ppal B'!$I$11>0,E149*'ppal B'!$I$11*100,F149*'ppal B'!$I$11*100)) -> 0 | H149: 171.06 | I149: =E149*(1+H149) -> 0 | K149: =_xll.RDP.Data(A149,"TR.WACCBeta") -> 1.2248123
A150: TDOC.P | B150: {=_xll.RDP.Data(A150,"CF_BID")} -> 5.23 | C150: {=_xll.RDP.Data(A150,"CF_ASK")} -> 5.24 | D150: =(B150+C150)/2 -> 5.235 | E150: 0 | F150: 0 | G150: =IF('ppal B'!$I$11=0,0,IF('ppal B'!$I$11>0,E150*'ppal B'!$I$11*100,F150*'ppal B'!$I$11*100)) -> 0 | H150: 5.065 | I150: =E150*(1+H150) -> 0 | K150: =_xll.RDP.Data(A150,"TR.WACCBeta") -> 2.0861052
A151: PLTR.O | B151: {=_xll.RDP.Data(A151,"CF_BID")} -> 133.31 | C151: {=_xll.RDP.Data(A151,"CF_ASK")} -> 133.34 | D151: =(B151+C151)/2 -> 133.325 | E151: 0 | F151: 0 | G151: =IF('ppal B'!$I$11=0,0,IF('ppal B'!$I$11>0,E151*'ppal B'!$I$11*100,F151*'ppal B'!$I$11*100)) -> 0 | H151: 132.23 | I151: =E151*(1+H151) -> 0 | K151: =_xll.RDP.Data(A151,"TR.WACCBeta") -> 1.6527615
A152: CSCO.O | B152: {=_xll.RDP.Data(A152,"CF_BID")} -> 81.77 | C152: {=_xll.RDP.Data(A152,"CF_ASK")} -> 81.78 | D152: =(B152+C152)/2 -> 81.775 | E152: 0 | F152: 0 | G152: =IF('ppal B'!$I$11=0,0,IF('ppal B'!$I$11>0,E152*'ppal B'!$I$11*100,F152*'ppal B'!$I$11*100)) -> 0 | H152: 81.615 | I152: =E152*(1+H152) -> 0 | K152: =_xll.RDP.Data(A152,"TR.WACCBeta") -> 0.84909726
B153: {=_xll.RDP.Data(A153,"CF_BID")} -> No universe defined. | C153: {=_xll.RDP.Data(A153,"CF_ASK")} -> No universe defined. | D153: =(B153+C153)/2 -> #VALUE! | E153: 0 | F153: 0 | G153: =IF('ppal B'!$I$11=0,0,IF('ppal B'!$I$11>0,E153*'ppal B'!$I$11*100,F153*'ppal B'!$I$11*100)) -> 0 | H153: #VALUE! | I153: =E153*(1+H153) -> #VALUE! | K153: =_xll.RDP.Data(A153,"TR.WACCBeta") -> No universe defined.
A154: QQQ.O | B154: {=_xll.RDP.Data(A154,"CF_BID")} -> 613.9 | C154: {=_xll.RDP.Data(A154,"CF_ASK")} -> 613.92 | D154: =(B154+C154)/2 -> 613.91 | E154: 0.0118 | F154: 0.0118 | G154: =IF('ppal B'!$I$11=0,0,IF('ppal B'!$I$11>0,E154*'ppal B'!$I$11*100,F154*'ppal B'!$I$11*100)) -> 0 | H154: 611.135 | I154: =E154*(1+H154) -> 7.223193 | K154: =_xll.RDP.Data(A154,"TR.WACCBeta") -> NULL
A155: SLV | B155: {=_xll.RDP.Data(A155,"CF_BID")} -> 68.08 | C155: {=_xll.RDP.Data(A155,"CF_ASK")} -> 68.09 | D155: =(B155+C155)/2 -> 68.085 | E155: 0 | F155: 0 | G155: =IF('ppal B'!$I$11=0,0,IF('ppal B'!$I$11>0,E155*'ppal B'!$I$11*100,F155*'ppal B'!$I$11*100)) -> 0 | H155: 66.955 | I155: =E155*(1+H155) -> 0 | K155: =_xll.RDP.Data(A155,"TR.WACCBeta") -> NULL
A156: RKLB.O | B156: {=_xll.RDP.Data(A156,"CF_BID")} -> 70.95 | C156: {=_xll.RDP.Data(A156,"CF_ASK")} -> 70.99 | D156: =(B156+C156)/2 -> 70.97 | E156: 0 | F156: 0 | G156: =IF('ppal B'!$I$11=0,0,IF('ppal B'!$I$11>0,E156*'ppal B'!$I$11*100,F156*'ppal B'!$I$11*100)) -> 0 | H156: 70.29 | I156: =E156*(1+H156) -> 0 | K156: =_xll.RDP.Data(A156,"TR.WACCBeta") -> 2.2854784
A157: PLTM.K | B157: {=_xll.RDP.Data(A157,"CF_BID")} -> 19.76 | C157: {=_xll.RDP.Data(A157,"CF_ASK")} -> 19.78 | D157: =(B157+C157)/2 -> 19.77 | E157: 0 | F157: 0 | G157: =IF('ppal B'!$I$11=0,0,IF('ppal B'!$I$11>0,E157*'ppal B'!$I$11*100,F157*'ppal B'!$I$11*100)) -> 0 | H157: 19.45 | I157: =E157*(1+H157) -> 0 | K157: =_xll.RDP.Data(A157,"TR.WACCBeta") -> NULL
A158: CPER.K | B158: {=_xll.RDP.Data(A158,"CF_BID")} -> 36.71 | C158: {=_xll.RDP.Data(A158,"CF_ASK")} -> 36.73 | D158: =(B158+C158)/2 -> 36.72 | E158: 0 | F158: 0 | G158: =IF('ppal B'!$I$11=0,0,IF('ppal B'!$I$11>0,E158*'ppal B'!$I$11*100,F158*'ppal B'!$I$11*100)) -> 0 | H158: 36.335 | I158: =E158*(1+H158) -> 0 | K158: =_xll.RDP.Data(A158,"TR.WACCBeta") -> NULL
A159: DIA | B159: {=_xll.RDP.Data(A159,"CF_BID")} -> 479.33 | C159: {=_xll.RDP.Data(A159,"CF_ASK")} -> 479.37 | D159: =(B159+C159)/2 -> 479.35 | E159: 0 | F159: 0 | G159: =IF('ppal B'!$I$11=0,0,IF('ppal B'!$I$11>0,E159*'ppal B'!$I$11*100,F159*'ppal B'!$I$11*100)) -> 0 | H159: 477 | I159: =E159*(1+H159) -> 0 | K159: =_xll.RDP.Data(A159,"TR.WACCBeta") -> NULL
A160: RBLX.P | B160: {=_xll.RDP.Data(A160,"CF_BID")} -> 58.55 | C160: {=_xll.RDP.Data(A160,"CF_ASK")} -> 58.7 | D160: =(B160+C160)/2 -> 58.625 | E160: 0 | F160: 0 | G160: =IF('ppal B'!$I$11=0,0,IF('ppal B'!$I$11>0,E160*'ppal B'!$I$11*100,F160*'ppal B'!$I$11*100)) -> 0 | H160: 57.955 | I160: =E160*(1+H160) -> 0 | K160: =_xll.RDP.Data(A160,"TR.WACCBeta") -> 1.6205865
A161: JPM | B161: {=_xll.RDP.Data(A161,"CF_BID")} -> 311.17 | C161: {=_xll.RDP.Data(A161,"CF_ASK")} -> 311.25 | D161: =(B161+C161)/2 -> 311.21 | E161: 0.0121 | F161: 0.0121 | G161: =IF('ppal B'!$I$11=0,0,IF('ppal B'!$I$11>0,E161*'ppal B'!$I$11*100,F161*'ppal B'!$I$11*100)) -> 0 | H161: 308.365 | I161: =E161*(1+H161) -> 3.7433165 | K161: =_xll.RDP.Data(A161,"TR.WACCBeta") -> 1.0618305
...

Sheet UF
A6: Fecha | B6: Contraparte | C6: Monto UF | D6: Tasa Spot | E6: Dif Inicial | F6: vto | G6: Días | H6: Precio Cierre | I6: MTM
A7: 45848 | B7: BCI | C7: 30000 | D7: 0.0332 | E7: 3.0388 | J7: =3.39-3.08 -> 0.31
C26: =SUM(C7:C25) -> 30000 | I26: =SUM(I7:I20) -> 0
A31: REALIZADO
A33: Fecha | B33: Contraparte | C33: Monto UF | D33: Tasa Spot | E33: Precio Inicial | F33: vto | G33: Días | H33: Precio Cierre | I33: MTM
I45: =SUM(I34:I44) -> 0

Sheet t10y
D1: FUTUROS T10Y
A4: REALIZADO
A6: Instumento | B6: fecha | C6: Contraparte | D6: Pos | E6: ytm inicial | F6: ytm merc | G6: Precio Inicial | H6: vto | I6: Precio Cierre | J6: result | K6: fecha cierre | L6: EXP
A7: WNH6 | C7: CS-K | E7: 0.0493 | F7: 0.0485 | G7: 116.34375 | H7: =G7*1000*D7 -> 0 | I7: 117.65625 | J7: =(I7-G7)*D7*1000 -> 0
J48: =SUM(J7:J47) -> 0
A55: Instumento | B55: fecha | C55: Contraparte | D55: Pos | E55: ytm inicial | F55: ytm merc | G55: Precio Inicial | H55: vto | I55: Precio Cierre | J55: result | K55: fecha cierre
A56: WNH6 | B56: 45992 | C56: CS-K | D56: 9 | G56: 119.59375 | H56: 1076343.8 | I56: 118.65625 | J56: -8437.5 | K56: 46036
A57: WNH6 | B57: 46042 | C57: CS-K | D57: 5 | E57: 0.0493 | F57: 0.0485 | G57: 116.34375 | H57: 581718.75 | I57: 117.65625 | J57: 6562.5 | K57: 46044
D87: =SUM(D56:D86) -> 14 | J87: =SUM(J56:J86) -> -1875

Sheet cartera
A1: CARTERA RENTA FIJA
A3: BANCO | B3: ISIN | C3: Name | D3: Monto Compra | E3: Coupon | F3: Maturity | G3: PRECIO COMPRA | H3: Precio 31-Dic-2021 | I3: Precio 31-Dic-2025 | J3: Precio Mercado (29-05) | K3: CurrYield | L3: YLD_YTM_ask | M3: DUR_MID | N3: rtg_sp | O3: rtg_moody | P3: rtg_fitch | Q3: industry_subgroup | R3: PAIS | S3: crncy | T3: callable | U3: NXT_CALL_DT | V3: payment_rank | W3: Monto Compra | X3: Costo | Y3: status | Z3: VP | AA3: MTM | AB3: MTM trib | AC3: VPxYTM | AD3: VPxDur | AE3: Rt % año | AF3: INTERESES x AÑO | AG3: FECHA COMPRA | AH3: VENTA | AI3: compra | AJ3: LTV | AK3: LTV usd
A4: SCH | B4: XS145DGFDJHDKJ | C4: bono1 | D4: 588.23529 | E4: 1.5 | F4: 31-07-2040 | G4: 106 | H4: 29.433 | I4: 64.825 | J4: 57.908 | K4: =IF(AF4="","",AF4/Z4) -> 0.025903157 | L4: 13.423314 | M4: 7.4970215 | N4: NR | O4: #N/A N/A | P4: WD | Q4: Sovereign | R4: EC | S4: USD | T4: SINKABLE | V4: Sr Unsecured | W4: =+D4*G4/100 -> 623.52941 | X4: =+D4*G4/100 -> 623.52941 | Z4: =+D4*J4/100 -> 340.63529 | AA4: =IF(+I4=0,AB4,D4*(J4-I4)/100) -> -40.688235 | AB4: =+$D4*($J4-$G4)/100 -> -282.89412 | AC4: =+Z4*L4 -> 4572.4547 | AD4: =+Z4*M4 -> 2553.7501 | AE4: =+AA4/X4 -> -0.065254717 | AF4: =+D4*E4/100 -> 8.8235294 | AJ4: 0 | AK4: =AJ4*Z4 -> 0
A5: SCH | B5: XS145DGFDJHDKJ | C5: bono2 | D5: 32352.941 | E5: 0 | F5: 46177 | G5: 98.236688 | I5: 98.5194 | J5: 98.881 | K5: =IF(AF5="","",AF5/Z5) -> 0.037029686 | L5: 3.6615324 | M5: 0.30684932 | N5: #N/A N/A | O5: #N/A N/A | P5: #N/A N/A | Q5: Sovereign | R5: US | S5: USD | T5: NORMAL | V5: Unsecured | W5: =+D5*G5/100 -> 31782.458 | X5: =+D5*G5/100 -> 31782.458 | Z5: =+D5*J5/100 -> 31990.912 | AA5: =IF(+I5=0,AB5,D5*(J5-I5)/100) -> 116.98824 | AB5: =+$D5*($J5-$G5)/100 -> 208.45404 | AC5: =+Z5*L5 -> 117135.76 | AD5: =+Z5*M5 -> 9816.3894 | AE5: =+AA5/X5 -> 0.0036809059 | AF5: =+D5*L5/100 -> 1184.6134 | AJ5: 0.95 | AK5: =AJ5*Z5 -> 30391.366
A6: SCH | B6: XS145DGFDJHDKJ | C6: bono3 | D6: 1544.1176 | E6: 0 | F6: 46177 | G6: 98.24 | I6: 98.5194 | J6: 98.881 | K6: =IF(AF6="","",AF6/Z6) -> 0.037029686 | L6: 3.6615324 | M6: 0.30684932 | N6: #N/A N/A | O6: #N/A N/A | P6: #N/A N/A | Q6: Sovereign | R6: US | S6: USD | T6: NORMAL | V6: Unsecured | W6: =+D6*G6/100 -> 1516.9412 | X6: =+D6*G6/100 -> 1516.9412 | Z6: =+D6*J6/100 -> 1526.839 | AA6: =IF(+I6=0,AB6,D6*(J6-I6)/100) -> 5.5835294 | AB6: =+$D6*($J6-$G6)/100 -> 9.8977941 | AC6: =+Z6*L6 -> 5590.5703 | AD6: =+Z6*M6 -> 468.50949 | AE6: =+AA6/X6 -> 0.0036807818 | AF6: =+D6*L6/100 -> 56.538367 | AG6: 45120 | AJ6: 0.95 | AK6: =AJ6*Z6 -> 1450.497 | AN6: LTV RF
A7: SCH | B7: XS145DGFDJHDKJ | C7: bono4 | D7: 1973.5294 | E7: 0 | F7: 46177 | G7: 98.236 | I7: 98.5194 | J7: 98.881 | K7: =IF(AF7="","",AF7/Z7) -> 0.037029686 | L7: 3.6615324 | M7: 0.30684932 | N7: #N/A N/A | O7: #N/A N/A | P7: #N/A N/A | Q7: Sovereign | R7: US | S7: USD | T7: NORMAL | V7: Unsecured | W7: =+D7*G7/100 -> 1938.7164 | X7: =+D7*G7/100 -> 1938.7164 | Z7: =+D7*J7/100 -> 1951.4456 | AA7: =IF(+I7=0,AB7,D7*(J7-I7)/100) -> 7.1362824 | AB7: =+$D7*($J7-$G7)/100 -> 12.729265 | AC7: =+Z7*L7 -> 7145.2813 | AD7: =+Z7*M7 -> 598.79975 | AE7: =+AA7/X7 -> 0.0036809316 | AF7: =+D7*L7/100 -> 72.261418 | AG7: 45120 | AJ7: 0.95 | AK7: =AJ7*Z7 -> 1853.8733 | AM7: DB | AN7: =SUMIF($A$4:$A$25,AM7,$AK$4:$AK$25) -> 0
A8: SCH | B8: XS145DGFDJHDKJ | C8: bono5 | D8: 764.70588 | E8: 0 | F8: 46177 | G8: 98.1886 | I8: 98.5194 | J8: 98.881 | K8: =IF(AF8="","",AF8/Z8) -> 0.037029686 | L8: 3.6615324 | M8: 0.30684932 | N8: #N/A N/A | O8: #N/A N/A | P8: #N/A N/A | Q8: Sovereign | R8: US | S8: USD | T8: NORMAL | V8: Unsecured | W8: =+D8*G8/100 -> 750.854 | X8: =+D8*G8/100 -> 750.854 | Z8: =+D8*J8/100 -> 756.14882 | AA8: =IF(+I8=0,AB8,D8*(J8-I8)/100) -> 2.7651765 | AB8: =+$D8*($J8-$G8)/100 -> 5.2948235 | AC8: =+Z8*L8 -> 2768.6634 | AD8: =+Z8*M8 -> 232.02375 | AE8: =+AA8/X8 -> 0.0036827086 | AF8: =+D8*L8/100 -> 27.999953 | AJ8: 0.85 | AK8: =AJ8*Z8 -> 642.7265 | AM8: MS-K | AN8: =SUMIF($A$4:$A$25,AM8,$AK$4:$AK$25) -> 0
A9: SCH | B9: XS145DGFDJHDKJ | C9: bono6 | D9: 17264.706 | E9: 0 | F9: 46177 | G9: 98.255083 | I9: 98.5194 | J9: 98.881 | K9: =IF(AF9="","",AF9/Z9) -> 0.037029686 | L9: 3.6615324 | M9: 0.30684932 | N9: #N/A N/A | O9: #N/A N/A | P9: #N/A N/A | Q9: Sovereign | R9: US | S9: USD | T9: NORMAL | V9: Unsecured | W9: =+D9*G9/100 -> 16963.451 | X9: =+D9*G9/100 -> 16963.451 | Z9: =+D9*J9/100 -> 17071.514 | AA9: =IF(+I9=0,AB9,D9*(J9-I9)/100) -> 62.429176 | AB9: =+$D9*($J9-$G9)/100 -> 108.06273 | AC9: =+Z9*L9 -> 62507.9 | AD9: =+Z9*M9 -> 5238.3823 | AE9: =+AA9/X9 -> 0.0036802167 | AF9: =+D9*L9/100 -> 632.15279 | AJ9: 0.99 | AK9: =AJ9*Z9 -> 16900.799 | AM9: MS | AN9: =SUMIF($A$4:$A$25,AM9,$AK$4:$AK$25) -> 0
A10: SCH | B10: XS145DGFDJHDKJ | C10: bono7 | D10: 794.11765 | E10: 0 | F10: 46177 | G10: 98.191375 | I10: 98.5194 | J10: 98.881 | K10: =IF(AF10="","",AF10/Z10) -> 0.037029686 | L10: 3.6615324 | M10: 0.30684932 | N10: #N/A N/A | O10: #N/A N/A | P10: #N/A N/A | Q10: Sovereign | R10: US | S10: USD | T10: NORMAL | V10: Unsecured | W10: =+D10*G10/100 -> 779.75504 | X10: =+D10*G10/100 -> 779.75504 | Z10: =+D10*J10/100 -> 785.23147 | AA10: =IF(+I10=0,AB10,D10*(J10-I10)/100) -> 2.8715294 | AB10: =+$D10*($J10-$G10)/100 -> 5.4764338 | AC10: =+Z10*L10 -> 2875.1504 | AD10: =+Z10*M10 -> 240.94774 | AE10: =+AA10/X10 -> 0.0036826045 | AF10: =+D10*L10/100 -> 29.076875 | AG10: 45120 | AJ10: 0.95 | AK10: =AJ10*Z10 -> 745.9699 | AM10: UBS-H | AN10: =SUMIF($A$4:$A$25,AM10,$AK$4:$AK$25) -> 0
A11: SCH | B11: XS145DGFDJHDKJ | C11: bono8 | D11: 1823.5294 | E11: 0 | F11: 46177 | G11: 99.07175 | I11: 98.5194 | J11: 99.07175 | K11: =IF(AF11="","",AF11/Z11) -> 0.03695839 | L11: 3.6615324 | M11: 0.30684932 | N11: #N/A N/A | O11: #N/A N/A | P11: #N/A N/A | Q11: Sovereign | R11: US | S11: USD | T11: NORMAL | V11: Unsecured | W11: =+D11*G11/100 -> 1806.6025 | X11: =+D11*G11/100 -> 1806.6025 | Z11: =+D11*J11/100 -> 1806.6025 | AA11: =IF(+I11=0,AB11,D11*(J11-I11)/100) -> 10.072265 | AB11: =+$D11*($J11-$G11)/100 -> 0 | AC11: =+Z11*L11 -> 6614.9335 | AD11: =+Z11*M11 -> 554.35474 | AE11: =+AA11/X11 -> 0.0055752523 | AF11: =+D11*L11/100 -> 66.769119 | AG11: 45120 | AJ11: 0.95 | AK11: =AJ11*Z11 -> 1716.2724 | AM11: UBS-H | AN11: =SUMIF($A$4:$A$25,AM11,$AK$4:$AK$25) -> 0
A12: SCH | B12: XS145DGFDJHDKJ | C12: bono9 | D12: 97.058824 | E12: 8.25 | F12: 17-01-2034 | G12: 98.51 | H12: 119.22 | I12: 120.489 | J12: 120.197 | K12: =IF(AF12="","",AF12/Z12) -> 0.06863732 | L12: 5.0995894 | M12: 6.1421473 | N12: BBB- | O12: Baa3 | P12: BBB | Q12: Metal-Iron | R12: BR | S12: USD | T12: AT MATURITY | V12: Sr Unsecured | W12: =+D12*G12/100 -> 95.612647 | X12: =+D12*G12/100 -> 95.612647 | Z12: =+D12*J12/100 -> 116.66179 | AA12: =IF(+I12=0,AB12,D12*(J12-I12)/100) -> -0.28341176 | AB12: =+$D12*($J12-$G12)/100 -> 21.049147 | AC12: =+Z12*L12 -> 594.92725 | AD12: =+Z12*M12 -> 716.55393 | AE12: =+AA12/X12 -> -0.0029641661 | AF12: =+D12*E12/100 -> 8.0073529 | AK12: =AJ12*Z12 -> 0
A13: SCH | B13: XS145DGFDJHDKJ | C13: bono10 | D13: 147.05882 | E13: 6.95 | F13: 07-13-2027 | G13: 101.6 | H13: 70.768 | I13: 100.773 | J13: 100.977 | K13: =IF(AF13="","",AF13/Z13) -> 0.068827555 | L13: 6.0445878 | M13: 1.3921988 | N13: CCC+ | O13: #N/A N/A | P13: CCC- | Q13: Oil Comp-Integrated | R13: AR | S13: USD | T13: AT MATURITY | V13: Sr Unsecured | W13: =+D13*G13/100 -> 149.41176 | X13: =+D13*G13/100 -> 149.41176 | Z13: =+D13*J13/100 -> 148.49559 | AA13: =IF(+I13=0,AB13,D13*(J13-I13)/100) -> 0.3 | AB13: =+$D13*($J13-$G13)/100 -> -0.91617647 | AC13: =+Z13*L13 -> 897.59463 | AD13: =+Z13*M13 -> 206.73538 | AE13: =+AA13/X13 -> 0.002007874 | AF13: =+D13*E13/100 -> 10.220588 | AJ13: 0 | AK13: =AJ13*Z13 -> 0
A14: SCH | B14: XS145DGFDJHDKJ | C14: bono11 | D14: 1470.5882 | E14: 5.75 | F14: 54001 | G14: 74.45 | I14: 82.12 | J14: 82.099 | K14: =IF(AF14="","",AF14/Z14) -> 0.070037394 | L14: 7.4247526 | M14: 11.400297 | O14: B3 | P14: B | Q14: Sovereign | R14: TR | S14: USD | V14: Sr Unsecured | W14: =+D14*G14/100 -> 1094.8529 | X14: =+D14*G14/100 -> 1094.8529 | Z14: =+D14*J14/100 -> 1207.3382 | AA14: =IF(+I14=0,AB14,D14*(J14-I14)/100) -> -0.30882353 | AB14: =+$D14*($J14-$G14)/100 -> 112.48529 | AC14: =+Z14*L14 -> 8964.1877 | AD14: =+Z14*M14 -> 13764.015 | AE14: =+AA14/X14 -> -0.0002820685 | AF14: =+D14*E14/100 -> 84.558824 | AJ14: 0 | AK14: =AJ14*Z14 -> 0
A15: SCH | B15: XS145DGFDJHDKJ | C15: bono12 | D15: 2941.1765 | E15: 7.5 | F15: Perpetuo | G15: 102.15 | I15: 106.241 | J15: 106.786 | K15: =IF(AF15="","",AF15/Z15) -> 0.070233926 | L15: 7.0608097 | M15: 6.5089424 | N15: BB+ | O15: Ba1 | Q15: Banks | R15: CL | S15: USD | T15: CALLABLE | V15: Jr Subordinated | W15: =+D15*G15/100 -> 3004.4118 | X15: =+D15*G15/100 -> 3004.4118 | Z15: =+D15*J15/100 -> 3140.7647 | AA15: =IF(+I15=0,AB15,D15*(J15-I15)/100) -> 16.029412 | AB15: =+$D15*($J15-$G15)/100 -> 136.35294 | AC15: =+Z15*L15 -> 22176.342 | AD15: =+Z15*M15 -> 20443.056 | AE15: =+AA15/X15 -> 0.0053352912 | AF15: =+D15*E15/100 -> 220.58824 | AJ15: 0.6 | AK15: =AJ15*Z15 -> 1884.4588
A16: SCH | B16: XS145DGFDJHDKJ | C16: bono13 | D16: 970.58824 | E16: 8.25 | F16: 20-01-2034 | G16: 127.625 | H16: 112.492 | I16: 116.286 | J16: 115.558 | K16: =IF(AF16="","",AF16/Z16) -> 0.071392721 | L16: 5.7538904 | M16: 6.1098108 | N16: BB- | O16: Ba2 | P16: BB- | Q16: Sovereign | R16: BR | S16: USD | T16: AT MATURITY | V16: Sr Unsecured | W16: =+D16*G16/100 -> 1238.7132 | X16: =+D16*G16/100 -> 1238.7132 | Z16: =+D16*J16/100 -> 1121.5924 | AA16: =IF(+I16=0,AB16,D16*(J16-I16)/100) -> -7.0658824 | AB16: =+$D16*($J16-$G16)/100 -> -117.12088 | AC16: =+Z16*L16 -> 6453.5194 | AD16: =+Z16*M16 -> 6852.7171 | AE16: =+AA16/X16 -> -0.0057042116 | AF16: =+D16*E16/100 -> 80.073529 | AJ16: 0.55 | AK16: =AJ16*Z16 -> 616.87579
A17: SCH | B17: XS145DGFDJHDKJ | C17: bono14 | D17: 1470.5882 | E17: 7.625 | F17: 47855 | G17: 101.901 | I17: 105.26 | J17: 105.045 | K17: =IF(AF17="","",AF17/Z17) -> 0.072587939 | L17: 6.3821658 | M17: 3.0507515 | N17: BBB- | O17: Ba2 | P17: BB+ | Q17: Líneas Aéreas | R17: CL | S17: USD | T17: CALLABLE | V17: Secured | W17: =+D17*G17/100 -> 1498.5441 | X17: =+D17*G17/100 -> 1498.5441 | Z17: =+D17*J17/100 -> 1544.7794 | AA17: =IF(+I17=0,AB17,D17*(J17-I17)/100) -> -3.1617647 | AB17: =+$D17*($J17-$G17)/100 -> 46.235294 | AC17: =+Z17*L17 -> 9859.0383 | AD17: =+Z17*M17 -> 4712.7381 | AE17: =+AA17/X17 -> -0.002109891 | AF17: =+D17*E17/100 -> 112.13235 | AJ17: 0.55 | AK17: =AJ17*Z17 -> 849.62868
A18: SCH | B18: XS145DGFDJHDKJ | C18: bono15 | D18: 194.11765 | E18: 8.6 | F18: 15-12-2030 | G18: 146 | H18: 121.59 | I18: 117.411 | J18: 117.539 | K18: =IF(AF18="","",AF18/Z18) -> 0.073167204 | L18: 4.4734589 | M18: 4.0866908 | N18: A- | O18: A2 | P18: WD | Q18: Property/Casualty Ins | R18: FR | S18: USD | T18: AT MATURITY | V18: Subordinated | W18: =+D18*G18/100 -> 283.41176 | X18: =+D18*G18/100 -> 283.41176 | Z18: =+D18*J18/100 -> 228.16394 | AA18: =IF(+I18=0,AB18,D18*(J18-I18)/100) -> 0.24847059 | AB18: =+$D18*($J18-$G18)/100 -> -55.247824 | AC18: =+Z18*L18 -> 1020.682 | AD18: =+Z18*M18 -> 932.43548 | AE18: =+AA18/X18 -> 0.00087671233 | AF18: =+D18*E18/100 -> 16.694118 | AK18: =AJ18*Z18 -> 0
A19: SCH | B19: XS145DGFDJHDKJ | C19: bono16 | D19: 882.35294 | E19: 6.5 | F19: 02-06-2041 | G19: 74.167 | H19: 65.698 | I19: 86.682 | J19: 88.498 | K19: =IF(AF19="","",AF19/Z19) -> 0.073447988 | L19: 7.7798601 | M19: 9.4231421 | N19: BBB | O19: B1 | P19: BB-u | Q19: Oil Comp-Integrated | R19: MX | S19: USD | T19: AT MATURITY | V19: Sr Unsecured | W19: =+D19*G19/100 -> 654.41471 | X19: =+D19*G19/100 -> 654.41471 | Z19: =+D19*J19/100 -> 780.86471 | AA19: =IF(+I19=0,AB19,D19*(J19-I19)/100) -> 16.023529 | AB19: =+$D19*($J19-$G19)/100 -> 126.45 | AC19: =+Z19*L19 -> 6075.0181 | AD19: =+Z19*M19 -> 7358.1991 | AE19: =+AA19/X19 -> 0.024485283 | AF19: =+D19*E19/100 -> 57.352941 | AJ19: 0.5 | AK19: =AJ19*Z19 -> 390.43235
A20: SCH | B20: XS145DGFDJHDKJ | C20: bono17 | D20: 294.11765 | E20: 6.5 | F20: 02-06-2041 | G20: 74.167 | H20: 65.698 | I20: 86.682 | J20: 88.498 | K20: =IF(AF20="","",AF20/Z20) -> 0.073447988 | L20: 7.7798601 | M20: 9.4231421 | N20: BBB | O20: B1 | P20: BB-u | Q20: Oil Comp-Integrated | R20: MX | S20: USD | T20: AT MATURITY | V20: Sr Unsecured | W20: =+D20*G20/100 -> 218.13824 | X20: =+D20*G20/100 -> 218.13824 | Z20: =+D20*J20/100 -> 260.28824 | AA20: =IF(+I20=0,AB20,D20*(J20-I20)/100) -> 5.3411765 | AB20: =+$D20*($J20-$G20)/100 -> 42.15 | AC20: =+Z20*L20 -> 2025.006 | AD20: =+Z20*M20 -> 2452.733 | AE20: =+AA20/X20 -> 0.024485283 | AF20: =+D20*E20/100 -> 19.117647 | AJ20: 0.55 | AK20: =AJ20*Z20 -> 143.15853
A21: SCH | B21: XS145DGFDJHDKJ | C21: bono18 | D21: 291.17647 | E21: 6.5 | F21: 02-06-2041 | G21: 100.65 | H21: 65.698 | I21: 86.682 | J21: 88.498 | K21: =IF(AF21="","",AF21/Z21) -> 0.073447988 | L21: 7.7798601 | M21: 9.4231421 | N21: BBB | O21: B1 | P21: BB-u | Q21: Oil Comp-Integrated | R21: MX | S21: USD | T21: AT MATURITY | V21: Sr Unsecured | W21: =+D21*G21/100 -> 293.06912 | X21: =+D21*G21/100 -> 293.06912 | Z21: =+D21*J21/100 -> 257.68535 | AA21: =IF(+I21=0,AB21,D21*(J21-I21)/100) -> 5.2877647 | AB21: =+$D21*($J21-$G21)/100 -> -35.383765 | AC21: =+Z21*L21 -> 2004.756 | AD21: =+Z21*M21 -> 2428.2057 | AE21: =+AA21/X21 -> 0.018042722 | AF21: =+D21*E21/100 -> 18.926471 | AK21: =AJ21*Z21 -> 0
A22: SCH | B22: XS145DGFDJHDKJ | C22: bono19 | D22: 429.41176 | E22: 10.75 | F22: 01-08-2039 | G22: 165.5 | H22: 133.03 | I22: 133.254 | J22: 133.125 | K22: =IF(AF22="","",AF22/Z22) -> 0.080751174 | L22: 6.9017989 | M22: 6.1441006 | N22: BBB | O22: Baa2 | P22: BBB | Q22: Multi-line Insurance | R22: US | S22: USD | T22: CALL/EXT | V22: Jr Subordinated | W22: =+D22*G22/100 -> 710.67647 | X22: =+D22*G22/100 -> 710.67647 | Z22: =+D22*J22/100 -> 571.65441 | AA22: =IF(+I22=0,AB22,D22*(J22-I22)/100) -> -0.55394118 | AB22: =+$D22*($J22-$G22)/100 -> -139.02206 | AC22: =+Z22*L22 -> 3945.4438 | AD22: =+Z22*M22 -> 3512.3022 | AE22: =+AA22/X22 -> -0.00077945619 | AF22: =+D22*E22/100 -> 46.161765 | AK22: =AJ22*Z22 -> 0
A23: SCH | B23: XS145DGFDJHDKJ | C23: bono20 | D23: 588.23529 | E23: 7.25 | F23: 30-06-2031 | G23: 103.582 | H23: 82.581 | I23: 88.052 | J23: 84.706 | K23: =IF(AF23="","",AF23/Z23) -> 0.085590159 | L23: 11.061985 | M23: 3.7589709 | N23: #N/A N/A | O23: Ba3 | P23: BB- | Q23: Oil Refining&Marketing | R23: BR | S23: USD | T23: SINKABLE | V23: Secured | W23: =+D23*G23/100 -> 609.30588 | X23: =+D23*G23/100 -> 609.30588 | Z23: =+D23*J23/100 -> 498.27059 | AA23: =IF(+I23=0,AB23,D23*(J23-I23)/100) -> -19.682353 | AB23: =+$D23*($J23-$G23)/100 -> -111.03529 | AC23: =+Z23*L23 -> 5511.8616 | AD23: =+Z23*M23 -> 1872.9847 | AF23: =+D23*E23/100 -> 42.647059 | AJ23: 0.6 | AK23: =AJ23*Z23 -> 298.96235
A24: SCH | B24: XS145DGFDJHDKJ | C24: bono21 | D24: 291.17647 | E24: 6.625 | F24: #N/A Field Not Applicable | G24: 104.88 | H24: 57.39 | I24: 74.284 | J24: 75.03 | K24: =IF(AF24="","",AF24/Z24) -> 0.088298014 | L24: 8.7924846 | M24: 11.501221 | N24: BBB | O24: B1 | P24: BB-u | Q24: Oil Comp-Integrated | R24: MX | S24: USD | T24: PERP/CALL | V24: Sr Unsecured | W24: =+D24*G24/100 -> 305.38588 | X24: =+D24*G24/100 -> 305.38588 | Z24: =+D24*J24/100 -> 218.46971 | AA24: =IF(+I24=0,AB24,D24*(J24-I24)/100) -> 2.1721765 | AB24: =+$D24*($J24-$G24)/100 -> -86.916176 | AC24: =+Z24*L24 -> 1920.8915 | AD24: =+Z24*M24 -> 2512.6683 | AE24: =+AA24/X24 -> 0.0071128909 | AF24: =+D24*E24/100 -> 19.290441 | AG24: 45099 | AJ24: 0.5 | AK24: =AJ24*Z24 -> 109.23485
A25: SCH | B25: XS145DGFDJHDKJ | C25: bono22 | D25: 1470.5882 | E25: 9.625 | F25: 47528 | G25: 97.3 | I25: 100.312 | J25: 102.125 | K25: =IF(AF25="","",AF25/Z25) -> 0.094247246 | L25: 8.9617325 | M25: 2.5650448 | O25: B2 | Q25: Líneas Aéreas | R25: GB | S25: USD | T25: NORMAL | V25: Secured | W25: =+D25*G25/100 -> 1430.8824 | X25: =+D25*G25/100 -> 1430.8824 | Z25: =+D25*J25/100 -> 1501.8382 | AA25: =IF(+I25=0,AB25,D25*(J25-I25)/100) -> 26.661765 | AB25: =+$D25*($J25-$G25)/100 -> 70.955882 | AC25: =+Z25*L25 -> 13459.073 | AD25: =+Z25*M25 -> 3852.2823 | AE25: =+AA25/X25 -> 0.018633094 | AF25: =+D25*E25/100 -> 141.54412 | AG25: 45904 | AJ25: 0.4 | AK25: =AJ25*Z25 -> 600.73529
D27: =SUM(D4:D26) -> 68644.118 | Z27: =SUM(Z4:Z26) -> 67826.196 | AA27: =SUM(AA4:AA26) -> 208.16608 | AB27: =SUM(AB4:AB26) -> 77.057354 | AC27: =SUM(AC4:AC26) -> 294119.05 | AD27: =SUM(AD4:AD26) -> 91320.784 | AF27: =SUM(AF4:AF26) -> 2955.5509
AF28: =AF27/360*AE31 -> 845.61595
AB29: IRR | AC29: =AC27/Z27 -> 4.3363637 | AE29: =TODAY() -> 46125
AB30: Dur | AC30: =AD27/Z27 -> 1.346394 | AE30: 46022
AE31: =AE29-AE30 -> 103
A33: RENTA FIJA (BANCO MALO)
A34: BANCO | B34: ISIN | C34: Name | D34: Monto Compra | E34: Coupon | F34: Maturity | G34: PRECIO COMPRA | H34: Precio 31-Dic-2021 | I34: Precio 31-Dic-2024 | J34: Precio Mercado (29-05) | K34: CurrYield | L34: YLD_YTM_ask | M34: DUR_MID | N34: rtg_sp | O34: rtg_moody | P34: rtg_fitch | Q34: industry_subgroup | R34: PAIS | S34: crncy | T34: callable | U34: NXT_CALL_DT | V34: payment_rank | W34: Monto Compra | X34: Costo | Y34: status | Z34: VP | AA34: MTM | AB34: MTM trib | AC34: VPxYTM | AD34: VPxDur | AE34: Rt % año | AF34: INTERESES x AÑO | AG34: FECHA COMPRA | AH34: VENTA | AI34: compra | AJ34: LTV
A35: SCH | B35: XS145DGFDJHDKJ | C35: bono22 | D35: 294.11765 | E35: 12.75 | F35: 17-02-2022 | G35: 61.45537 | H35: 5.246 | I35: 13.16 | J35: 41.35 | K35: =IF(AF35="","",AF35/Z35) | L35: 72.944676 | M35: 0 | N35: #N/A N/A | O35: #N/A N/A | P35: WD | Q35: Oil Comp-Integrated | R35: VE | S35: USD | T35: SINKABLE | V35: Sr Unsecured | W35: =+D35*J35/100 -> 121.61765 | X35: =+D35*G35/100 -> 180.75109 | Z35: =+D35*J35/100 -> 121.61765 | AA35: =IF(+I35=0,AB35,W35*(J35-I35)/100) -> 34.284015 | AB35: =+$W35*($J35-$G35)/100 -> -24.451678 | AC35: =+Z35*L35 -> 8871.3599 | AE35: =+AA35/X35 -> 0.18967529 | AJ35: 0 | AK35: =AJ35*Z35 -> 0
A36: SCH | B36: XS145DGFDJHDKJ | C36: bono23 | D36: 294.11765 | E36: 8.25 | F36: 20-01-2016 | G36: 85.405 | H36: 0.404 | I36: 0.221 | J36: 0.113 | K36: =IF(AF36="","",AF36/Z36) | L36: 4166.6667 | M36: 0 | N36: NR | O36: WR | P36: #N/A N/A | Q36: Commer Banks Non-US | R36: BR | S36: USD | T36: AT MATURITY | V36: Sr Unsecured | W36: =+D36*G36/100 -> 251.19118 | X36: =+D36*G36/100 -> 251.19118 | Z36: =+D36*J36/100 -> 0.33235294 | AA36: =IF(+I36=0,AB36,W36*(J36-I36)/100) -> -0.27128647 | AB36: =+$W36*($J36-$G36)/100 -> -214.24598 | AC36: =+Z36*L36 -> 1384.8039 | AD36: =+Z36*M36 -> 0 | AE36: =+AA36/X36 -> -0.00108 | AK36: =AJ36*Z36 -> 0
A37: SCH | B37: XS145DGFDJHDKJ | C37: bono24 | D37: 588.23529 | E37: 5.25 | F37: 23-05-2023 | G37: 93.5 | H37: 14.102 | I37: 33.854 | J37: 6.875 | K37: =IF(AF37="","",AF37/Z37) | L37: 59.456399 | M37: 0 | N37: #N/A N/A | O37: #N/A N/A | P37: WD | Q37: Commer Banks Non-US | R37: RU | S37: USD | T37: AT MATURITY | V37: Subordinated | W37: =+D37*G37/100 -> 550 | X37: =+D37*G37/100 -> 550 | Z37: =+D37*J37/100 -> 40.441176 | AA37: =IF(+I37=0,AB37,W37*(J37-I37)/100) -> -148.3845 | AB37: =+$W37*($J37-$G37)/100 -> -476.4375 | AC37: =+Z37*L37 -> 2404.4867 | AD37: =+Z37*M37 -> 0 | AE37: =+AA37/X37 -> -0.26979 | AJ37: 0 | AK37: =AJ37*Z37 -> 0
A38: SCH | B38: XS145DGFDJHDKJ | C38: bono25 | D38: 735.29412 | E38: 6.75 | F38: 15-03-2023 | G38: 95.55862 | H38: 5.558 | I38: 3.488 | J38: 3 | K38: =IF(AF38="","",AF38/Z38) | L38: 162.6506 | M38: 0 | N38: NR | O38: WR | P38: #N/A N/A | Q38: Commer Banks Non-US | R38: CL | S38: USD | T38: CALLABLE | V38: Sr Unsecured | W38: =+D38*G38/100 -> 702.63691 | X38: =+D38*G38/100 -> 702.63691 | Z38: =+D38*J38/100 -> 22.058824 | AA38: =IF(+I38=0,AB38,W38*(J38-I38)/100) -> -3.4288681 | AB38: =+$W38*($J38-$G38)/100 -> -650.35103 | AC38: =+Z38*L38 -> 3587.8809 | AD38: =+Z38*M38 -> 0 | AE38: =+AA38/X38 -> -0.00488 | AJ38: 0 | AK38: =AJ38*Z38 -> 0
A39: SCH | B39: XS145DGFDJHDKJ | C39: bono26 | D39: 735.29412 | E39: 6.75 | F39: 15-03-2023 | G39: 96.15 | H39: 5.558 | I39: 3.488 | J39: 3 | K39: =IF(AF39="","",AF39/Z39) | L39: 162.6506 | M39: 0 | N39: NR | O39: WR | P39: #N/A N/A | Q39: Commer Banks Non-US | R39: CL | S39: USD | T39: CALLABLE | V39: Sr Unsecured | W39: =+D39*G39/100 -> 706.98529 | X39: =+D39*G39/100 -> 706.98529 | Z39: =+D39*J39/100 -> 22.058824 | AA39: =IF(+I39=0,AB39,W39*(J39-I39)/100) -> -3.4500882 | AB39: =+$W39*($J39-$G39)/100 -> -658.5568 | AC39: =+Z39*L39 -> 3587.8809 | AD39: =+Z39*M39 -> 0 | AE39: =+AA39/X39 -> -0.00488 | AJ39: 0 | AK39: =AJ39*Z39 -> 0
A40: SCH | B40: XS145DGFDJHDKJ | C40: bono27 | D40: 441.17647 | E40: 12 | F40: 04-05-2013 | G40: 0 | H40: 0.378 | I40: 0.378 | J40: 0.216 | K40: =IF(AF40="","",AF40/Z40) | L40: 3174.6032 | M40: 0 | N40: #N/A N/A | O40: WR | P40: #N/A N/A | Q40: Steel Pipe&Tube | R40: BG | S40: EUR | T40: AT MATURITY | V40: Secured | W40: =+D40*G40/100 -> 0 | X40: =+D40*G40/100 -> 0 | Z40: =+D40*J40/100 -> 0.95294118 | AA40: =IF(+I40=0,AB40,W40*(J40-I40)/100) -> 0 | AB40: =+$W40*($J40-$G40)/100 -> 0 | AC40: =+Z40*L40 -> 3025.2101 | AD40: =+Z40*M40 -> 0 | AE40: =+AA40/X40 -> #DIV/0! | AK40: =AJ40*Z40 -> 0
A41: SCH | B41: XS145DGFDJHDKJ | C41: bono28 | D41: 1470.5882 | E41: 7.121 | F41: 25-06-2024 | G41: 104 | H41: 23.415 | I41: 23.722 | J41: 15.809 | K41: =IF(AF41="","",AF41/Z41) | L41: 38.326157 | M41: 0 | N41: NR | O41: #N/A N/A | P41: WD | Q41: Commer Banks Non-US | R41: RU | S41: USD | T41: AT MATURITY | V41: Sr Unsecured | W41: =+D41*G41/100 -> 1529.4118 | X41: =+D41*G41/100 -> 1529.4118 | Z41: =+D41*J41/100 -> 232.48529 | AA41: =IF(+I41=0,AB41,W41*(J41-I41)/100) -> -121.02235 | AB41: =+$W41*($J41-$G41)/100 -> -1348.8035 | AC41: =+Z41*L41 -> 8910.2679 | AD41: =+Z41*M41 -> 0 | AE41: =+AA41/X41 -> -0.07913 | AJ41: 0 | AK41: =AJ41*Z41 -> 0
A42: SCH | B42: XS145DGFDJHDKJ | C42: bono29 | D42: 294.11765 | E42: 9.75 | F42: 17-05-2035 | G42: 48.99444 | H42: 4.82 | I42: 12.671 | J42: 39.05 | K42: =IF(AF42="","",AF42/Z42) | L42: 52.656709 | M42: 2.9279895 | N42: #N/A N/A | O42: WR | P42: WD | Q42: Oil Comp-Integrated | R42: VE | S42: USD | T42: SINKABLE | V42: Sr Unsecured | W42: =+D42*G42/100 -> 144.10129 | X42: =+D42*G42/100 -> 144.10129 | Z42: =+D42*J42/100 -> 114.85294 | AA42: =IF(+I42=0,AB42,W42*(J42-I42)/100) -> 38.01248 | AB42: =+$W42*($J42-$G42)/100 -> -14.330067 | AJ42: 0 | AK42: =AJ42*Z42 -> 0
A43: SCH | B43: XS145DGFDJHDKJ | C43: bono30 | D43: 2941.1765 | E43: 4.7 | F43: 29-01-2025 | G43: 98.88 | H43: 22.724 | I43: 35.583 | J43: #N/A N/A | K43: =IF(AF43="","",AF43/Z43) | L43: 0 | M43: 0 | N43: NR | O43: #N/A N/A | P43: WD | Q43: Commer Banks Non-US | R43: RU | S43: USD | T43: AT MATURITY | V43: Sr Unsecured | W43: =+D43*G43/100 -> 2908.2353 | X43: =+D43*G43/100 -> 2908.2353 | Z43: 0 | AA43: 0 | AB43: 0 | AC43: =+Z43*L43 -> 0 | AD43: =+Z43*M43 -> 0 | AE43: =+AA43/X43 -> 0 | AJ43: 0 | AK43: =AJ43*Z43 -> 0
A44: SCH | B44: XS145DGFDJHDKJ | C44: bono31 | D44: 1617.6471 | E44: 9.375 | F44: 13-01-2034 | G44: 48.95 | H44: 8.932 | I44: 17.404 | J44: 44.405 | K44: =IF(AF44="","",AF44/Z44) | L44: 35.908176 | M44: 4.2422559 | N44: NR | O44: Cu | P44: WD | Q44: Sovereign | R44: VE | S44: USD | T44: AT MATURITY | V44: Sr Unsecured | W44: =+D44*G44/100 -> 791.83824 | X44: =+D44*G44/100 -> 791.83824 | Z44: =+D44*J44/100 -> 718.31618 | AA44: =IF(+I44=0,AB44,W44*(J44-I44)/100) -> 213.80424 | AB44: =+$W44*($J44-$G44)/100 -> -35.989048 | AC44: =+Z44*L44 -> 25793.424 | AD44: =+Z44*M44 -> 3047.2811 | AE44: =+AA44/X44 -> 0.27001 | AK44: =AJ44*Z44 -> 0
A45: SCH | B45: XS145DGFDJHDKJ | C45: bono32 | D45: 882.35294 | E45: 9.5 | F45: #N/A Field Not Applicable | G45: 92.65 | H45: 15.49 | I45: 17.913 | J45: 13.101 | K45: =IF(AF45="","",AF45/Z45) | L45: 67.7586 | M45: 2.231383 | N45: #N/A N/A | O45: NR | P45: #N/A N/A | Q45: Commer Banks Non-US | R45: RU | S45: USD | T45: PERP/CALL | V45: Jr Subordinated | W45: =+D45*G45/100 -> 817.5 | X45: =+D45*G45/100 -> 817.5 | Z45: =+D45*J45/100 -> 115.59706 | AA45: =IF(+I45=0,AB45,W45*(J45-I45)/100) -> -39.3381 | AB45: =+$W45*($J45-$G45)/100 -> -650.31308 | AC45: =+Z45*L45 -> 7832.6948 | AD45: =+Z45*M45 -> 257.94132 | AE45: =+AA45/X45 -> -0.04812 | AJ45: 0 | AK45: =AJ45*Z45 -> 0
A46: SCH | B46: XS145DGFDJHDKJ | C46: bono33 | D46: 588.23529 | E46: 9.5 | F46: #N/A Field Not Applicable | G46: 103.75 | H46: 15.49 | I46: 17.913 | J46: 13.101 | K46: =IF(AF46="","",AF46/Z46) | L46: 67.7586 | M46: 2.231383 | N46: #N/A N/A | O46: NR | P46: #N/A N/A | Q46: Commer Banks Non-US | R46: RU | S46: USD | T46: PERP/CALL | V46: Jr Subordinated | W46: =+D46*G46/100 -> 610.29412 | X46: =+D46*G46/100 -> 610.29412 | Z46: =+D46*J46/100 -> 77.064706 | AA46: =IF(+I46=0,AB46,W46*(J46-I46)/100) -> -29.367353 | AB46: =+$W46*($J46-$G46)/100 -> -553.22551 | AC46: =+Z46*L46 -> 5221.7966 | AD46: =+Z46*M46 -> 171.96088 | AE46: =+AA46/X46 -> -0.04812 | AK46: =AJ46*Z46 -> 0
A47: SCH | B47: XS145DGFDJHDKJ | C47: bono34 | D47: 1126.4706 | E47: 9.25 | F47: 15-09-2027 | G47: 51.875 | H47: 8.921 | I47: 19.39 | J47: 44.004 | K47: =IF(AF47="","",AF47/Z47) | L47: 109.62668 | M47: 1.7447821 | N47: NR | O47: Cu | P47: WD | Q47: Sovereign | R47: VE | S47: USD | T47: AT MATURITY | V47: Sr Unsecured | W47: =+D47*G47/100 -> 584.35662 | X47: =+D47*G47/100 -> 584.35662 | Z47: =+D47*J47/100 -> 495.69212 | AA47: =IF(+I47=0,AB47,W47*(J47-I47)/100) -> 143.83354 | AB47: =+$W47*($J47-$G47)/100 -> -45.994709 | AC47: =+Z47*L47 -> 54341.084 | AD47: =+Z47*M47 -> 864.87472 | AE47: =+AA47/X47 -> 0.24614 | AJ47: 0 | AK47: =AJ47*Z47 -> 0
A48: SCH | B48: XS145DGFDJHDKJ | C48: bono35 | D48: 1029.4118 | F48: 31-03-2038 | G48: 43.375 | H48: 9.003 | I48: 14.763 | J48: 38.789 | K48: =IF(AF48="","",AF48/Z48) | L48: 34.004834 | M48: 4.0934491 | N48: NR | O48: WR | P48: WD | Q48: Sovereign | R48: VE | S48: USD | T48: AT MATURITY | V48: Sr Unsecured | W48: =+D48*G48/100 -> 446.50735 | X48: =+D48*G48/100 -> 446.50735 | Z48: =+D48*J48/100 -> 399.29853 | AA48: =IF(+I48=0,AB48,W48*(J48-I48)/100) -> 107.27786 | AB48: =+$W48*($J48-$G48)/100 -> -20.476827 | AC48: =+Z48*L48 -> 13578.08 | AD48: =+Z48*M48 -> 1634.5082 | AE48: =+AA48/X48 -> 0.24026 | AK48: =AJ48*Z48 -> 0
A49: SCH | B49: XS145DGFDJHDKJ | C49: bono36 | D49: 2205.8824 | E49: 4.95 | F49: 23-03-2027 | G49: 93.99 | H49: 69.681 | I49: 75.737 | J49: 86.92 | K49: =IF(AF49="","",AF49/Z49) | L49: 14.913888 | M49: 1.4735965 | N49: NR | O49: WR | P49: WD | Q49: Oil Comp-Explor&Prodtn | R49: RU | S49: USD | T49: AT MATURITY | V49: Sr Unsecured | W49: =+D49*G49/100 -> 2073.3088 | X49: =+D49*G49/100 -> 2073.3088 | Z49: =+D49*J49/100 -> 1917.3529 | AA49: =IF(+I49=0,AB49,W49*(J49-I49)/100) -> 231.85813 | AB49: =+$W49*($J49-$G49)/100 -> -146.58293 | AC49: =+Z49*L49 -> 28595.187 | AD49: =+Z49*M49 -> 2825.4045 | AE49: =+AA49/X49 -> 0.11183 | AJ49: 0 | AK49: =AJ49*Z49 -> 0
A50: SCH | B50: XS145DGFDJHDKJ | C50: bono37 | D50: 588.23529 | E50: 7.375 | F50: 25-09-2034 | G50: 102.11 | H50: 19.586 | I50: 23 | J50: #N/A N/A | K50: =IF(AF50="","",AF50/Z50) | L50: 0 | M50: 0 | N50: CCC+ | O50: #N/A N/A | P50: CC | Q50: Sovereign | R50: UA | S50: USD | T50: SINKABLE | V50: Sr Unsecured | W50: =+D50*G50/100 -> 600.64706 | X50: =+D50*G50/100 -> 600.64706 | Z50: 0 | AA50: 0 | AB50: 0 | AD50: =+Z50*M50 -> 0 | AE50: =+AA50/X50 -> 0 | AJ50: 0 | AK50: =AJ50*Z50 -> 0
A51: SCH | B51: XS145DGFDJHDKJ | C51: bono38 | D51: 1470.5882 | E51: 4.95 | F51: 06-02-2028 | G51: 103.45 | H51: 74.1 | I51: 72.802 | J51: 81.862 | K51: =IF(AF51="","",AF51/Z51) | L51: 14.455844 | M51: 2.2884171 | N51: NR | O51: WR | P51: WD | Q51: Oil Comp-Explor&Prodtn | R51: RU | S51: USD | T51: AT MATURITY | V51: Sr Unsecured | W51: =+D51*G51/100 -> 1521.3235 | X51: =+D51*G51/100 -> 1521.3235 | Z51: =+D51*J51/100 -> 1203.8529 | AA51: =IF(+I51=0,AB51,W51*(J51-I51)/100) -> 137.83191 | AB51: =+$W51*($J51-$G51)/100 -> -328.42332 | AC51: =+Z51*L51 -> 17402.711 | AD51: =+Z51*M51 -> 2754.9176 | AE51: =+AA51/X51 -> 0.0906 | AJ51: 0 | AK51: =AJ51*Z51 -> 0
A52: SCH | B52: XS145DGFDJHDKJ | C52: bono39 | D52: 882.35294 | E52: 6.25 | F52: 30-06-2035 | G52: 110 | H52: 24.036 | I52: 24.464 | J52: 21.875 | K52: =IF(AF52="","",AF52/Z52) | L52: 29.740621 | M52: 5.164167 | N52: NR | O52: WR | P52: WD | Q52: Commer Banks Non-US | R52: RU | S52: USD | T52: PUTABLE | V52: Sr Unsecured | W52: =+D52*G52/100 -> 970.58824 | X52: =+D52*G52/100 -> 970.58824 | Z52: =+D52*J52/100 -> 193.01471 | AA52: =IF(+I52=0,AB52,W52*(J52-I52)/100) -> -25.128529 | AB52: =+$W52*($J52-$G52)/100 -> -855.33088 | AC52: =+Z52*L52 -> 5740.3773 | AD52: =+Z52*M52 -> 996.76018 | AE52: =+AA52/X52 -> -0.02589 | AJ52: 0 | AK52: =AJ52*Z52 -> 0
A53: SCH | B53: XS145DGFDJHDKJ | C53: bono40 | D53: 2647.0588 | E53: 7.288 | F53: 16-08-2037 | G53: 109.9 | H53: 78.157 | I53: 80.235 | J53: 71.529 | K53: =IF(AF53="","",AF53/Z53) | L53: 10.958298 | M53: 7.5200319 | N53: NR | O53: WR | P53: WD | Q53: Oil Comp-Explor&Prodtn | R53: RU | S53: USD | T53: AT MATURITY | V53: Sr Unsecured | W53: =+D53*G53/100 -> 2909.1176 | X53: =+D53*G53/100 -> 2909.1176 | Z53: =+D53*J53/100 -> 1893.4147 | AA53: =IF(+I53=0,AB53,W53*(J53-I53)/100) -> -253.26778 | AB53: =+$W53*($J53-$G53)/100 -> -1116.2575 | AC53: =+Z53*L53 -> 20748.602 | AD53: =+Z53*M53 -> 14238.539 | AE53: =+AA53/X53 -> -0.08706 | AJ53: 0 | AK53: =AJ53*Z53 -> 0
A54: SCH | B54: XS145DGFDJHDKJ | C54: bono41 | D54: 294.11765 | E54: 11.75 | F54: 10-05-2016 | G54: 100.005 | H54: 0 | I54: 0 | J54: #N/A N/A | K54: =IF(AF54="","",AF54/Z54) | L54: 0 | M54: 0 | N54: #N/A N/A | O54: #N/A N/A | P54: WD | Q54: Commer Banks Non-US | R54: RU | S54: USD | T54: AT MATURITY | V54: Subordinated | W54: =+D54*G54/100 -> 294.13235 | X54: =+D54*G54/100 -> 294.13235 | Z54: 0 | AK54: =AJ54*Z54 -> 0
D56: =SUM(D35:D54) -> 21126.471 | Z56: =SUM(Z35:Z54) -> 7568.4039 | AA56: =SUM(AA35:AA54) -> 283.24331 | AB56: =SUM(AB35:AB54) -> -7139.7704 | AC56: =SUM(AC35:AC54) -> 211025.85 | AD56: =SUM(AD4:AD55) -> 209433.76 | AF56: =SUM(AF35:AF54) -> 0
A58: FONDOS
A60: BANCO | B60: FECHA COMPRA | C60: NOMBRE | D60: ISIN | F60: CANTIDAD | G60: PRECIO COMPRA | H60: PRECIO 31-12-2025 | I60: PRECIO ACTUAL | J60: VP | K60: DIVIDENDOS | L60: MTM | M60: MTM Trib | P60: LTV | R60: FAMILIA
A61: PUP | B61: 44299 | C61: FONDO 1 | D61: LU05ERGERF | F61: 49152.12 | G61: 40.69 | H61: 49.99 | I61: 50.13 | J61: =I61*F61 -> 2463995.8 | L61: =(I61-H61)*F61 -> 6881.2968 | M61: =(I61-G61)*F61 -> 463996.01 | N61: reinvierte | O61: mantener | P61: 0.75 | Q61: =P61*J61 -> 1847996.8 | R61: RENTA FIJA
A62: PUP | B62: 45063 | C62: FONDO 2 | D62: LU05ERGERF | F62: 213675.21 | G62: 9.36 | H62: 9.7 | I62: 9.73 | J62: =I62*F62 -> 2079059.8 | K62: 114230.82 | L62: =(I62-H62)*F62 -> 6410.2564 | M62: =(I62-G62)*F62 -> 79059.829 | N62: paga div | O62: mantener | P62: 0.8 | Q62: =P62*J62 -> 1663247.9 | R62: RENTA FIJA
A63: PUP | B63: 45847 | C63: FONDO 3 | D63: LU05ERGERF | F63: 61349.693 | G63: 24.45 | H63: 24.73 | I63: 24.62 | J63: =I63*F63 -> 1510429.4 | K63: =36796.8+33535.49+32638.18+32805.98 -> 135776.45 | L63: =(I63-H63)*F63 -> -6748.4662 | M63: =(I63-G63)*F63 -> 10429.448 | N63: paga div | O63: mantener | P63: 0.5 | Q63: =P63*J63 -> 755214.72 | R63: RENTA FIJA
A64: PUP | B64: 45848 | C64: FONDO 4 | D64: LU05ERGERF | F64: 31276.06 | G64: 47.96 | H64: 49.99 | I64: 50.27 | J64: =I64*F64 -> 1572247.5 | L64: =(I64-H64)*F64 -> 8757.2968 | M64: =(I64-G64)*F64 -> 72247.699 | N64: reinvierte | O64: mantener | P64: 0.75 | Q64: =P64*J64 -> 1179185.7 | R64: RENTA FIJA
J66: =SUM(J61:J65) -> 7625732.6 | K66: =SUM(K61:K65) -> 250007.27 | L66: =SUM(L61:L65) -> 15300.384 | M66: =SUM(M61:M65) -> 625732.99
A71: ORO + PLATA
V72: XAGUSD | W72: XAUUSD | X72: COPX | Y72: CPER
A73: BANCO | B73: FECHA | C73: NOMBRE | D73: TICKER | F73: CANTIDAD | G73: PRECIO COMPRA | H73: PRECIO ACTUAL | I73: COSTO | J73: VP | K73: MTM | L73: Retorno | M73: Plazo | N73: Vencimiento
A74: SCH | B74: 46099 | C74: XAGUSD | D74: PLATA | F74: 23 | G74: 76.6028 | H74: 76.77 | I74: =G74*F74 -> 1761.8644 | J74: =H74*F74 -> 1765.71 | K74: =(H74-G74)*F74 -> 3.8456 | L74: =K74/(F74*G74) -> 0.0021826878 | M74: =IF(N74="","",N74-TODAY()) -> 7 | N74: 46132 | Q74: Cobre | R74: =+X88+Y88 -> #VALUE! | V74: =IF(V$72=$C74,$J74,0) -> 1765.71 | W74: =IF(W$72=$C74,$J74,0) -> 0 | X74: =IF(X$72=$C74,$J74,0) -> 0 | Y74: =IF(Y$72=$C74,$J74,0) -> 0
A75: SCH | B75: 46099 | C75: XAUUSD | D75: ORO | F75: 45 | G75: 4885.886 | H75: =Hoja1!$H$11 -> 4720.375 | I75: =G75*F75 -> 219864.87 | J75: =H75*F75 -> 212416.88 | K75: =(H75-G75)*F75 -> -7447.995 | L75: =K75/(F75*G75) -> -0.03387533 | M75: =IF(N75="","",N75-TODAY()) -> 7 | N75: 46132
A76: SCH | B76: 46099 | C76: XAUUSD | D76: ORO | F76: 45 | G76: 4876.8528 | H76: =Hoja1!$H$11 -> 4720.375 | I76: =G76*F76 -> 219458.38 | J76: =H76*F76 -> 212416.88 | K76: =(H76-G76)*F76 -> -7041.501 | L76: =K76/(F76*G76) -> -0.032085816 | M76: =IF(N76="","",N76-TODAY()) -> 7 | N76: 46132
A77: SCH | B77: 46051 | C77: COPX | D77: ETF COBRE (EMPRESAS) | F77: 45 | G77: 99.74 | H77: =Hoja1!$H$77 -> 83.12 | I77: =G77*F77 -> 4488.3 | J77: =H77*F77 -> 3740.4 | K77: =(H77-G77)*F77 -> -747.9 | L77: =K77/(F77*G77) -> -0.16663325 | M77: =IF(N77="","",N77-TODAY()) | V77: =IF(V$72=$C77,$J77,0) -> 0 | W77: =IF(W$72=$C77,$J77,0) -> 0 | X77: =IF(X$72=$C77,$J77,0) -> 3740.4 | Y77: =IF(Y$72=$C77,$J77,0) -> 0
A78: SCH | B78: 46052 | C78: COPX | D78: ETF COBRE (EMPRESAS) | F78: 45 | G78: 87.7199 | H78: =Hoja1!$H$77 -> 83.12 | I78: =G78*F78 -> 3947.3955 | J78: =H78*F78 -> 3740.4 | K78: =(H78-G78)*F78 -> -206.9955 | L78: =K78/(F78*G78) -> -0.0524385 | M78: =IF(N78="","",N78-TODAY()) | V78: =IF(V$72=$C78,$J78,0) -> 0 | W78: =IF(W$72=$C78,$J78,0) -> 0 | X78: =IF(X$72=$C78,$J78,0) -> 3740.4 | Y78: =IF(Y$72=$C78,$J78,0) -> 0
A79: SCH | B79: 46055 | C79: COPX | D79: ETF COBRE (EMPRESAS) | F79: 45 | G79: 84.2387 | H79: =Hoja1!$H$77 -> 83.12 | I79: =G79*F79 -> 3790.7415 | J79: =H79*F79 -> 3740.4 | K79: =(H79-G79)*F79 -> -50.3415 | L79: =K79/(F79*G79) -> -0.013280119 | M79: =IF(N79="","",N79-TODAY()) | V79: =IF(V$72=$C79,$J79,0) -> 0 | W79: =IF(W$72=$C79,$J79,0) -> 0 | X79: =IF(X$72=$C79,$J79,0) -> 3740.4 | Y79: =IF(Y$72=$C79,$J79,0) -> 0
A80: SCH | B80: 46051 | C80: CPER | D80: ETF COBRE | F80: 45 | G80: 39.8699 | H80: =Hoja1!$H$82 -> 36.335 | I80: =G80*F80 -> 1794.1455 | J80: =H80*F80 -> 1635.075 | K80: =(H80-G80)*F80 -> -159.0705 | L80: =K80/(F80*G80) -> -0.088660869 | V80: =IF(V$72=$C80,$J80,0) -> 0 | W80: =IF(W$72=$C80,$J80,0) -> 0 | X80: =IF(X$72=$C80,$J80,0) -> 0 | Y80: =IF(Y$72=$C80,$J80,0) -> 1635.075
A81: SCH | B81: 46052 | C81: CPER | D81: ETF COBRE | F81: 45 | G81: 36.419 | H81: =Hoja1!$H$82 -> 36.335 | I81: =G81*F81 -> 1638.855 | J81: =H81*F81 -> 1635.075 | K81: =(H81-G81)*F81 -> -3.78 | L81: =K81/(F81*G81) -> -0.0023064884 | V81: =IF(V$72=$C81,$J81,0) -> 0 | W81: =IF(W$72=$C81,$J81,0) -> 0 | X81: =IF(X$72=$C81,$J81,0) -> 0 | Y81: =IF(Y$72=$C81,$J81,0) -> 1635.075
A82: SCH | B82: 46052 | C82: CPER | D82: ETF COBRE | F82: 45 | G82: 37.2 | H82: =Hoja1!$H$82 -> 36.335 | I82: =G82*F82 -> 1674 | J82: =H82*F82 -> 1635.075 | K82: =(H82-G82)*F82 -> -38.925 | L82: =K82/(F82*G82) -> -0.023252688 | V82: =IF(V$72=$C82,$J82,0) -> 0 | W82: =IF(W$72=$C82,$J82,0) -> 0 | X82: =IF(X$72=$C82,$J82,0) -> 0 | Y82: =IF(Y$72=$C82,$J82,0) -> 1635.075
A83: SCH | B83: 46055 | C83: CPER | D83: ETF COBRE | F83: 45 | G83: =(35.7206+35.7641)/2 -> 35.74235 | H83: =Hoja1!$H$82 -> 36.335 | I83: =G83*F83 -> 1608.4058 | J83: =H83*F83 -> 1635.075 | K83: =(H83-G83)*F83 -> 26.66925 | L83: =K83/(F83*G83) -> 0.016581171 | V83: =IF(V$72=$C83,$J83,0) -> 0 | W83: =IF(W$72=$C83,$J83,0) -> 0 | X83: =IF(X$72=$C83,$J83,0) -> 0 | Y83: =IF(Y$72=$C83,$J83,0) -> 1635.075
A84: SCH | B84: 46059 | C84: COPX | D84: ETF COBRE (EMPRESAS) | F84: 45 | G84: 84.4695 | H84: =Hoja1!$H$77 -> 83.12 | I84: =G84*F84 -> 3801.1275 | J84: =H84*F84 -> 3740.4 | K84: =(H84-G84)*F84 -> -60.7275 | L84: =K84/(F84*G84) -> -0.015976181 | V84: =IF(V$72=$C84,$J84,0) -> 0 | W84: =IF(W$72=$C84,$J84,0) -> 0 | X84: =IF(X$72=$C84,$J84,0) -> 3740.4 | Y84: =IF(Y$72=$C84,$J84,0) -> 0
A85: SCH | B85: 46056 | C85: CPER | D85: ETF COBRE | F85: 45 | G85: 37.2499 | H85: =Hoja1!$H$82 -> 36.335 | I85: =G85*F85 -> 1676.2455 | J85: =H85*F85 -> 1635.075 | K85: =(H85-G85)*F85 -> -41.1705 | L85: =K85/(F85*G85) -> -0.02456114 | V85: =IF(V$72=$C85,$J85,0) -> 0 | W85: =IF(W$72=$C85,$J85,0) -> 0 | X85: =IF(X$72=$C85,$J85,0) -> 0 | Y85: =IF(Y$72=$C85,$J85,0) -> 1635.075
V86: =IF(V$72=$C86,$J86,0) -> 0 | W86: =IF(W$72=$C86,$J86,0) -> 0 | X86: =IF(X$72=$C86,$J86,0) -> 0 | Y86: =IF(Y$72=$C86,$J86,0) -> 0
D87: 500000 | E87: =D87/H78 -> 6015.3994 | F87: =SUM(F74:F86) -> 518 | I87: =SUM(I74:I86) -> 465504.33 | J87: =SUM(J74:J86) -> 449736.44 | K87: =SUM(K74:K86) -> -15767.892 | V87: =SUM(V74:V86) -> 1765.71 | W87: =SUM(W74:W86) -> 0 | X87: =SUM(X74:X86) -> 14961.6 | Y87: =SUM(Y74:Y86) -> 8175.375
D88: 500000 | E88: =D88/H82 -> 13760.837 | V88: =+V72 -> XAGUSD | W88: =+W72 -> XAUUSD | X88: =+X72 -> COPX | Y88: =+Y72 -> CPER
H89: 5000 | I89: =+H89*H82 -> 181675 | V89: =+V87 -> 1765.71 | W89: =+W87 -> 0 | X89: =+X87 -> 14961.6 | Y89: =+Y87 -> 8175.375
V90: =+V89/$J87 -> 0.0039260995 | W90: =+W89/$J87 -> 0 | X90: =+X89/$J87 -> 0.033267485 | Y90: =+Y89/$J87 -> 0.018178147
A91: EQUITY
V92: AMZN | W92: ARGT | X92: BCH | Y92: BLK | Z92: BRK/B | AA92: CRCL | AB92: AIQ | AC92: QQQ | AD92: ESM6 | AE92: SPY | AF92: GOOG | AG92: LTM | AH92: META | AI92: MSFT | AJ92: NVDA | AK92: TGS | AL92: USCI | AM92: PLTR | AN92: FCX | AO92: XBI | AP92: ARKK | AQ92: ECH | AR92: QTUM | AS92: SLV | AT92: IIF | AU92: RKLB | AV92: XIACY | AW92: BYDDY | AX92: JD | AY92: BABA | AZ92: TCEHY
A93: BANCO | B93: FECHA | C93: NOMBRE | D93: TICKER | E93: precio 31-12-2025 | F93: CANTIDAD | G93: PRECIO COMPRA | H93: PRECIO ACTUAL | I93: COSTO | J93: VP | K93: MTM | L93: MTM trib | M93: Retorno | N93: VP Cierre 2025 | O93: LTV | P93: Monto LTV
A94: PUP | B94: 46091 | C94: Amazon | D94: AMZN | E94: 230.82 | F94: 12 | G94: 213.91 | H94: 210.1601 | I94: =G94*F94 -> 2566.92 | J94: =H94*F94 -> 2521.9212 | K94: =(H94-E94)*F94 -> -247.9188 | L94: =(H94-G94)*F94 -> -44.9988 | M94: =+(H94-E94)/E94 -> -0.089506542 | N94: =F94*E94 -> 2769.84 | V94: =IF(V$92=$D94,$J94,0) -> 2521.9212 | W94: =IF(W$92=$D94,$J94,0) -> 0 | X94: =IF(X$92=$D94,$J94,0) -> 0 | Y94: =IF(Y$92=$D94,$J94,0) -> 0 | Z94: =IF(Z$92=$D94,$J94,0) -> 0 | AA94: =IF(AA$92=$D94,$J94,0) -> 0 | AB94: =IF(AB$92=$D94,$J94,0) -> 0 | AC94: =IF(AC$92=$D94,$J94,0) -> 0 | ... AZ94: =IF(AZ$92=$D94,$J94,0) -> 0
A95: PUP | B95: 45883 | C95: Amazon | D95: AMZN | E95: 230.82 | F95: 2 | G95: 228.8007 | H95: =Hoja1!H30 -> 236.985 | I95: =G95*F95 -> 457.6014 | J95: =H95*F95 -> 473.97 | K95: =(H95-E95)*F95 -> 12.33 | L95: =(H95-G95)*F95 -> 16.3686 | M95: =+(H95-E95)/E95 -> 0.026709124 | N95: =F95*E95 -> 461.64 | O95: 0.5 | P95: =O95*J95 -> 236.985 | V95: =IF(V$92=$D95,$J95,0) -> 473.97 | W95: =IF(W$92=$D95,$J95,0) -> 0 | X95: =IF(X$92=$D95,$J95,0) -> 0 | Y95: =IF(Y$92=$D95,$J95,0) -> 0 | Z95: =IF(Z$92=$D95,$J95,0) -> 0 | AA95: =IF(AA$92=$D95,$J95,0) -> 0 | AB95: =IF(AB$92=$D95,$J95,0) -> 0 | AC95: =IF(AC$92=$D95,$J95,0) -> 0 | ... AZ95: =IF(AZ$92=$D95,$J95,0) -> 0
A96: PUP | C96: ETF Argentina | D96: ARGT | E96: 91.41 | F96: -8 | G96: 90.3386 | H96: 87.1797 | I96: =G96*F96 -> -722.7088 | J96: =H96*F96 -> -697.4376 | K96: =(H96-E96)*F96 -> 33.8424 | L96: =(H96-G96)*F96 -> 25.2712 | M96: =+(H96-E96)/E96 -> -0.046278307 | N96: =F96*E96 -> -731.28 | V96: =IF(V$92=$D96,$J96,0) -> 0 | W96: =IF(W$92=$D96,$J96,0) -> -697.4376 | X96: =IF(X$92=$D96,$J96,0) -> 0 | Y96: =IF(Y$92=$D96,$J96,0) -> 0 | Z96: =IF(Z$92=$D96,$J96,0) -> 0 | AA96: =IF(AA$92=$D96,$J96,0) -> 0 | AB96: =IF(AB$92=$D96,$J96,0) -> 0 | AC96: =IF(AC$92=$D96,$J96,0) -> 0 | ... AZ96: =IF(AZ$92=$D96,$J96,0) -> 0
A97: PUP | B97: 45860 | C97: Banco de Chile | D97: BCH | E97: 38 | F97: -18 | G97: 28.3768 | H97: =Hoja1!H46 -> 38.29 | I97: =G97*F97 -> -510.7824 | J97: =H97*F97 -> -689.22 | K97: =(H97-E97)*F97 -> -5.22 | L97: =(H97-G97)*F97 -> -178.4376 | M97: =+(H97-E97)/E97 -> 0.0076315789 | N97: =F97*E97 -> -684 | V97: =IF(V$92=$D97,$J97,0) -> 0 | W97: =IF(W$92=$D97,$J97,0) -> 0 | X97: =IF(X$92=$D97,$J97,0) -> -689.22 | Y97: =IF(Y$92=$D97,$J97,0) -> 0 | Z97: =IF(Z$92=$D97,$J97,0) -> 0 | AA97: =IF(AA$92=$D97,$J97,0) -> 0 | AB97: =IF(AB$92=$D97,$J97,0) -> 0 | AC97: =IF(AC$92=$D97,$J97,0) -> 0 | ... AZ97: =IF(AZ$92=$D97,$J97,0) -> 0
A98: PUP | B98: 45783 | C98: Black Rock | D98: BLK | E98: 1070.34 | F98: -28 | G98: 917.8399 | H98: =Hoja1!H183 -> 1002.635 | I98: =G98*F98 -> -25699.517 | J98: =H98*F98 -> -28073.78 | K98: =(H98-E98)*F98 -> 1895.74 | L98: =(H98-G98)*F98 -> -2374.2628 | M98: =+(H98-E98)/E98 -> -0.063255601 | N98: =F98*E98 -> -29969.52 | V98: =IF(V$92=$D98,$J98,0) -> 0 | W98: =IF(W$92=$D98,$J98,0) -> 0 | X98: =IF(X$92=$D98,$J98,0) -> 0 | Y98: =IF(Y$92=$D98,$J98,0) -> -28073.78 | Z98: =IF(Z$92=$D98,$J98,0) -> 0 | AA98: =IF(AA$92=$D98,$J98,0) -> 0 | AB98: =IF(AB$92=$D98,$J98,0) -> 0 | AC98: =IF(AC$92=$D98,$J98,0) -> 0 | ... AZ98: =IF(AZ$92=$D98,$J98,0) -> 0
A99: PUP | B99: 45782 | C99: Berkshire | D99: BRK/B | E99: 502.65 | F99: -38 | G99: =(200*517.415+90*517.72+90*515.5444)/380 -> 517.0442 | H99: =Hoja1!H182 -> 480.04 | I99: =G99*F99 -> -19647.68 | J99: =H99*F99 -> -18241.52 | K99: =(H99-E99)*F99 -> 859.18 | L99: =(H99-G99)*F99 -> 1406.1596 | M99: =+(H99-E99)/E99 -> -0.044981598 | N99: =F99*E99 -> -19100.7 | V99: =IF(V$92=$D99,$J99,0) -> 0 | W99: =IF(W$92=$D99,$J99,0) -> 0 | X99: =IF(X$92=$D99,$J99,0) -> 0 | Y99: =IF(Y$92=$D99,$J99,0) -> 0 | Z99: =IF(Z$92=$D99,$J99,0) -> -18241.52 | AA99: =IF(AA$92=$D99,$J99,0) -> 0 | AB99: =IF(AB$92=$D99,$J99,0) -> 0 | AC99: =IF(AC$92=$D99,$J99,0) -> 0 | ... AZ99: =IF(AZ$92=$D99,$J99,0) -> 0
A100: PUP | C100: Circle Internet Group | D100: CRCL | E100: 79.3 | F100: -48 | G100: 229.7046 | H100: 118.7721 | I100: =G100*F100 -> -11025.821 | J100: =H100*F100 -> -5701.0608 | K100: =(H100-E100)*F100 -> -1894.6608 | L100: =(H100-G100)*F100 -> 5324.76 | M100: =+(H100-E100)/E100 -> 0.49775662 | N100: =F100*E100 -> -3806.4 | O100: 0.5 | P100: =O100*J100 -> -2850.5304 | V100: =IF(V$92=$D100,$J100,0) -> 0 | W100: =IF(W$92=$D100,$J100,0) -> 0 | X100: =IF(X$92=$D100,$J100,0) -> 0 | Y100: =IF(Y$92=$D100,$J100,0) -> 0 | Z100: =IF(Z$92=$D100,$J100,0) -> 0 | AA100: =IF(AA$92=$D100,$J100,0) -> -5701.0608 | AB100: =IF(AB$92=$D100,$J100,0) -> 0 | AC100: =IF(AC$92=$D100,$J100,0) -> 0 | ... AZ100: =IF(AZ$92=$D100,$J100,0) -> 0
A101: PUP | B101: 45873 | C101: ETF AI | D101: AIQ | E101: 50.86 | F101: -58 | G101: 44.17 | H101: =Hoja1!H174 -> 49.635 | I101: =G101*F101 -> -2561.86 | J101: =H101*F101 -> -2878.83 | K101: =(H101-E101)*F101 -> 71.05 | L101: =(H101-G101)*F101 -> -316.97 | M101: =+(H101-E101)/E101 -> -0.024085726 | N101: =F101*E101 -> -2949.88 | O101: 0.75 | P101: =O101*J101 -> -2159.1225 | V101: =IF(V$92=$D101,$J101,0) -> 0 | W101: =IF(W$92=$D101,$J101,0) -> 0 | X101: =IF(X$92=$D101,$J101,0) -> 0 | Y101: =IF(Y$92=$D101,$J101,0) -> 0 | Z101: =IF(Z$92=$D101,$J101,0) -> 0 | AA101: =IF(AA$92=$D101,$J101,0) -> 0 | AB101: =IF(AB$92=$D101,$J101,0) -> -2878.83 | AC101: =IF(AC$92=$D101,$J101,0) -> 0 | ... AZ101: =IF(AZ$92=$D101,$J101,0) -> 0
A102: PUP | B102: 45940 | C102: ETF AI | D102: AIQ | E102: 50.86 | F102: -68 | G102: 49.2772 | H102: =Hoja1!H174 -> 49.635 | I102: =G102*F102 -> -3350.8496 | J102: =H102*F102 -> -3375.18 | K102: =(H102-E102)*F102 -> 83.3 | L102: =(H102-G102)*F102 -> -24.3304 | M102: =+(H102-E102)/E102 -> -0.024085726 | N102: =F102*E102 -> -3458.48 | O102: 0.5 | P102: =O102*J102 -> -1687.59 | V102: =IF(V$92=$D102,$J102,0) -> 0 | W102: =IF(W$92=$D102,$J102,0) -> 0 | X102: =IF(X$92=$D102,$J102,0) -> 0 | Y102: =IF(Y$92=$D102,$J102,0) -> 0 | Z102: =IF(Z$92=$D102,$J102,0) -> 0 | AA102: =IF(AA$92=$D102,$J102,0) -> 0 | AB102: =IF(AB$92=$D102,$J102,0) -> -3375.18 | AC102: =IF(AC$92=$D102,$J102,0) -> 0 | ... AZ102: =IF(AZ$92=$D102,$J102,0) -> 0
A103: PUP | B103: 45950 | C103: ETF AI | D103: AIQ | E103: 50.86 | F103: -78 | G103: 51.12 | H103: =Hoja1!H174 -> 49.635 | I103: =G103*F103 -> -3987.36 | J103: =H103*F103 -> -3871.53 | K103: =(H103-E103)*F103 -> 95.55 | L103: =(H103-G103)*F103 -> 115.83 | M103: =+(H103-E103)/E103 -> -0.024085726 | N103: =F103*E103 -> -3967.08 | O103: 0.5 | P103: =O103*J103 -> -1935.765 | S103: LTV EQUITY | V103: =IF(V$92=$D103,$J103,0) -> 0 | W103: =IF(W$92=$D103,$J103,0) -> 0 | X103: =IF(X$92=$D103,$J103,0) -> 0 | Y103: =IF(Y$92=$D103,$J103,0) -> 0 | Z103: =IF(Z$92=$D103,$J103,0) -> 0 | AA103: =IF(AA$92=$D103,$J103,0) -> 0 | AB103: =IF(AB$92=$D103,$J103,0) -> -3871.53 | AC103: =IF(AC$92=$D103,$J103,0) -> 0 | ... AZ103: =IF(AZ$92=$D103,$J103,0) -> 0
A104: PUP | B104: 45981 | C104: ETF Nasdaq | D104: QQQ | E104: 614.31 | F104: -88 | G104: 611.66 | H104: =Hoja1!H154 -> 611.135 | I104: =G104*F104 -> -53826.08 | J104: =H104*F104 -> -53779.88 | K104: =(H104-E104)*F104 -> 279.4 | L104: =(H104-G104)*F104 -> 46.2 | M104: =+(H104-E104)/E104 -> -0.0051684003 | N104: =F104*E104 -> -54059.28 | O104: 0.75 | P104: =O104*J104 -> -40334.91 | R104: DB | S104: =SUMIF($A$94:$A$147,R104,$P$94:$P$147) -> 0 | V104: =IF(V$92=$D104,$J104,0) -> 0 | W104: =IF(W$92=$D104,$J104,0) -> 0 | X104: =IF(X$92=$D104,$J104,0) -> 0 | Y104: =IF(Y$92=$D104,$J104,0) -> 0 | Z104: =IF(Z$92=$D104,$J104,0) -> 0 | AA104: =IF(AA$92=$D104,$J104,0) -> 0 | AB104: =IF(AB$92=$D104,$J104,0) -> 0 | AC104: =IF(AC$92=$D104,$J104,0) -> -53779.88 | ... AZ104: =IF(AZ$92=$D104,$J104,0) -> 0
A105: PUP | B105: 45981 | C105: ETF Nasdaq | D105: QQQ | E105: 614.31 | F105: -98 | G105: 611.719 | H105: =Hoja1!H154 -> 611.135 | I105: =G105*F105 -> -59948.462 | J105: =H105*F105 -> -59891.23 | K105: =(H105-E105)*F105 -> 311.15 | L105: =(H105-G105)*F105 -> 57.232 | M105: =+(H105-E105)/E105 -> -0.0051684003 | N105: =F105*E105 -> -60202.38 | O105: 0.5 | P105: =O105*J105 -> -29945.615 | R105: MS-K | S105: =SUMIF($A$94:$A$147,R105,$P$94:$P$147) -> 0 | V105: =IF(V$92=$D105,$J105,0) -> 0 | W105: =IF(W$92=$D105,$J105,0) -> 0 | X105: =IF(X$92=$D105,$J105,0) -> 0 | Y105: =IF(Y$92=$D105,$J105,0) -> 0 | Z105: =IF(Z$92=$D105,$J105,0) -> 0 | AA105: =IF(AA$92=$D105,$J105,0) -> 0 | AB105: =IF(AB$92=$D105,$J105,0) -> 0 | AC105: =IF(AC$92=$D105,$J105,0) -> -59891.23 | ... AZ105: =IF(AZ$92=$D105,$J105,0) -> 0
A106: PUP | B106: 45981 | C106: ETF Nasdaq | D106: QQQ | E106: 614.31 | F106: -108 | G106: 605.65 | H106: =Hoja1!H154 -> 611.135 | I106: =G106*F106 -> -65410.2 | J106: =H106*F106 -> -66002.58 | K106: =(H106-E106)*F106 -> 342.9 | L106: =(H106-G106)*F106 -> -592.38 | M106: =+(H106-E106)/E106 -> -0.0051684003 | N106: =F106*E106 -> -66345.48 | O106: 0.5 | P106: =O106*J106 -> -33001.29 | R106: MS | S106: =SUMIF($A$94:$A$147,R106,$P$94:$P$147) -> 0 | V106: =IF(V$92=$D106,$J106,0) -> 0 | W106: =IF(W$92=$D106,$J106,0) -> 0 | X106: =IF(X$92=$D106,$J106,0) -> 0 | Y106: =IF(Y$92=$D106,$J106,0) -> 0 | Z106: =IF(Z$92=$D106,$J106,0) -> 0 | AA106: =IF(AA$92=$D106,$J106,0) -> 0 | AB106: =IF(AB$92=$D106,$J106,0) -> 0 | AC106: =IF(AC$92=$D106,$J106,0) -> -66002.58 | ... AZ106: =IF(AZ$92=$D106,$J106,0) -> 0
A107: PUP | B107: 45981 | C107: ETF Nasdaq | D107: QQQ | E107: 614.31 | F107: -118 | G107: 605.88 | H107: =Hoja1!H154 -> 611.135 | I107: =G107*F107 -> -71493.84 | J107: =H107*F107 -> -72113.93 | K107: =(H107-E107)*F107 -> 374.65 | L107: =(H107-G107)*F107 -> -620.09 | M107: =+(H107-E107)/E107 -> -0.0051684003 | N107: =F107*E107 -> -72488.58 | O107: 0.5 | P107: =O107*J107 -> -36056.965 | R107: UBS-H | S107: =SUMIF($A$94:$A$147,R107,$P$94:$P$147) -> 0 | V107: =IF(V$92=$D107,$J107,0) -> 0 | W107: =IF(W$92=$D107,$J107,0) -> 0 | X107: =IF(X$92=$D107,$J107,0) -> 0 | Y107: =IF(Y$92=$D107,$J107,0) -> 0 | Z107: =IF(Z$92=$D107,$J107,0) -> 0 | AA107: =IF(AA$92=$D107,$J107,0) -> 0 | AB107: =IF(AB$92=$D107,$J107,0) -> 0 | AC107: =IF(AC$92=$D107,$J107,0) -> -72113.93 | ... AZ107: =IF(AZ$92=$D107,$J107,0) -> 0
A108: PUP | B108: 46077 | C108: Futuro S&P | D108: ESM6 | E108: 6892.5 | F108: -128 | G108: 6903.8833 | H108: =Hoja1!H12*10.115 -> 6870.6138 | I108: =G108*F108*50 -> -44184853 | J108: =H108*F108*50 -> -43971928 | K108: =(H108-E108)*F108*50 -> 140072 | L108: =(H108-G108)*F108*50 -> 212925.12 | M108: =+(H108-E108)/E108 -> -0.0031753718 | N108: =F108*E108*50 -> -44112000 | O108: 0.5 | P108: =O108*J108 -> -21985964 | V108: =IF(V$92=$D108,$J108,0) -> 0 | W108: =IF(W$92=$D108,$J108,0) -> 0 | X108: =IF(X$92=$D108,$J108,0) -> 0 | Y108: =IF(Y$92=$D108,$J108,0) -> 0 | Z108: =IF(Z$92=$D108,$J108,0) -> 0 | AA108: =IF(AA$92=$D108,$J108,0) -> 0 | AB108: =IF(AB$92=$D108,$J108,0) -> 0 | AC108: =IF(AC$92=$D108,$J108,0) -> 0 | ... AZ108: =IF(AZ$92=$D108,$J108,0) -> 0
A109: PUP | B109: 45882 | C109: S&P | D109: SPY | E109: 681.92 | F109: -138 | G109: 643.2298 | H109: =Hoja1!H12 -> 679.25 | I109: =G109*F109 -> -88765.712 | J109: =H109*F109 -> -93736.5 | K109: =(H109-E109)*F109 -> 368.46 | L109: =(H109-G109)*F109 -> -4970.7876 | M109: =+(H109-E109)/E109 -> -0.0039154153 | N109: =F109*E109 -> -94104.96 | O109: 0.5 | P109: =O109*J109 -> -46868.25 | V109: =IF(V$92=$D109,$J109,0) -> 0 | W109: =IF(W$92=$D109,$J109,0) -> 0 | X109: =IF(X$92=$D109,$J109,0) -> 0 | Y109: =IF(Y$92=$D109,$J109,0) -> 0 | Z109: =IF(Z$92=$D109,$J109,0) -> 0 | AA109: =IF(AA$92=$D109,$J109,0) -> 0 | AB109: =IF(AB$92=$D109,$J109,0) -> 0 | AC109: =IF(AC$92=$D109,$J109,0) -> 0 | ... AZ109: =IF(AZ$92=$D109,$J109,0) -> 0
A110: PUP | B110: 45940 | C110: S&P | D110: SPY | E110: 681.92 | F110: -148 | G110: 657.195 | H110: =H109 -> 679.25 | I110: =G110*F110 -> -97264.86 | J110: =H110*F110 -> -100529 | K110: =(H110-E110)*F110 -> 395.16 | L110: =(H110-G110)*F110 -> -3264.14 | M110: =+(H110-E110)/E110 -> -0.0039154153 | N110: =F110*E110 -> -100924.16 | O110: 0.5 | P110: =O110*J110 -> -50264.5 | V110: =IF(V$92=$D110,$J110,0) -> 0 | W110: =IF(W$92=$D110,$J110,0) -> 0 | X110: =IF(X$92=$D110,$J110,0) -> 0 | Y110: =IF(Y$92=$D110,$J110,0) -> 0 | Z110: =IF(Z$92=$D110,$J110,0) -> 0 | AA110: =IF(AA$92=$D110,$J110,0) -> 0 | AB110: =IF(AB$92=$D110,$J110,0) -> 0 | AC110: =IF(AC$92=$D110,$J110,0) -> 0 | ... AZ110: =IF(AZ$92=$D110,$J110,0) -> 0
A111: PUP | B111: 45883 | C111: GOOG | D111: GOOG | E111: 313.8 | F111: -158 | G111: 204.445 | H111: =Hoja1!H23 -> 316.16 | I111: =G111*F111 -> -32302.31 | J111: =H111*F111 -> -49953.28 | K111: =(H111-E111)*F111 -> -372.88 | L111: =(H111-G111)*F111 -> -17650.97 | M111: =+(H111-E111)/E111 -> 0.0075207138 | N111: =F111*E111 -> -49580.4 | O111: 0.5 | P111: =O111*J111 -> -24976.64 | V111: =IF(V$92=$D111,$J111,0) -> 0 | W111: =IF(W$92=$D111,$J111,0) -> 0 | X111: =IF(X$92=$D111,$J111,0) -> 0 | Y111: =IF(Y$92=$D111,$J111,0) -> 0 | Z111: =IF(Z$92=$D111,$J111,0) -> 0 | AA111: =IF(AA$92=$D111,$J111,0) -> 0 | AB111: =IF(AB$92=$D111,$J111,0) -> 0 | AC111: =IF(AC$92=$D111,$J111,0) -> 0 | ... AZ111: =IF(AZ$92=$D111,$J111,0) -> 0
...

Sheet Equity
C4: =+cartera!V92 -> AMZN | D4: =+cartera!W92 -> ARGT | E4: =+cartera!X92 -> BCH | F4: =+cartera!Y92 -> BLK | G4: =+cartera!Z92 -> BRK/B | H4: =+cartera!AA92 -> CRCL | I4: =+cartera!AB92 -> AIQ | J4: =+cartera!AC92 -> QQQ | ... AG4: =+cartera!AZ92 -> TCEHY
C5: =+cartera!V151 -> 2995.8912 | D5: =+cartera!W151 -> -697.4376 | E5: =+cartera!X151 -> -689.22 | F5: =+cartera!Y151 -> -28073.78 | G5: =+cartera!Z151 -> -18241.52 | H5: =+cartera!AA151 -> -5701.0608 | I5: =+cartera!AB151 -> -10125.54 | J5: =+cartera!AC151 -> -251787.62 | ... AG5: =+cartera!AZ151 -> -32696.16
M8: TICKER | N8: VP USD | O8: % | P8: Rt 2026
M9: AMZN | N9: =_xlfn.XLOOKUP(M9,C$4:AG$4,C$5:AG$5,"") -> 2995.8912 | O9: =+N9/N$42 -> -6.5078894e-05
M10: ARGT | N10: =_xlfn.XLOOKUP(M10,C$4:AG$4,C$5:AG$5,"") -> -697.4376 | O10: =+N10/N$42 -> 1.5150239e-05
M11: BCH | N11: =_xlfn.XLOOKUP(M11,C$4:AG$4,C$5:AG$5,"") -> -689.22 | O11: =+N11/N$42 -> 1.497173e-05
M12: BLK | N12: =_xlfn.XLOOKUP(M12,C$4:AG$4,C$5:AG$5,"") -> -28073.78 | O12: =+N12/N$42 -> 0.00060983876
M13: BRK/B | N13: =_xlfn.XLOOKUP(M13,C$4:AG$4,C$5:AG$5,"") -> -18241.52 | O13: =+N13/N$42 -> 0.00039625536
M14: CRCL | N14: =_xlfn.XLOOKUP(M14,C$4:AG$4,C$5:AG$5,"") -> -5701.0608 | O14: =+N14/N$42 -> 0.00012384253
M15: AIQ | N15: =_xlfn.XLOOKUP(M15,C$4:AG$4,C$5:AG$5,"") -> -10125.54 | O15: =+N15/N$42 -> 0.00021995423
M16: QQQ | N16: =_xlfn.XLOOKUP(M16,C$4:AG$4,C$5:AG$5,"") -> -251787.62 | O16: =+N16/N$42 -> 0.005469511
M17: ESM6 | N17: =_xlfn.XLOOKUP(M17,C$4:AG$4,C$5:AG$5,"") -> -43971928 | O17: =+N17/N$42 -> 0.95518971
M18: SPY | N18: =_xlfn.XLOOKUP(M18,C$4:AG$4,C$5:AG$5,"") -> -194265.5 | O18: =+N18/N$42 -> 0.0042199743
M19: GOOG | N19: =_xlfn.XLOOKUP(M19,C$4:AG$4,C$5:AG$5,"") -> -49953.28 | O19: =+N19/N$42 -> 0.0010851209
M20: LTM | N20: =_xlfn.XLOOKUP(M20,C$4:AG$4,C$5:AG$5,"") -> -48814.2 | O20: =+N20/N$42 -> 0.001060377
... M39: TCEHY | N39: =_xlfn.XLOOKUP(M39,C$4:AG$4,C$5:AG$5,"") -> -32696.16 | O39: =+N39/N$42 -> 0.0007102494
M42: TOTAL | N42: =SUM(N9:N41) -> -46034759

Sheet registro
A1: BANCO | B1: FECHA | C1: NOMBRE | D1: TICKER | E1: precio 31-12-2025 | F1: CANTIDAD | G1: PRECIO COMPRA | H1: PRECIO ACTUAL | I1: COSTO | J1: VP | K1: MTM | L1: MTM trib | M1: Retorno | N1: FECHA CIERRE
A2: SCH | B2: 46045 | C2: ETF Plata | D2: SLV | F2: 13 | G2: =F2*1.1 -> 14.3 | H2: =G2*1.2 -> 17.16 | I2: 1537.9684 | J2: 11.830526 | K2: 183.2633 | L2: 1.832633 | N2: 46048
A3: SCH | B3: 45986 | C3: Futuro S&P | D3: ESH6 | E3: 6892.5 | F3: 3 | G3: =F3*1.1 -> 3.3 | H3: =G3*1.2 -> 3.96 | I3: 7822.3846 | J3: 60.172189 | K3: -61.5 | L3: -0.615 | M3: -0.0059484947 | N3: 46077
A4: SCH | B4: 45873 | C4: META | D4: META | E4: 660.09 | F4: 4 | G4: =F4*1.1 -> 4.4 | H4: =G4*1.2 -> 5.28 | I4: 772.3499 | J4: 5.9411531 | K4: -32.0905 | L4: -0.320905 | M4: -0.037396416 | N4: 46090
A5: SCH | B5: 45870 | C5: Amazon | D5: AMZN | E5: 230.82 | F5: 5 | G5: =F5*1.1 -> 5.5 | H5: =G5*1.2 -> 6.6 | I5: 1538.474 | J5: 11.834415 | K5: -192.13707 | L5: -1.9213707 | M5: -0.089506542 | N5: 46090
A6: SCH | B6: 45859 | C6: Circle Internet Group | D6: CRCL | E6: 79.3 | F6: 23 | G6: =F6*1.1 -> 25.3 | H6: =G6*1.2 -> 30.36 | I6: 768.62693 | J6: 5.9125149 | K6: 171.70363 | L6: 1.7170363 | M6: 0.49775662 | N6: 46091
J112: REALIZADO | K112: =SUM(K2:K111) -> 69.239365
J113: MTM | K113: =cartera!K150 -> 65103.668
J115: TOTAL | K115: =SUM(K112:K114) -> 65172.907
A123: FONDOS
A125: BANCO | B125: FECHA | C125: NOMBRE | D125: TICKER | F125: CANTIDAD | G125: PRECIO COMPRA | I125: PRECIO VENTA | J125: VP | K125: Resultado | L125: Retorno | M125: Fecha Cierre
J132: MTM | K132: =SUM(K126:K131) -> 0
A137: ORO
A138: CS-K | B138: 46035 | C138: XAUUSD | D138: ORO | F138: -1400 | G138: 4627 | H138: 4608.755 | I138: -14082.174 | J138: -14082.174 | K138: 45.6125 | L138: -0.0039431597 | M138: 0 | N138: 46038
A139: CS-K | B139: 46008 | C139: XAUUSD | D139: ORO | F139: 1400 | G139: 4333.3 | H139: 4608.755 | I139: 13188.304 | J139: 13188.304 | K139: 688.6375 | L139: 0.063567027 | M139: 0 | N139: 46038
A140: CS-K | B140: 46035 | C140: XAUUSD | D140: ORO | F140: 1400 | G140: 4634.54 | H140: 5280.325 | I140: 14105.122 | J140: 14105.122 | K140: 1614.4625 | L140: 0.13934177 | M140: 2 | N140: 46052
A141: CS-K | B141: 46050 | C141: XAUUSD | D141: ORO | F141: -1400 | G141: 5275 | H141: 5280.325 | I141: -16054.348 | J141: -16054.348 | K141: -13.3125 | L141: 0.0010094787 | M141: 2 | N141: 46052
A142: UBS | B142: 46048 | C142: XAGUSD | D142: PLATA | F142: 3000 | G142: 110 | H142: 115.45755 | I142: 717.3913 | J142: 717.3913 | K142: 29.236875 | L142: 0.049614091 | M142: 16 | N142: 46066
A143: UBS | B143: 46050 | C143: XAGUSD | D143: PLATA | F143: -3000 | G143: 115.2 | H143: 115.45755 | I143: -750 | J143: -750 | K143: -1.3797321 | L143: 0.0039786957 | M143: 16 | N143: 46066
A144: CS-K | B144: 46050 | C144: XAUUSD | D144: ORO | F144: 700 | G144: 5291.5 | H144: 5297.0001 | I144: 8052.2826 | J144: 8052.2826 | K144: 6.8751875 | L144: 0.0010394312 | M144: 30 | N144: 46080
A145: CS-K | B145: 46050 | C145: XAUUSD | D145: ORO | F145: -200 | G145: 5285 | H145: 5297.0001 | I145: -2297.8261 | J145: -2297.8261 | K145: -4.2857679 | L145: 0.0022706055 | M145: 30 | N145: 46080
A146: CS-K | B146: 46050 | C146: XAUUSD | D146: ORO | F146: -500 | G146: 5302 | H146: 5297.0001 | I146: -5763.0435 | J146: -5763.0435 | K146: 4.4641518 | L146: -0.00094301207 | M146: 30 | N146: 46080
A147: SCHWAB | B147: 46056 | C147: COPX | D147: ETF COBRE (EMPRESAS) | F147: 5600 | G147: 88.9282 | H147: 84.3218 | I147: 1082.6042 | J147: 1082.6042 | K147: -46.064 | L147: -0.046646621 | N147: 46059
A148: UBS-H | B148: 46048 | C148: XAGUSD | D148: PLATA | F148: 6000 | G148: 110.75 | H148: 83.43 | I148: 1444.5652 | J148: 1444.5652 | K148: -292.71429 | L148: -0.24668172 | M148: 1 | N148: 46066
A149: UBS-H | B149: 46052 | C149: XAGUSD | D149: PLATA | F149: 6000 | G149: 103.5 | H149: 83.43 | I149: 1350 | J149: 1350 | K149: -215.03571 | L149: -0.19391304 | M149: 1 | N149: 46066
A150: UBS-H | B150: 46052 | C150: XAGUSD | D150: PLATA | F150: 3000 | G150: 86 | H150: 83.43 | I150: 560.86957 | J150: 560.86957 | K150: -13.767857 | L150: -0.029883721 | M150: 1 | N150: 46066
A151: UBS-H | B151: 46064 | C151: XAGUSD | D151: PLATA | F151: -15000 | G151: 83.288 | H151: 83.43 | I151: -2715.913 | J151: -2715.913 | K151: -3.8035714 | L151: 0.0017049275 | M151: 1 | N151: 46066
A152: UBS-H | B152: 46078 | C152: XAGUSD | D152: PLATA | F152: -15000 | G152: 90.31 | H152: 90.2739 | I152: -2942.9348 | J152: -2942.9348 | K152: 0.96696429 | L152: 0.00026481994 | M152: 2 | N152: 46080
A153: UBS-H | B153: 46064 | C153: XAGUSD | D153: PLATA | F153: 15000 | G153: 83.46 | H153: 90.2739 | I153: 2721.5217 | J153: 2721.5217 | K153: 182.51518 | L153: 0.081642703 | M153: 2 | N153: 46080
A154: CS-M | B154: 46056 | C154: XAUUSD | D154: ORO | F154: 200 | G154: 4933 | H154: 5184.735 | I154: 2144.7826 | J154: 2144.7826 | K154: 89.905357 | L154: 0.051030813 | M154: 2 | N154: 46080
A155: CS-M | B155: 46078 | C155: XAUUSD | D155: ORO | F155: -200 | G155: 5185 | H155: 5184.735 | I155: -2254.3478 | J155: -2254.3478 | K155: 0.094642857 | L155: -5.1108968e-05 | M155: 2 | N155: 46080
A156: CS-K | B156: 46050 | C156: XAUUSD | D156: ORO | F156: 700 | G156: 5291.5 | H156: 5182.8 | I156: 8052.2826 | J156: 8052.2826 | K156: -135.875 | L156: -0.020542379 | M156: 2 | N156: 46080
A157: UBS-H | B157: 46052 | C157: XAUUSD | D157: ORO | F157: 400 | G157: 5143 | H157: 5182.8 | I157: 4472.1739 | J157: 4472.1739 | K157: 28.428571 | L157: 0.0077386739 | M157: 2 | N157: 46080
A158: UBS-H | B158: 46052 | C158: XAUUSD | D158: ORO | F158: 200 | G158: 4820 | H158: 5182.8 | I158: 2095.6522 | J158: 2095.6522 | K158: 129.57143 | L158: 0.07526971 | M158: 2 | N158: 46080
A159: CS-K | B159: 46078 | C159: XAUUSD | D159: ORO | F159: 200 | G159: 5185 | H159: 5182.8 | I159: 2144.7826 | J159: 2144.7826 | K159: -0.78571429 | L159: 0.050638557 | M159: 2 | N159: 46080
... A167: UBS-H | B167: 46099 | C167: XAUUSD | D167: ORO | F167: -600 | G167: 4856.95 | H167: 4868.63 | I167: -6341.7391 | J167: -6341.7391 | K167: -12.514286 | L167: 0.0013636364 | M167: 2 | N167: 46101
J194: REALIZADO | K194: =SUM(K138:K193) -> 819.36171
J195: MTM | K195: =cartera!K87 -> -15767.892
J197: TOTAL | K197: =K194+K195 -> -14948.53
A206: FUTURO TREASURY
A208: Instumento | B208: fecha | C208: Contraparte | D208: Pos | E208: ytm inicial | F208: ytm merc | G208: Precio Inicial | H208: Monto | I208: Precio Cierre | J208: result | K208: Fecha cierre
A209: WNH6 | B209: 45986 | C209: CS-K | D209: 39 | E209: 0.0467 | G209: 121.09375 | H209: 3190.494 | I209: 120.09375 | J209: -1695.6522 | K209: 46065
A210: WNH6 | B210: 45986 | C210: CS-K | D210: 11 | E210: 0.0467 | G210: 121.09375 | H210: 398.81175 | I210: 120.09375 | J210: -478.26087 | K210: 46065
A211: WNH6 | B211: 45986 | C211: CS-K | D211: 49 | E211: 0.0467 | G211: 121.09375 | H211: 1776.5251 | I211: 120.59375 | J211: -1065.2174 | K211: 46066
I225: REALIZADO | J225: =SUM(J209:J224) -> -3239.1304
I226: MTM | J226: =cartera!J166 -> -992.625
I228: TOTAL | J228: =J225+J226 -> -4231.7554

Sheet registro rf
A1: BANCO | B1: ISIN | C1: Name | D1: Monto Compra | E1: Coupon | F1: Maturity | G1: PRECIO COMPRA | H1: Precio 31-Dic-2021 | I1: Precio 31-Dic-2023 | J1: Precio Venta | L1: YLD_YTM_ask | M1: DUR_MID | N1: rtg_sp | O1: rtg_moody | P1: rtg_fitch | Q1: industry_subgroup | R1: PAIS | S1: crncy | T1: callable | U1: NXT_CALL_DT | V1: payment_rank | W1: Monto Compra | X1: Costo | Y1: status | Z1: VP | AA1: MTM | AB1: MTM trib | AC1: VPxYTM | AD1: VPxDur | AE1: Rt % año | AF1: INTERESES x AÑO | AG1: FECHA VENTA
A2: HSBC | B2: US46625HLL23 | C2: JPMORGAN CHASE | D2: 23 | E2: 4.95 | F2: 01-06-2045 | G2: 93.527 | I2: 94.503 | J2: 94.173 | K2: 0.052562836 | L2: 5.4404152 | M2: 12.378987 | N2: BBB+ | O2: A3 | P2: A | Q2: Diversified Banking Inst | R2: US | S2: USD | T2: AT MATURITY | V2: Subordinated | W2: 467635 | X2: 467635 | Z2: 34 | AA2: -0.69708492 | AB2: -0.00029450144 | AC2: 2561701.1 | AD2: 5828831.7 | AE2: -0.0035283929 | AF2: =+D2*E2/100/365*15 -> 0.046787671 | AG2: 46037
A3: HSBC | B3: US172967KR13 | C3: CITIGROUP | D3: 23 | E3: 4.75 | F3: 18-05-2046 | G3: 88.4031 | I3: 87.986 | J3: 88.298 | K3: 0.053795103 | L3: 5.7302765 | M3: 12.659062 | N3: BBB | O3: Baa2 | P3: BBB+ | Q3: Diversified Banking Inst | R3: US | S3: USD | T3: AT MATURITY | V3: Subordinated | W3: 884031 | X3: 884031 | Z3: 34 | AA3: 1.3181242 | AB3: 0.00055687546 | AC3: 5059719.5 | AD3: 11177698 | AE3: 0.003529288 | AF3: =+D3*E3/100/365*15 -> 0.04489726 | AG3: 46037
A4: MS-K | B4: US05567SAA06 | C4: BNSF FUNDING TRUST I | D4: 23 | E4: 6.613 | F4: 15-12-2055 | G4: 115.09 | H4: 94.553 | I4: 100.175 | J4: 100 | K4: 0.06613 | L4: 7.2589283 | M4: 0.0055555556 | N4: A | O4: Baa2 | P4: #N/A N/A | Q4: Transport-Rail | R4: US | S4: USD | T4: CALLABLE | V4: Jr Subordinated | W4: 195653 | X4: 195653 | Z4: 34 | AA4: -0.12568652 | AB4: -5.3099503e-05 | AC4: 1234017.8 | AD4: 944.44444 | AE4: -0.0015205491 | AF4: =+D4*E4/100/365*16 -> 0.066673534 | AG4: 46037
A5: CS-M | B5: US912810TJ79 | C5: US TREASURY N/B | D5: 23 | E5: 3 | F5: 15-08-2052 | G5: 85.042969 | H5: 82.953125 | I5: 71.773438 | J5: 71.640625 | K5: 0.041486603 | L5: 4.8671563 | M5: 16.559258 | N5: #N/A N/A | O5: Aaa | P5: #N/A N/A | Q5: Sovereign | R5: US | S5: USD | T5: NORMAL | V5: Unsecured | W5: 1360687.5 | X5: 1360687.5 | Z5: 34 | AA5: -1.2905313e-05 | AB5: -5.4521811e-09 | AC5: 5631299.8 | AD5: 19159061 | AE5: 0.0063387075 | AF5: 48000
A6: UBS-H | B6: US61746BEG77 | C6: MORGAN STANLEY | D6: 23 | E6: 4.375 | F6: 22-01-2047 | G6: 89.358 | H6: 85.29 | I6: 86.597 | J6: 86.251 | K6: 0.05072405 | L6: 5.4002231 | M6: 13.066472 | N6: A- | O6: A1 | P6: A+ | Q6: Diversified Banking Inst | R6: US | S6: USD | T6: AT MATURITY | V6: Sr Unsecured | W6: 893580 | X6: 893580 | Z6: 34 | AA6: -3.3620617e-05 | AB6: -1.4203894e-08 | AC6: 4657746.4 | AD6: 11269963 | AE6: -0.0038720652 | AF6: 43750 | AG6: 46059
A7: CS-M | B7: US912810TJ79 | C7: US TREASURY N/B | D7: 23 | E7: 3 | F7: 15-08-2052 | G7: 85.042969 | H7: 82.953125 | I7: 71.773438 | J7: 73.84375 | K7: 0.040626322 | L7: 4.8711261 | M7: 16.504394 | N7: #N/A N/A | O7: Aaa | P7: #N/A N/A | Q7: Sovereign | R7: US | S7: USD | T7: NORMAL | V7: Unsecured | W7: 1105558.6 | X7: 1105558.6 | Z7: 34 | AA7: 0.00020117105 | AB7: 8.4989882e-08 | AC7: 4676128.9 | AD7: 15843703 | AE7: 0.024344311 | AF7: 39000 | AG7: 46077
A8: CS-MCHT | B8: US912810TJ79 | C8: US TREASURY N/B | D8: 23 | E8: 3 | F8: 15-08-2052 | G8: 85.81821 | H8: 82.953125 | I8: 71.773438 | J8: 73.84375 | K8: 0.040626322 | L8: 4.8711261 | M8: 16.504394 | N8: #N/A N/A | O8: Aaa | P8: #N/A N/A | Q8: Sovereign | R8: US | S8: USD | T8: NORMAL | V8: Unsecured | W8: 600727.47 | X8: 600727.47 | Z8: 34 | AA8: 0.00020117105 | AB8: 8.4989882e-08 | AC8: 2517915.5 | AD8: 8531224.5 | AE8: 0.024124396 | AF8: 21000 | AG8: 46077
A9: DB | B9: US46625HLL23 | C9: JPMORGAN CHASE | D9: 23 | E9: 4.95 | F9: 01-06-2045 | G9: 94.93 | I9: 94.503 | J9: 93.047 | K9: 0.053198921 | L9: 5.435265 | M9: 12.300837 | N9: BBB+ | O9: A3 | P9: A | Q9: Diversified Banking Inst | R9: US | S9: USD | T9: AT MATURITY | V9: Subordinated | W9: 949300 | X9: 949300 | Z9: 34 | AA9: -0.00014147866 | AB9: -5.9771299e-08 | AC9: 5057351 | AD9: 11445560 | AE9: -0.015337617 | AF9: 49500 | AG9: 46091
A10: CS-MChT | B10: US912797SX61 | C10: TREASURY BILLS | D10: 23 | E10: 0 | F10: 46177 | G10: 99.07175 | I10: 98.5194 | J10: 99.1517 | K10: 0.03695839 | L10: 3.6615324 | M10: 0.30684932 | N10: #N/A N/A | O10: #N/A N/A | P10: #N/A N/A | Q10: Sovereign | R10: US | S10: USD | T10: NORMAL | V10: Unsecured | W10: 614244.85 | X10: 614244.85 | Z10: 34 | AA10: 6.144022e-05 | AB10: 2.5957e-08 | AC10: 2249077.4 | AD10: 188480.61 | AE10: 0.0055752523 | AF10: 22701.501
Z40: =SUM(Z2:Z39) -> 306 | AA40: =SUM(AA2:AA39) -> 0.49562854 | AB40: =SUM(AB2:AB39) -> 0.00020939102 | AF40: =SUM(AF2:AF39) -> 223951.66

Sheet JEBPOS
F1: MONEDAS
A5: REALIZADAS
R7: DB | S7: UBS | T7: SB | U7: SAXO | X7: HEDGE
A8: Fecha Aper | B8: Fecha Cierre | C8: Contraparte | D8: ticker | E8: País | F8: Monto | G8: Precio Inicial | H8: Precio Cierre | I8: MTM | J8: Rent | K8: Garantía | L8: Plazo | M8: Fix | N8: Settelment
AF21: DB-KIF | AG21: UBS-MON | AH21: UBS-KIF | AI21: SAXO-MON | AJ21: SAXO-KIF | AK21: Chile-Mon
I22: =SUM(I9:I21) -> 0 | J22: =SUM(J9:J21) -> 0 | AE22: USDZAR | AF22: 0.15 | AG22: 0.09 | AH22: 0.09 | AI22: 0.15 | AJ22: 0.15 | AK22: 0.15
H23: SAXO | I23: =SUMIF(C9:C21,"saxo",I9:I21) -> 0 | AE23: EURUSD | AF23: 0.07 | AG23: 0.07 | AH23: 0.07 | AI23: 0.07 | AJ23: 0.07 | AK23: 0.07
H24: SCHWAB | I24: =SUMIF(C9:C21,"schwab",I9:I21) -> 0 | AE24: AUDUSD | AF24: 0.09 | AG24: 0.09 | AH24: 0.09 | AI24: 0.09 | AJ24: 0.09 | AK24: 0.09
H25: CHILE | I25: =SUMIF(C9:C21,"CHILE",I9:I21) -> 0 | AE25: USDJPY | AF25: 0.07 | AG25: 0.07 | AH25: 0.07 | AI25: 0.07 | AJ25: 0.07 | AK25: 0.07
H26: UBS | I26: =SUMIF(C9:C21,"UBS",I9:I21) -> 0 | AE26: GBPUSD | AF26: 0.07 | AG26: 0.07 | AH26: 0.07 | AI26: 0.07 | AJ26: 0.07 | AK26: 0.07
H27: SB | I27: =SUMIF(C9:C21,"SB",I9:I21) -> 0 | AE27: XAUUSD | AF27: 0.12 | AG27: 0.15 | AH27: 0.15 | AI27: 0.12 | AJ27: 0.12 | AK27: 0.12
A28: TRADING | AE28: USDCLP | AF28: 0.15 | AG28: 0.11 | AH28: 0.11 | AI28: 0.15 | AJ28: 0.15 | AK28: 0.15
AE29: USDMXN | AF29: 0.15 | AG29: 0.09 | AH29: 0.09 | AI29: 0.15 | AJ29: 0.15 | AK29: 0.15
R30: MTM | Y30: NOCIONAL | AE30: USDBRL | AF30: 0.15 | AG30: 0.11 | AH30: 0.11 | AI30: 0.15 | AJ30: 0.15 | AK30: 0.15 | AM30: RIESGO
A31: FECHA | B31: Contraparte | C31: Pos | D31: ticker | E31: País | F31: Monto | G31: Precio Inicial | H31: Precio Cierre | I31: MTM | J31: Rent | K31: Garantía | L31: Plazo | M31: Plazo | N31: Fix/Exp | O31: Val Date/Settlement | R31: DB-MON | S31: UBS-MON | T31: UBS-KIF | U31: SAXO-MON | V31: SAXO-KIF | W31: Chile-Mon | Y31: DB-MON | Z31: UBS-MON | AA31: UBS-KIF | AB31: SAXO-MON | AC31: SAXO-KIF | AD31: Chile-Mon | AF31: DB-KIF | AG31: UBS-MON | AH31: UBS-KIF | AI31: SAXO-MON | AJ31: SAXO-KIF | AK31: Chile-Mon | AM31: DB | AN31: UBS | AO31: SB | AP31: SAXO
D32: USDCLP | H32: ='ppal B'!F2 -> 898.375 | I32: =+((F32*(H32-G32)))/H32 -> 0 | J32: =IF(G32="","",(H32-G32)/G32) | K32: =ABS(F32) -> 0 | M32: =IF(N32="","",N32-TODAY()) | R32: =IF($B32="DB-KIF",$I32,0) -> 0 | S32: =IF($B32="UBS-MON",$I32,0) -> 0 | T32: =IF($B32="UBS-KIF",$I32,0) -> 0 | U32: =IF($B32="SAXO-MON",$I32,0) -> 0 | V32: =IF($B32="SAXO-KIF",$I32,0) -> 0 | W32: =IF($B32="chile",$I32,0) -> 0 | Y32: =IF(R32<>0,$F32,0) -> 0 | Z32: =IF(S32<>0,$F32,0) -> 0 | AA32: =IF(T32<>0,$F32,0) -> 0 | AB32: =IF(U32<>0,$F32,0) -> 0 | AC32: =IF(V32<>0,$F32,0) -> 0 | AD32: =IF(W32<>0,$F32,0) -> 0 | AF32: =+$AF$28*Y32 -> 0 | AG32: =+$AG$28*Z32 -> 0 | AH32: =+$AH$28*AA32 -> 0 | AI32: =+$AI$28*AB32 -> 0 | AJ32: =+$AJ$28*AC32 -> 0 | AK32: =+$AK$28*AD32 -> 0 | AM32: =+AF32-R32 -> 0 | AN32: =+AG32-S32 -> 0 | AO32: =+AH32-T32 -> 0 | AP32: =+AI32-U32 -> 0
D33: USDCLP | H33: =+H32 -> 898.375 | I33: =+((F33*(H33-G33)))/H33 -> 0 | J33: =IF(G33="","",(H33-G33)/G33) | K33: =ABS(F33) -> 0 | M33: =IF(N33="","",N33-TODAY()) | R33: =IF($B33="DB-KIF",$I33,0) -> 0 | S33: =IF($B33="UBS-MON",$I33,0) -> 0 | T33: =IF($B33="UBS-KIF",$I33,0) -> 0 | U33: =IF($B33="SAXO-MON",$I33,0) -> 0 | V33: =IF($B33="SAXO-KIF",$I33,0) -> 0 | W33: =IF($B33="chile",$I33,0) -> 0 | Y33: =IF(R33<>0,$F33,0) -> 0 | Z33: =IF(S33<>0,$F33,0) -> 0 | AA33: =IF(T33<>0,$F33,0) -> 0 | AB33: =IF(U33<>0,$F33,0) -> 0 | AC33: =IF(V33<>0,$F33,0) -> 0 | AD33: =IF(W33<>0,$F33,0) -> 0 | AF33: =+$AF$28*Y33 -> 0 | AG33: =+$AG$28*Z33 -> 0 | AH33: =+$AH$28*AA33 -> 0 | AI33: =+$AI$28*AB33 -> 0 | AJ33: =+$AJ$28*AC33 -> 0 | AK33: =+$AK$28*AD33 -> 0 | AM33: =+AF33-R33 -> 0 | AN33: =+AG33-S33 -> 0 | AO33: =+AH33-T33 -> 0 | AP33: =+AI33-U33 -> 0
D34: USDCLP | H34: =+H33 -> 898.375 | I34: =+((F34*(H34-G34)))/H34 -> 0 | J34: =IF(G34="","",(H34-G34)/G34) | K34: =ABS(F34) -> 0 | M34: =IF(N34="","",N34-TODAY()) | R34: =IF($B34="DB-KIF",$I34,0) -> 0 | S34: =IF($B34="UBS-MON",$I34,0) -> 0 | T34: =IF($B34="UBS-KIF",$I34,0) -> 0 | U34: =IF($B34="SAXO-MON",$I34,0) -> 0 | V34: =IF($B34="SAXO-KIF",$I34,0) -> 0 | W34: =IF($B34="chile",$I34,0) -> 0 | Y34: =IF(R34<>0,$F34,0) -> 0 | Z34: =IF(S34<>0,$F34,0) -> 0 | AA34: =IF(T34<>0,$F34,0) -> 0 | AB34: =IF(U34<>0,$F34,0) -> 0 | AC34: =IF(V34<>0,$F34,0) -> 0 | AD34: =IF(W34<>0,$F34,0) -> 0 | AF34: =+$AF$28*Y34 -> 0 | AG34: =+$AG$28*Z34 -> 0 | AH34: =+$AH$28*AA34 -> 0 | AI34: =+$AI$28*AB34 -> 0 | AJ34: =+$AJ$28*AC34 -> 0 | AK34: =+$AK$28*AD34 -> 0 | AM34: =+AF34-R34 -> 0 | AN34: =+AG34-S34 -> 0 | AO34: =+AH34-T34 -> 0 | AP34: =+AI34-U34 -> 0
D35: USDCLP | H35: =+H34 -> 898.375 | I35: =+((F35*(H35-G35)))/H35 -> 0 | J35: =IF(G35="","",(H35-G35)/G35) | K35: =ABS(F35) -> 0 | M35: =IF(N35="","",N35-TODAY()) | R35: =IF($B35="DB-KIF",$I35,0) -> 0 | S35: =IF($B35="UBS-MON",$I35,0) -> 0 | T35: =IF($B35="UBS-KIF",$I35,0) -> 0 | U35: =IF($B35="SAXO-MON",$I35,0) -> 0 | V35: =IF($B35="SAXO-KIF",$I35,0) -> 0 | W35: =IF($B35="chile",$I35,0) -> 0 | Y35: =IF(R35<>0,$F35,0) -> 0 | Z35: =IF(S35<>0,$F35,0) -> 0 | AA35: =IF(T35<>0,$F35,0) -> 0 | AB35: =IF(U35<>0,$F35,0) -> 0 | AC35: =IF(V35<>0,$F35,0) -> 0 | AD35: =IF(W35<>0,$F35,0) -> 0 | AF35: =+$AF$28*Y35 -> 0 | AG35: =+$AG$28*Z35 -> 0 | AH35: =+$AH$28*AA35 -> 0 | AI35: =+$AI$28*AB35 -> 0 | AJ35: =+$AJ$28*AC35 -> 0 | AK35: =+$AK$28*AD35 -> 0 | AM35: =+AF35-R35 -> 0 | AN35: =+AG35-S35 -> 0 | AO35: =+AH35-T35 -> 0 | AP35: =+AI35-U35 -> 0
D36: USDCLP | H36: =+H35 -> 898.375 | I36: =+((F36*(H36-G36)))/H36 -> 0 | J36: =IF(G36="","",(H36-G36)/G36) | K36: =ABS(F36) -> 0 | M36: =IF(N36="","",N36-TODAY()) | R36: =IF($B36="DB-KIF",$I36,0) -> 0 | S36: =IF($B36="UBS-MON",$I36,0) -> 0 | T36: =IF($B36="UBS-KIF",$I36,0) -> 0 | U36: =IF($B36="SAXO-MON",$I36,0) -> 0 | V36: =IF($B36="SAXO-KIF",$I36,0) -> 0 | W36: =IF($B36="chile",$I36,0) -> 0 | Y36: =IF(R36<>0,$F36,0) -> 0 | Z36: =IF(S36<>0,$F36,0) -> 0 | AA36: =IF(T36<>0,$F36,0) -> 0 | AB36: =IF(U36<>0,$F36,0) -> 0 | AC36: =IF(V36<>0,$F36,0) -> 0 | AD36: =IF(W36<>0,$F36,0) -> 0 | AF36: =+$AF$28*Y36 -> 0 | AG36: =+$AG$28*Z36 -> 0 | AH36: =+$AH$28*AA36 -> 0 | AI36: =+$AI$28*AB36 -> 0 | AJ36: =+$AJ$28*AC36 -> 0 | AK36: =+$AK$28*AD36 -> 0 | AM36: =+AF36-R36 -> 0 | AN36: =+AG36-S36 -> 0 | AO36: =+AH36-T36 -> 0 | AP36: =+AI36-U36 -> 0
D37: USDCLP | H37: =+H36 -> 898.375 | I37: =+((F37*(H37-G37)))/H37 -> 0 | J37: =IF(G37="","",(H37-G37)/G37) | K37: =ABS(F37) -> 0 | M37: =IF(N37="","",N37-TODAY()) | R37: =IF($B37="DB-KIF",$I37,0) -> 0 | S37: =IF($B37="UBS-MON",$I37,0) -> 0 | T37: =IF($B37="UBS-KIF",$I37,0) -> 0 | U37: =IF($B37="SAXO-MON",$I37,0) -> 0 | V37: =IF($B37="SAXO-KIF",$I37,0) -> 0 | W37: =IF($B37="chile",$I37,0) -> 0 | Y37: =IF(R37<>0,$F37,0) -> 0 | Z37: =IF(S37<>0,$F37,0) -> 0 | AA37: =IF(T37<>0,$F37,0) -> 0 | AB37: =IF(U37<>0,$F37,0) -> 0 | AC37: =IF(V37<>0,$F37,0) -> 0 | AD37: =IF(W37<>0,$F37,0) -> 0 | AF37: =+$AF$28*Y37 -> 0 | AG37: =+$AG$28*Z37 -> 0 | AH37: =+$AH$28*AA37 -> 0 | AI37: =+$AI$28*AB37 -> 0 | AJ37: =+$AJ$28*AC37 -> 0 | AK37: =+$AK$28*AD37 -> 0 | AM37: =+AF37-R37 -> 0 | AN37: =+AG37-S37 -> 0 | AO37: =+AH37-T37 -> 0 | AP37: =+AI37-U37 -> 0
D38: USDCLP | H38: =+H37 -> 898.375 | I38: =+((F38*(H38-G38)))/H38 -> 0 | J38: =IF(G38="","",(H38-G38)/G38) | K38: =ABS(F38) -> 0 | M38: =IF(N38="","",N38-TODAY()) | R38: =IF($B38="DB-KIF",$I38,0) -> 0 | S38: =IF($B38="UBS-MON",$I38,0) -> 0 | T38: =IF($B38="UBS-KIF",$I38,0) -> 0 | U38: =IF($B38="SAXO-MON",$I38,0) -> 0 | V38: =IF($B38="SAXO-KIF",$I38,0) -> 0 | W38: =IF($B38="chile",$I38,0) -> 0 | Y38: =IF(R38<>0,$F38,0) -> 0 | Z38: =IF(S38<>0,$F38,0) -> 0 | AA38: =IF(T38<>0,$F38,0) -> 0 | AB38: =IF(U38<>0,$F38,0) -> 0 | AC38: =IF(V38<>0,$F38,0) -> 0 | AD38: =IF(W38<>0,$F38,0) -> 0 | AF38: =+$AF$28*Y38 -> 0 | AG38: =+$AG$28*Z38 -> 0 | AH38: =+$AH$28*AA38 -> 0 | AI38: =+$AI$28*AB38 -> 0 | AJ38: =+$AJ$28*AC38 -> 0 | AK38: =+$AK$28*AD38 -> 0 | AM38: =+AF38-R38 -> 0 | AN38: =+AG38-S38 -> 0 | AO38: =+AH38-T38 -> 0 | AP38: =+AI38-U38 -> 0
D39: USDCLP | H39: =+H38 -> 898.375 | I39: =+((F39*(H39-G39)))/H39 -> 0 | J39: =IF(G39="","",(H39-G39)/G39) | K39: =ABS(F39) -> 0 | M39: =IF(N39="","",N39-TODAY()) | R39: =IF($B39="DB-KIF",$I39,0) -> 0 | S39: =IF($B39="UBS-MON",$I39,0) -> 0 | T39: =IF($B39="UBS-KIF",$I39,0) -> 0 | U39: =IF($B39="SAXO-MON",$I39,0) -> 0 | V39: =IF($B39="SAXO-KIF",$I39,0) -> 0 | W39: =IF($B39="chile",$I39,0) -> 0 | Y39: =IF(R39<>0,$F39,0) -> 0 | Z39: =IF(S39<>0,$F39,0) -> 0 | AA39: =IF(T39<>0,$F39,0) -> 0 | AB39: =IF(U39<>0,$F39,0) -> 0 | AC39: =IF(V39<>0,$F39,0) -> 0 | AD39: =IF(W39<>0,$F39,0) -> 0 | AF39: =+$AF$28*Y39 -> 0 | AG39: =+$AG$28*Z39 -> 0 | AH39: =+$AH$28*AA39 -> 0 | AI39: =+$AI$28*AB39 -> 0 | AJ39: =+$AJ$28*AC39 -> 0 | AK39: =+$AK$28*AD39 -> 0 | AM39: =+AF39-R39 -> 0 | AN39: =+AG39-S39 -> 0 | AO39: =+AH39-T39 -> 0 | AP39: =+AI39-U39 -> 0
D40: USDCLP | H40: =+H39 -> 898.375 | I40: =+((F40*(H40-G40)))/H40 -> 0 | J40: =IF(G40="","",(H40-G40)/G40) | K40: =ABS(F40) -> 0 | M40: =IF(N40="","",N40-TODAY()) | R40: =IF($B40="DB-KIF",$I40,0) -> 0 | S40: =IF($B40="UBS-MON",$I40,0) -> 0 | T40: =IF($B40="UBS-KIF",$I40,0) -> 0 | U40: =IF($B40="SAXO-MON",$I40,0) -> 0 | V40: =IF($B40="SAXO-KIF",$I40,0) -> 0 | W40: =IF($B40="chile",$I40,0) -> 0 | Y40: =IF(R40<>0,$F40,0) -> 0 | Z40: =IF(S40<>0,$F40,0) -> 0 | AA40: =IF(T40<>0,$F40,0) -> 0 | AB40: =IF(U40<>0,$F40,0) -> 0 | AC40: =IF(V40<>0,$F40,0) -> 0 | AD40: =IF(W40<>0,$F40,0) -> 0 | AF40: =+$AF$28*Y40 -> 0 | AG40: =+$AG$28*Z40 -> 0 | AH40: =+$AH$28*AA40 -> 0 | AI40: =+$AI$28*AB40 -> 0 | AJ40: =+$AJ$28*AC40 -> 0 | AK40: =+$AK$28*AD40 -> 0 | AM40: =+AF40-R40 -> 0 | AN40: =+AG40-S40 -> 0 | AO40: =+AH40-T40 -> 0 | AP40: =+AI40-U40 -> 0
D41: USDCLP | H41: =+H40 -> 898.375 | I41: =+((F41*(H41-G41)))/H41 -> 0 | J41: =IF(G41="","",(H41-G41)/G41) | K41: =ABS(F41) -> 0 | M41: =IF(N41="","",N41-TODAY()) | R41: =IF($B41="DB-KIF",$I41,0) -> 0 | S41: =IF($B41="UBS-MON",$I41,0) -> 0 | T41: =IF($B41="UBS-KIF",$I41,0) -> 0 | U41: =IF($B41="SAXO-MON",$I41,0) -> 0 | V41: =IF($B41="SAXO-KIF",$I41,0) -> 0 | W41: =IF($B41="chile",$I41,0) -> 0 | Y41: =IF(R41<>0,$F41,0) -> 0 | Z41: =IF(S41<>0,$F41,0) -> 0 | AA41: =IF(T41<>0,$F41,0) -> 0 | AB41: =IF(U41<>0,$F41,0) -> 0 | AC41: =IF(V41<>0,$F41,0) -> 0 | AD41: =IF(W41<>0,$F41,0) -> 0 | AF41: =+$AF$28*Y41 -> 0 | AG41: =+$AG$28*Z41 -> 0 | AH41: =+$AH$28*AA41 -> 0 | AI41: =+$AI$28*AB41 -> 0 | AJ41: =+$AJ$28*AC41 -> 0 | AK41: =+$AK$28*AD41 -> 0 | AM41: =+AF41-R41 -> 0 | AN41: =+AG41-S41 -> 0 | AO41: =+AH41-T41 -> 0 | AP41: =+AI41-U41 -> 0
D42: USDCLP | H42: =+H41 -> 898.375 | I42: =+((F42*(H42-G42)))/H42 -> 0 | J42: =IF(G42="","",(H42-G42)/G42) | K42: =ABS(F42) -> 0 | M42: =IF(N42="","",N42-TODAY()) | R42: =IF($B42="DB-KIF",$I42,0) -> 0 | S42: =IF($B42="UBS-MON",$I42,0) -> 0 | T42: =IF($B42="UBS-KIF",$I42,0) -> 0 | U42: =IF($B42="SAXO-MON",$I42,0) -> 0 | V42: =IF($B42="SAXO-KIF",$I42,0) -> 0 | W42: =IF($B42="chile",$I42,0) -> 0 | Y42: =IF(R42<>0,$F42,0) -> 0 | Z42: =IF(S42<>0,$F42,0) -> 0 | AA42: =IF(T42<>0,$F42,0) -> 0 | AB42: =IF(U42<>0,$F42,0) -> 0 | AC42: =IF(V42<>0,$F42,0) -> 0 | AD42: =IF(W42<>0,$F42,0) -> 0 | AF42: =+$AF$28*Y42 -> 0 | AG42: =+$AG$28*Z42 -> 0 | AH42: =+$AH$28*AA42 -> 0 | AI42: =+$AI$28*AB42 -> 0 | AJ42: =+$AJ$28*AC42 -> 0 | AK42: =+$AK$28*AD42 -> 0 | AM42: =+AF42-R42 -> 0 | AN42: =+AG42-S42 -> 0 | AO42: =+AH42-T42 -> 0 | AP42: =+AI42-U42 -> 0
D43: USDCLP | H43: =+H42 -> 898.375 | I43: =+((F43*(H43-G43)))/H43 -> 0 | J43: =IF(G43="","",(H43-G43)/G43) | K43: =ABS(F43) -> 0 | M43: =IF(N43="","",N43-TODAY()) | R43: =IF($B43="DB-KIF",$I43,0) -> 0 | S43: =IF($B43="UBS-MON",$I43,0) -> 0 | T43: =IF($B43="UBS-KIF",$I43,0) -> 0 | U43: =IF($B43="SAXO-MON",$I43,0) -> 0 | V43: =IF($B43="SAXO-KIF",$I43,0) -> 0 | W43: =IF($B43="chile",$I43,0) -> 0 | Y43: =IF(R43<>0,$F43,0) -> 0 | Z43: =IF(S43<>0,$F43,0) -> 0 | AA43: =IF(T43<>0,$F43,0) -> 0 | AB43: =IF(U43<>0,$F43,0) -> 0 | AC43: =IF(V43<>0,$F43,0) -> 0 | AD43: =IF(W43<>0,$F43,0) -> 0 | AF43: =+$AF$28*Y43 -> 0 | AG43: =+$AG$28*Z43 -> 0 | AH43: =+$AH$28*AA43 -> 0 | AI43: =+$AI$28*AB43 -> 0 | AJ43: =+$AJ$28*AC43 -> 0 | AK43: =+$AK$28*AD43 -> 0 | AM43: =+AF43-R43 -> 0 | AN43: =+AG43-S43 -> 0 | AO43: =+AH43-T43 -> 0 | AP43: =+AI43-U43 -> 0
D44: USDCLP | H44: =+H43 -> 898.375 | I44: =+((F44*(H44-G44)))/H44 -> 0 | J44: =IF(G44="","",(H44-G44)/G44) | K44: =ABS(F44) -> 0 | M44: =IF(N44="","",N44-TODAY()) | R44: =IF($B44="DB-KIF",$I44,0) -> 0 | S44: =IF($B44="UBS-MON",$I44,0) -> 0 | T44: =IF($B44="UBS-KIF",$I44,0) -> 0 | U44: =IF($B44="SAXO-MON",$I44,0) -> 0 | V44: =IF($B44="SAXO-KIF",$I44,0) -> 0 | W44: =IF($B44="chile",$I44,0) -> 0 | Y44: =IF(R44<>0,$F44,0) -> 0 | Z44: =IF(S44<>0,$F44,0) -> 0 | AA44: =IF(T44<>0,$F44,0) -> 0 | AB44: =IF(U44<>0,$F44,0) -> 0 | AC44: =IF(V44<>0,$F44,0) -> 0 | AD44: =IF(W44<>0,$F44,0) -> 0 | AF44: =+$AF$28*Y44 -> 0 | AG44: =+$AG$28*Z44 -> 0 | AH44: =+$AH$28*AA44 -> 0 | AI44: =+$AI$28*AB44 -> 0 | AJ44: =+$AJ$28*AC44 -> 0 | AK44: =+$AK$28*AD44 -> 0 | AM44: =+AF44-R44 -> 0 | AN44: =+AG44-S44 -> 0 | AO44: =+AH44-T44 -> 0 | AP44: =+AI44-U44 -> 0
... D49: USDCLP | H49: =+H48 -> 898.375 | I49: =+((F49*(H49-G49)))/H49 -> 0 | J49: =IF(G49="","",(H49-G49)/G49) | K49: =ABS(F49) -> 0 | M49: =IF(N49="","",N49-TODAY()) | R49: =IF($B49="DB-KIF",$I49,0) -> 0 | S49: =IF($B49="UBS-MON",$I49,0) -> 0 | T49: =IF($B49="UBS-KIF",$I49,0) -> 0 | U49: =IF($B49="SAXO-MON",$I49,0) -> 0 | V49: =IF($B49="SAXO-KIF",$I49,0) -> 0 | W49: =IF($B49="chile",$I49,0) -> 0 | Y49: =IF(R49<>0,$F49,0) -> 0 | Z49: =IF(S49<>0,$F49,0) -> 0 | AA49: =IF(T49<>0,$F49,0) -> 0 | AB49: =IF(U49<>0,$F49,0) -> 0 | AC49: =IF(V49<>0,$F49,0) -> 0 | AD49: =IF(W49<>0,$F49,0) -> 0 | AF49: =+$AF$28*Y49 -> 0 | AG49: =+$AG$28*Z49 -> 0 | AH49: =+$AH$28*AA49 -> 0 | AI49: =+$AI$28*AB49 -> 0 | AJ49: =+$AJ$28*AC49 -> 0 | AK49: =+$AK$28*AD49 -> 0 | AM49: =+AF49-R49 -> 0 | AN49: =+AG49-S49 -> 0 | AO49: =+AH49-T49 -> 0 | AP49: =+AI49-U49 -> 0
D50: USDCLP | H50: =+H49 -> 898.375 | I50: =+IF(H50>G50,(H50-G50)*F50,0)/H50 -> 0 | J50: =IF(G50="","",(H50-G50)/G50) | K50: =IF(I50<>0,F50,0) -> 0 | M50: =IF(N50="","",N50-TODAY())
D51: CALL | H51: =+H50 -> 898.375 | I51: =+IF(H51>G51,(H51-G51)*F51,0)/H51 -> 0 | J51: =IF(G51="","",(H51-G51)/G51) | K51: =IF(I51<>0,F51,0) -> 0 | M51: =IF(N51="","",N51-TODAY())
D52: PUT | H52: =+H51 -> 898.375 | I52: =+IF(H52<G52,-(H52-G52)*F52,0)/H52 -> 0 | J52: =IF(G52="","",(H52-G52)/G52) | K52: =IF(I52<>0,F52,0) -> 0 | M52: =IF(N52="","",N52-TODAY())
D53: PUT | H53: =+H52 -> 898.375 | I53: =+IF(H53<G53,-(H53-G53)*F53,0)/H53 -> 0 | J53: =IF(G53="","",(H53-G53)/G53) | K53: =IF(I53<>0,F53,0) -> 0 | M53: =IF(N53="","",N53-TODAY())
D54: PUT | H54: =+H53 -> 898.375 | I54: =+IF(H54<G54,-(H54-G54)*F54,0)/H54 -> 0 | J54: =IF(G54="","",(H54-G54)/G54) | K54: =IF(I54<>0,F54,0) -> 0 | M54: =IF(N54="","",N54-TODAY())
H55: =+H54 -> 898.375
H56: =+H54 -> 898.375 | I56: =+((F56*(H56-G56)))/H56 -> 0 | J56: =IF(G56="","",(H56-G56)/G56) | K56: =ABS(F56) -> 0 | M56: =IF(N56="","",N56-TODAY()) | R56: =IF($B56="DB-KIF",$I56,0) -> 0 | S56: =IF($B56="UBS-MON",$I56,0) -> 0 | T56: =IF($B56="UBS-KIF",$I56,0) -> 0 | U56: =IF($B56="SAXO-MON",$I56,0) -> 0 | V56: =IF($B56="SAXO-KIF",$I56,0) -> 0 | W56: =IF($B56="chile",$I56,0) -> 0 | Y56: =IF(R56<>0,$F56,0) -> 0 | Z56: =IF(S56<>0,$F56,0) -> 0 | AA56: =IF(T56<>0,$F56,0) -> 0 | AB56: =IF(U56<>0,$F56,0) -> 0 | AC56: =IF(V56<>0,$F56,0) -> 0 | AD56: =IF(W56<>0,$F56,0) -> 0 | AF56: =+$AF$28*Y56 -> 0 | AG56: =+$AG$28*Z56 -> 0 | AH56: =+$AH$28*AA56 -> 0 | AI56: =+$AI$28*AB56 -> 0 | AJ56: =+$AJ$28*AC56 -> 0 | AK56: =+$AK$28*AD56 -> 0 | AM56: =+AF56-R56 -> 0 | AN56: =+AG56-S56 -> 0 | AO56: =+AH56-T56 -> 0 | AP56: =+AI56-U56 -> 0
E58: NDF | F58: =SUM(F32:F49) -> 0 | H58: Resultado USD | I58: =SUM(I32:I57) -> 0
E59: OPCIONES | F59: =SUM(K50:K51) -> 0
H60: HEDGE | I60: =SUMIF(B32:B57,"HEDGE",F32:F57) -> 0
E61: POS TOTAL | F61: =F58+F59 -> 0 | H61: DB | I61: =SUMIF(B32:B57,"DB",F32:F57) -> 0 | K61: 1 | L61: =SUMIF(M32:M56,K61,F32:F56) -> 0
H62: UBS | I62: =SUMIF(B32:B57,"UBS",F32:F57) -> 0 | K62: 38 | L62: =SUMIF(M32:M56,K62,F32:F56) -> 0
H63: SB | I63: =SUMIF(B32:B57,"SB",F32:F57) -> 0 | K63: 101 | L63: =SUMIF(M32:M56,K63,F32:F56) -> 0
A65: Fecha Aper | B65: Contraparte | C65: Pos | D65: ticker | E65: País | F65: Monto | G65: STRIKE | H65: Precio Cierre | I65: MTM | J65: STRIKE | K65: Exposición | L65: Exp/Fix | M65: DIAS
E84: BUZIOS USD
E86: ACTIVOS | G86: PASIVOS
E93: Total | F93: =SUM(F87:F92) -> 0 | H93: =SUM(H87:H92) -> 0
E95: POS | F95: =+F93-H93 -> 0

Sheet RIESGO
A1: 4
A3: Totales cartera (MTM firmado; short opciones = negativo)
A4: Resumen | B4: Base | C4: Vol +5 | D4: Vol +10 | E4: Vol +15 | F4: Notas
A5: MTM total (USD) | B5: =+'ppal B'!G24 -> #REF! | C5: -4690589.3 | D5: -6592029.7 | E5: -8766583.9
A6: ΔMTM vs Base (USD) | B6: 0 | C6: =C5-B5 -> #REF! | D6: =D5-B5 -> #REF! | E6: =E5-B5 -> #REF!
A7: Vega aprox (USD por 1 vol pt) | C7: =-(C6)/5 -> #REF! | D7: =-(D6)/10 -> #REF! | E7: =-(E6)/15 -> #REF! | F7: Aprox. usando ΔMTM/Δvol (positivo = corto vega si ΔMTM negativo)
A8: Resumen | B8: Base | C8: -0.02 | D8: -0.05 | E8: -0.08 | F8: Notas
A9: MTM total (USD) | B9: =+B5 -> #REF! | C9: -3358066.7 | D9: -3997702 | E9: -5082557
A10: ΔMTM vs Base (USD) | C10: =C9-B9 -> #REF! | D10: =D9-B9 -> #REF! | E10: =E9-B9 -> #REF!
A11: Delta aprox (USD por 1% pt base) | C11: =-(C10)/2 -> #REF! | D11: =-(D10)/5 -> #REF! | E11: =-(E10)/8 -> #REF!
A12: Exposición ponderada por prob. ITM (|V|×Prob ITM)
A13: Suma (USD) IMPACTOS | C13: =+C10+C6 -> #REF! | D13: =+D10+D6 -> #REF! | E13: =+E10+E6 -> #REF! | F13: Proxy de “riesgo de ejercicio”
A14: MTM total (USD) BASE | C14: =+B5 -> #REF! | D14: =+C14 -> #REF! | E14: =+D14 -> #REF!
A15: RESULTADO PRIMAS Y OTROS | C15: =+'ppal B'!C33 -> 26465.367 | D15: =+C15 -> 26465.367 | E15: =+D15 -> 26465.367
C17: =+C15+C14+C10+C6 -> #REF! | D17: =+D15+D14+D10+D6 -> #REF! | E17: =+E15+E14+E10+E6 -> #REF!
A18: Contribución por posición (selecciona escenario)
A19: Escenario seleccionado: | B19: Vol +10
A21: ID | B21: Underlying | C21: Type | D21: Δ Vol+5 (USD) | E21: Prob ITM +5 | F21: Δ Vol+10 (USD) | G21: Prob ITM +10 | H21: Δ Vol+20 (USD) | I21: Prob ITM +20
A22: FX1 | B22: USDCLP | C22: Call | D22: -48575.751 | E22: 0.26304293 | F22: -101947.09 | G22: 0.29659422 | H22: -214170.95 | I22: 0.3257598
A23: FX2 | B23: USDCLP | C23: Put | D23: -35379.328 | E23: 0.24728119 | F23: -77176.959 | G23: 0.30995695 | H23: -169630.71 | I23: 0.39558021
A24: FX3 | B24: USDCLP | C24: Call | D24: -44867.123 | E24: 0.22502126 | F24: -95945.358 | G24: 0.26248465 | H24: -205946.79 | I24: 0.29877917
A25: SPY-P25 | B25: SPY | C25: Put | D25: -27378.602 | E25: 0.14037472 | F25: -63433.337 | G25: 0.19379217 | H25: -152894.99 | I25: 0.28427258
A26: SPY-P30 | B26: SPY | C26: Put | D26: -19310.324 | E26: 0.10085476 | F26: -47000.708 | G26: 0.14985738 | H26: -121065.9 | I26: 0.23962795
A27: SPY-P35 | B27: SPY | C27: Put | D27: -12906.931 | E27: 0.069651795 | F27: -33251.767 | G27: 0.11224873 | H27: -92574.856 | I27: 0.19767334
A28: QQQ-P25 | B28: QQQ | C28: Put | D28: -34517.689 | E28: 0.18351809 | F28: -75832.589 | G28: 0.23262542 | H28: -171827.01 | I28: 0.31477784
A29: QQQ-P30 | B29: QQQ | C29: Put | D29: -26138.831 | E29: 0.14015812 | F29: -59358.061 | G29: 0.18751403 | H29: -140921.74 | I29: 0.27126578
A30: QQQ-P35 | B30: QQQ | C30: Put | D30: -18902.875 | E30: 0.1035437 | F30: -44615.535 | G30: 0.14711152 | H30: -111935.93 | I30: 0.22940804
A31: NVDA-P25 | B31: NVDA | C31: Put | D31: -53832.08 | E31: 0.37418644 | F31: -109062.4 | G31: 0.40278817 | H31: -222127.4 | I31: 0.45298738
A32: NVDA-P30 | B32: NVDA | C32: Put | D32: -49467.982 | E32: 0.35900304 | F32: -100399.41 | G32: 0.38771898 | H32: -205139.64 | I32: 0.43884432
A33: NVDA-P35 | B33: NVDA | C33: Put | D33: -45197.554 | E33: 0.34484293 | F33: -91885.381 | G33: 0.37351916 | H33: -188321.11 | I33: 0.42525073
